Workbook
Name approvedby: #REF!
Name APPROVER1: #REF!
Name APPROVER2: #REF!
Name APPROVER2A: #REF!
Name APPROVER3: #REF!
Name APPROVER3a: #REF!
Name APPROVER4: #REF!
Name APPROVER5: #REF!
Name APPROVER6: #REF!
Name APPROVER7: #REF!
Name APPROVER8: #REF!
Name CONAME: #REF!
Name EFFECTIVEDATE: #REF!
Name ISSUEDBY: #REF!
Name k: #REF!
Name supercedes: #REF!
Name title: #REF!

Sheet All
I1: =2012-17 -> 1995 | K1: =2015-23 -> 1992 | T1: =NOW() -> 46315.632 | BL1: 3 | BM1: 3 | BN1: 2 | BO1: 3 | BP1: 3 | BQ1: 3 | BR1: 3 | BS1: 2 | BT1: 3 | BU1: 1 | BV1: 3 | BW1: 2 | BX1: 3 | BY1: 2 | BZ1: 2 | CA1: 2 | CB1: 2 | CC1: 2 | CD1: 2 | CE1: 2 | CF1: 1 | CG1: 2 | CH1: 1 | CI1: 1 | CR1: =8/12 -> 0.66666667 | DB1: =6/7 -> 0.85714286
G2: 2026
B3: Count | C3: Chat Status | D3: Chat Date | E3: Name | F3: Staff ID | G3: Age | H3: Birth Year | I3: Gender | J3: Nationality | K3: Department | L3: Section Name | M3: Unit Name | N3: Sub Unit | O3: Staff Position | P3: Email Address | Q3: Employment Category | R3: Contract Expire Date | S3: Joining Date | T3: Years in PET | U3: Years of RE Experience | V3: SG | W3: Age Promoted to Staff or Principal | X3: Years in Salary Grade | Y3: Date of Appointment to Current Grade | Z3: Current Location: | AA3: Date in Position | AB3: Length in Current Assignment | AC3: Assessment Level | AD3: Last Assesment Date | AE3: Ruler Type | AF3: Potential | AG3: Background | AH3: Strength | AI3: Recommendation | AJ3: Resource/SME | AK3: Interest | AL3: Preference | AM3: Comment/Suggestion | AN3: B1 | AO3: B2 | AP3: B3 | AQ3: B4 | AR3: B5 | AS3: B6 | AT3: B7 | AU3: B8 | AV3: B9 | AW3: B10 | AX3: B11 | AY3: B12 | AZ3: K1 | BA3: K2 | BB3: K3 | BC3: K4 | BD3: K5 | BE3: P1 | BF3: P2 | BG3: P3 | BH3: P4 | BI3: P5 | BJ3: E1 | BK3: E2 | BL3: R-B1 | BM3: R-B2 | BN3: R-B3 | BO3: R-B4 | BP3: R-B5 | BQ3: R-B6 | BR3: R-B7 | BS3: R-B8 | BT3: R-B9 | BU3: R-B10 | BV3: R-B11 | BW3: R-B12 | BX3: R-K1 | BY3: R-K2 | BZ3: R-K3 | CA3: R-K4 | CB3: R-K5 | CC3: R-P1 | CD3: R-P2 | CE3: R-P3 | CF3: R-P4 | CG3: R-P5 | CH3: R-E1 | CI3: R-E2 | CJ3: G-B1 | CK3: G-B2 | CL3: G-B3 | CM3: G-B4 | CN3: G-B5 | CO3: G-B6 | CP3: G-B7 | CQ3: G-B8 | CR3: G-B9 | CS3: G-B10 | CT3: G-B11 | CU3: G-B12 | CV3: G-K1 | CW3: G-K2 | CX3: G-K3 | CY3: G-K4 | CZ3: G-K5 | DA3: G-P1 | DB3: G-P2 | DC3: G-P3 | DD3: G-P4 | DE3: G-P5 | DF3: G-E1 | DG3: G-E2 | DH3: Next Grade Base | DI3: Next Grade Keys | DJ3: Next Grade Pacing | DK3: Next Grade Emerging | DL3: Next Grade CTI | DM3: Staff Base2 | DN3: Staff Keys3 | DO3: Staff Pacing4 | DP3: Staff Emerging5 | DQ3: Staff CTI6 | DR3: Principal Base | DS3: Principal Keys | DT3: Principal Pacing | DU3: Principal Emerging | DV3: Principal CTI | DW3: Custodian Base | DX3: Custodian Keys | DY3: Custodian Pacing | DZ3: Custodian Emerging | EA3: Custodian CTI | EB3: Assesor1 | EC3: Assessor2 | ED3: Supervisor | EE3: Remarks
B4: 1 | C4: Yes | D4: 46147 | E4: Abdul Hakim bin Ameludin | F4: 1019423 | G4: =($T$1-H4)/365 -> 36.82639 | H4: 32874 | I4: M | J4: Malaysia | K4: DPE | L4: RMS | M4: SBA | N4: Cluster 2 | O4: Executive | P4: hakim.ameludin@petronas.com.my | Q4: Permanent | S4: 41674 | T4: =YEARFRAC(S4,$T$1) -> 12.711111 | U4: =Table9[[#This Row],[Years in PET]] -> 12.711111 | V4: P3 | X4: =($T$1-Table9[[#This Row],[Date of Appointment to Current Grade]])/365 -> 1.5551569 | Y4: 45748 | Z4: SBA | AA4: 45658 | AB4: =($T$1-Table9[[#This Row],[Date in Position]])/365 -> 1.8017322 | AC4: UPE | AD4: 45689 | AE4: RDP | AF4: Average | AH4: ✅ FDP + Project Maturation governance ✅ MBAL+IAM, ✅ PVT/fluid characterization | AI4: Keep track competencies agaisnt next level | AJ4: Analytical, PVT | AK4: Study , PEI, DRO Choose RDP path | AL4: TP | AN4: 2 | AO4: 1 | AP4: 1 | AQ4: 2 | AR4: 2 | AS4: 2 | AT4: 2 | AU4: 2 | AV4: 1 | AW4: 1 | AX4: 1 | AY4: 1 | AZ4: 2 | BA4: 1 | BB4: 0 | BC4: 1 | BD4: 0 | BE4: 1 | BF4: 2 | BG4: 2 | BH4: 2 | BI4: 0 | BJ4: 0 | BK4: 0 | BL4: =IF(AND(All!$V4="P1",All!$AE4="RDP"),Ruler!E$6,IF(AND(All!$V4="P2",All!$AE4="RDP"),Ruler!E$7,IF(AND(All!$V4="P3",All!$AE4="RDP"),Ruler!E$8,IF(AND(All!$V4="P4",All!$AE4="RDP"),Ruler!E$9,IF(AND(All!$V4="P5",All!$AE4="RDP"),Ruler!E$10,IF(AND(All!$V4="P6",All!$AE4="RDP"),Ruler!E$11,IF(AND(All!$V4="P7",All!$AE4="RDP"),Ruler!E$12,IF(AND(All!$V4="P8",All!$AE4="RDP"),Ruler!E$13,IF(AND(All!$V4="P9",All!$AE4="RDP"),Ruler!E$14,IF(AND(All!$V4="P1",All!$AE4="RMS"),Ruler!E$6,IF(AND(All!$V4="P2",All!$AE4="RMS"),Ruler!E$15,IF(AND(All!$V4="P3",All!$AE4="RMS"),Ruler!E$16,IF(AND(All!$V4="P4",All!$AE4="RMS"),Ruler!E$17,IF(AND(All!$V4="P5",All!$AE4="RMS"),Ruler!E$18,IF(AND(All!$V4="P6",All!$AE4="RMS"),Ruler!E$19,IF(AND(All!$V4="P7",All!$AE4="RMS"),Ruler!E$20,IF(AND(All!$V4="P8",All!$AE4="RMS"),Ruler!E$21,IF(AND(All!$V4="P9",All!$AE4="RMS"),Ruler!E$22,IF(AND(All!$V4="P1",All!$AE4="RSS"),Ruler!E$6,IF(AND(All!$V4="P2",All!$AE4="RSS"),Ruler!E$23,IF(AND(All!$V4="P3",All!$AE4="RSS"),Ruler!E$24,IF(AND(All!$V4="P4",All!$AE4="RSS"),Ruler!E$25,IF(AND(All!$V4="P5",All!$AE4="RSS"),Ruler!E$26,IF(AND(All!$V4="P6",All!$AE4="RSS"),Ruler!E$27,IF(AND(All!$V4="P7",All!$AE4="RSS"),Ruler!E$28,IF(AND(All!$V4="P8",All!$AE4="RSS"),Ruler!E$29,IF(AND(All!$V4="P9",All!$AE4="RSS"),Ruler!E$30,0))))))))))))))))))))))))))) -> 2 | BM4: =IF(AND(All!$V4="P1",All!$AE4="RDP"),Ruler!F$6,IF(AND(All!$V4="P2",All!$AE4="RDP"),Ruler!F$7,IF(AND(All!$V4="P3",All!$AE4="RDP"),Ruler!F$8,IF(AND(All!$V4="P4",All!$AE4="RDP"),Ruler!F$9,IF(AND(All!$V4="P5",All!$AE4="RDP"),Ruler!F$10,IF(AND(All!$V4="P6",All!$AE4="RDP"),Ruler!F$11,IF(AND(All!$V4="P7",All!$AE4="RDP"),Ruler!F$12,IF(AND(All!$V4="P8",All!$AE4="RDP"),Ruler!F$13,IF(AND(All!$V4="P9",All!$AE4="RDP"),Ruler!F$14,IF(AND(All!$V4="P1",All!$AE4="RMS"),Ruler!F$6,IF(AND(All!$V4="P2",All!$AE4="RMS"),Ruler!F$15,IF(AND(All!$V4="P3",All!$AE4="RMS"),Ruler!F$16,IF(AND(All!$V4="P4",All!$AE4="RMS"),Ruler!F$17,IF(AND(All!$V4="P5",All!$AE4="RMS"),Ruler!F$18,IF(AND(All!$V4="P6",All!$AE4="RMS"),Ruler!F$19,IF(AND(All!$V4="P7",All!$AE4="RMS"),Ruler!F$20,IF(AND(All!$V4="P8",All!$AE4="RMS"),Ruler!F$21,IF(AND(All!$V4="P9",All!$AE4="RMS"),Ruler!F$22,IF(AND(All!$V4="P1",All!$AE4="RSS"),Ruler!F$6,IF(AND(All!$V4="P2",All!$AE4="RSS"),Ruler!F$23,IF(AND(All!$V4="P3",All!$AE4="RSS"),Ruler!F$24,IF(AND(All!$V4="P4",All!$AE4="RSS"),Ruler!F$25,IF(AND(All!$V4="P5",All!$AE4="RSS"),Ruler!F$26,IF(AND(All!$V4="P6",All!$AE4="RSS"),Ruler!F$27,IF(AND(All!$V4="P7",All!$AE4="RSS"),Ruler!F$28,IF(AND(All!$V4="P8",All!$AE4="RSS"),Ruler!F$29,IF(AND(All!$V4="P9",All!$AE4="RSS"),Ruler!F$30,0))))))))))))))))))))))))))) -> 2 | BN4: =IF(AND(All!$V4="P1",All!$AE4="RDP"),Ruler!G$6,IF(AND(All!$V4="P2",All!$AE4="RDP"),Ruler!G$7,IF(AND(All!$V4="P3",All!$AE4="RDP"),Ruler!G$8,IF(AND(All!$V4="P4",All!$AE4="RDP"),Ruler!G$9,IF(AND(All!$V4="P5",All!$AE4="RDP"),Ruler!G$10,IF(AND(All!$V4="P6",All!$AE4="RDP"),Ruler!G$11,IF(AND(All!$V4="P7",All!$AE4="RDP"),Ruler!G$12,IF(AND(All!$V4="P8",All!$AE4="RDP"),Ruler!G$13,IF(AND(All!$V4="P9",All!$AE4="RDP"),Ruler!G$14,IF(AND(All!$V4="P1",All!$AE4="RMS"),Ruler!G$6,IF(AND(All!$V4="P2",All!$AE4="RMS"),Ruler!G$15,IF(AND(All!$V4="P3",All!$AE4="RMS"),Ruler!G$16,IF(AND(All!$V4="P4",All!$AE4="RMS"),Ruler!G$17,IF(AND(All!$V4="P5",All!$AE4="RMS"),Ruler!G$18,IF(AND(All!$V4="P6",All!$AE4="RMS"),Ruler!G$19,IF(AND(All!$V4="P7",All!$AE4="RMS"),Ruler!G$20,IF(AND(All!$V4="P8",All!$AE4="RMS"),Ruler!G$21,IF(AND(All!$V4="P9",All!$AE4="RMS"),Ruler!G$22,IF(AND(All!$V4="P1",All!$AE4="RSS"),Ruler!G$6,IF(AND(All!$V4="P2",All!$AE4="RSS"),Ruler!G$23,IF(AND(All!$V4="P3",All!$AE4="RSS"),Ruler!G$24,IF(AND(All!$V4="P4",All!$AE4="RSS"),Ruler!G$25,IF(AND(All!$V4="P5",All!$AE4="RSS"),Ruler!G$26,IF(AND(All!$V4="P6",All!$AE4="RSS"),Ruler!G$27,IF(AND(All!$V4="P7",All!$AE4="RSS"),Ruler!G$28,IF(AND(All!$V4="P8",All!$AE4="RSS"),Ruler!G$29,IF(AND(All!$V4="P9",All!$AE4="RSS"),Ruler!G$30,0))))))))))))))))))))))))))) -> 1 | BO4: =IF(AND(All!$V4="P1",All!$AE4="RDP"),Ruler!H$6,IF(AND(All!$V4="P2",All!$AE4="RDP"),Ruler!H$7,IF(AND(All!$V4="P3",All!$AE4="RDP"),Ruler!H$8,IF(AND(All!$V4="P4",All!$AE4="RDP"),Ruler!H$9,IF(AND(All!$V4="P5",All!$AE4="RDP"),Ruler!H$10,IF(AND(All!$V4="P6",All!$AE4="RDP"),Ruler!H$11,IF(AND(All!$V4="P7",All!$AE4="RDP"),Ruler!H$12,IF(AND(All!$V4="P8",All!$AE4="RDP"),Ruler!H$13,IF(AND(All!$V4="P9",All!$AE4="RDP"),Ruler!H$14,IF(AND(All!$V4="P1",All!$AE4="RMS"),Ruler!H$6,IF(AND(All!$V4="P2",All!$AE4="RMS"),Ruler!H$15,IF(AND(All!$V4="P3",All!$AE4="RMS"),Ruler!H$16,IF(AND(All!$V4="P4",All!$AE4="RMS"),Ruler!H$17,IF(AND(All!$V4="P5",All!$AE4="RMS"),Ruler!H$18,IF(AND(All!$V4="P6",All!$AE4="RMS"),Ruler!H$19,IF(AND(All!$V4="P7",All!$AE4="RMS"),Ruler!H$20,IF(AND(All!$V4="P8",All!$AE4="RMS"),Ruler!H$21,IF(AND(All!$V4="P9",All!$AE4="RMS"),Ruler!H$22,IF(AND(All!$V4="P1",All!$AE4="RSS"),Ruler!H$6,IF(AND(All!$V4="P2",All!$AE4="RSS"),Ruler!H$23,IF(AND(All!$V4="P3",All!$AE4="RSS"),Ruler!H$24,IF(AND(All!$V4="P4",All!$AE4="RSS"),Ruler!H$25,IF(AND(All!$V4="P5",All!$AE4="RSS"),Ruler!H$26,IF(AND(All!$V4="P6",All!$AE4="RSS"),Ruler!H$27,IF(AND(All!$V4="P7",All!$AE4="RSS"),Ruler!H$28,IF(AND(All!$V4="P8",All!$AE4="RSS"),Ruler!H$29,IF(AND(All!$V4="P9",All!$AE4="RSS"),Ruler!H$30,0))))))))))))))))))))))))))) -> 2 | BP4: =IF(AND(All!$V4="P1",All!$AE4="RDP"),Ruler!I$6,IF(AND(All!$V4="P2",All!$AE4="RDP"),Ruler!I$7,IF(AND(All!$V4="P3",All!$AE4="RDP"),Ruler!I$8,IF(AND(All!$V4="P4",All!$AE4="RDP"),Ruler!I$9,IF(AND(All!$V4="P5",All!$AE4="RDP"),Ruler!I$10,IF(AND(All!$V4="P6",All!$AE4="RDP"),Ruler!I$11,IF(AND(All!$V4="P7",All!$AE4="RDP"),Ruler!I$12,IF(AND(All!$V4="P8",All!$AE4="RDP"),Ruler!I$13,IF(AND(All!$V4="P9",All!$AE4="RDP"),Ruler!I$14,IF(AND(All!$V4="P1",All!$AE4="RMS"),Ruler!I$6,IF(AND(All!$V4="P2",All!$AE4="RMS"),Ruler!I$15,IF(AND(All!$V4="P3",All!$AE4="RMS"),Ruler!I$16,IF(AND(All!$V4="P4",All!$AE4="RMS"),Ruler!I$17,IF(AND(All!$V4="P5",All!$AE4="RMS"),Ruler!I$18,IF(AND(All!$V4="P6",All!$AE4="RMS"),Ruler!I$19,IF(AND(All!$V4="P7",All!$AE4="RMS"),Ruler!I$20,IF(AND(All!$V4="P8",All!$AE4="RMS"),Ruler!I$21,IF(AND(All!$V4="P9",All!$AE4="RMS"),Ruler!I$22,IF(AND(All!$V4="P1",All!$AE4="RSS"),Ruler!I$6,IF(AND(All!$V4="P2",All!$AE4="RSS"),Ruler!I$23,IF(AND(All!$V4="P3",All!$AE4="RSS"),Ruler!I$24,IF(AND(All!$V4="P4",All!$AE4="RSS"),Ruler!I$25,IF(AND(All!$V4="P5",All!$AE4="RSS"),Ruler!I$26,IF(AND(All!$V4="P6",All!$AE4="RSS"),Ruler!I$27,IF(AND(All!$V4="P7",All!$AE4="RSS"),Ruler!I$28,IF(AND(All!$V4="P8",All!$AE4="RSS"),Ruler!I$29,IF(AND(All!$V4="P9",All!$AE4="RSS"),Ruler!I$30,0))))))))))))))))))))))))))) -> 2 | BQ4: =IF(AND(All!$V4="P1",All!$AE4="RDP"),Ruler!J$6,IF(AND(All!$V4="P2",All!$AE4="RDP"),Ruler!J$7,IF(AND(All!$V4="P3",All!$AE4="RDP"),Ruler!J$8,IF(AND(All!$V4="P4",All!$AE4="RDP"),Ruler!J$9,IF(AND(All!$V4="P5",All!$AE4="RDP"),Ruler!J$10,IF(AND(All!$V4="P6",All!$AE4="RDP"),Ruler!J$11,IF(AND(All!$V4="P7",All!$AE4="RDP"),Ruler!J$12,IF(AND(All!$V4="P8",All!$AE4="RDP"),Ruler!J$13,IF(AND(All!$V4="P9",All!$AE4="RDP"),Ruler!J$14,IF(AND(All!$V4="P1",All!$AE4="RMS"),Ruler!J$6,IF(AND(All!$V4="P2",All!$AE4="RMS"),Ruler!J$15,IF(AND(All!$V4="P3",All!$AE4="RMS"),Ruler!J$16,IF(AND(All!$V4="P4",All!$AE4="RMS"),Ruler!J$17,IF(AND(All!$V4="P5",All!$AE4="RMS"),Ruler!J$18,IF(AND(All!$V4="P6",All!$AE4="RMS"),Ruler!J$19,IF(AND(All!$V4="P7",All!$AE4="RMS"),Ruler!J$20,IF(AND(All!$V4="P8",All!$AE4="RMS"),Ruler!J$21,IF(AND(All!$V4="P9",All!$AE4="RMS"),Ruler!J$22,IF(AND(All!$V4="P1",All!$AE4="RSS"),Ruler!J$6,IF(AND(All!$V4="P2",All!$AE4="RSS"),Ruler!J$23,IF(AND(All!$V4="P3",All!$AE4="RSS"),Ruler!J$24,IF(AND(All!$V4="P4",All!$AE4="RSS"),Ruler!J$25,IF(AND(All!$V4="P5",All!$AE4="RSS"),Ruler!J$26,IF(AND(All!$V4="P6",All!$AE4="RSS"),Ruler!J$27,IF(AND(All!$V4="P7",All!$AE4="RSS"),Ruler!J$28,IF(AND(All!$V4="P8",All!$AE4="RSS"),Ruler!J$29,IF(AND(All!$V4="P9",All!$AE4="RSS"),Ruler!J$30,0))))))))))))))))))))))))))) -> 2 | BR4: =IF(AND(All!$V4="P1",All!$AE4="RDP"),Ruler!K$6,IF(AND(All!$V4="P2",All!$AE4="RDP"),Ruler!K$7,IF(AND(All!$V4="P3",All!$AE4="RDP"),Ruler!K$8,IF(AND(All!$V4="P4",All!$AE4="RDP"),Ruler!K$9,IF(AND(All!$V4="P5",All!$AE4="RDP"),Ruler!K$10,IF(AND(All!$V4="P6",All!$AE4="RDP"),Ruler!K$11,IF(AND(All!$V4="P7",All!$AE4="RDP"),Ruler!K$12,IF(AND(All!$V4="P8",All!$AE4="RDP"),Ruler!K$13,IF(AND(All!$V4="P9",All!$AE4="RDP"),Ruler!K$14,IF(AND(All!$V4="P1",All!$AE4="RMS"),Ruler!K$6,IF(AND(All!$V4="P2",All!$AE4="RMS"),Ruler!K$15,IF(AND(All!$V4="P3",All!$AE4="RMS"),Ruler!K$16,IF(AND(All!$V4="P4",All!$AE4="RMS"),Ruler!K$17,IF(AND(All!$V4="P5",All!$AE4="RMS"),Ruler!K$18,IF(AND(All!$V4="P6",All!$AE4="RMS"),Ruler!K$19,IF(AND(All!$V4="P7",All!$AE4="RMS"),Ruler!K$20,IF(AND(All!$V4="P8",All!$AE4="RMS"),Ruler!K$21,IF(AND(All!$V4="P9",All!$AE4="RMS"),Ruler!K$22,IF(AND(All!$V4="P1",All!$AE4="RSS"),Ruler!K$6,IF(AND(All!$V4="P2",All!$AE4="RSS"),Ruler!K$23,IF(AND(All!$V4="P3",All!$AE4="RSS"),Ruler!K$24,IF(AND(All!$V4="P4",All!$AE4="RSS"),Ruler!K$25,IF(AND(All!$V4="P5",All!$AE4="RSS"),Ruler!K$26,IF(AND(All!$V4="P6",All!$AE4="RSS"),Ruler!K$27,IF(AND(All!$V4="P7",All!$AE4="RSS"),Ruler!K$28,IF(AND(All!$V4="P8",All!$AE4="RSS"),Ruler!K$29,IF(AND(All!$V4="P9",All!$AE4="RSS"),Ruler!K$30,0))))))))))))))))))))))))))) -> 3 | BS4: =IF(AND(All!$V4="P1",All!$AE4="RDP"),Ruler!L$6,IF(AND(All!$V4="P2",All!$AE4="RDP"),Ruler!L$7,IF(AND(All!$V4="P3",All!$AE4="RDP"),Ruler!L$8,IF(AND(All!$V4="P4",All!$AE4="RDP"),Ruler!L$9,IF(AND(All!$V4="P5",All!$AE4="RDP"),Ruler!L$10,IF(AND(All!$V4="P6",All!$AE4="RDP"),Ruler!L$11,IF(AND(All!$V4="P7",All!$AE4="RDP"),Ruler!L$12,IF(AND(All!$V4="P8",All!$AE4="RDP"),Ruler!L$13,IF(AND(All!$V4="P9",All!$AE4="RDP"),Ruler!L$14,IF(AND(All!$V4="P1",All!$AE4="RMS"),Ruler!L$6,IF(AND(All!$V4="P2",All!$AE4="RMS"),Ruler!L$15,IF(AND(All!$V4="P3",All!$AE4="RMS"),Ruler!L$16,IF(AND(All!$V4="P4",All!$AE4="RMS"),Ruler!L$17,IF(AND(All!$V4="P5",All!$AE4="RMS"),Ruler!L$18,IF(AND(All!$V4="P6",All!$AE4="RMS"),Ruler!L$19,IF(AND(All!$V4="P7",All!$AE4="RMS"),Ruler!L$20,IF(AND(All!$V4="P8",All!$AE4="RMS"),Ruler!L$21,IF(AND(All!$V4="P9",All!$AE4="RMS"),Ruler!L$22,IF(AND(All!$V4="P1",All!$AE4="RSS"),Ruler!L$6,IF(AND(All!$V4="P2",All!$AE4="RSS"),Ruler!L$23,IF(AND(All!$V4="P3",All!$AE4="RSS"),Ruler!L$24,IF(AND(All!$V4="P4",All!$AE4="RSS"),Ruler!L$25,IF(AND(All!$V4="P5",All!$AE4="RSS"),Ruler!L$26,IF(AND(All!$V4="P6",All!$AE4="RSS"),Ruler!L$27,IF(AND(All!$V4="P7",All!$AE4="RSS"),Ruler!L$28,IF(AND(All!$V4="P8",All!$AE4="RSS"),Ruler!L$29,IF(AND(All!$V4="P9",All!$AE4="RSS"),Ruler!L$30,0))))))))))))))))))))))))))) -> 2 | ... CI4: =IF(AND(All!$V4="P1",All!$AE4="RDP"),Ruler!AB$6,IF(AND(All!$V4="P2",All!$AE4="RDP"),Ruler!AB$7,IF(AND(All!$V4="P3",All!$AE4="RDP"),Ruler!AB$8,IF(AND(All!$V4="P4",All!$AE4="RDP"),Ruler!AB$9,IF(AND(All!$V4="P5",All!$AE4="RDP"),Ruler!AB$10,IF(AND(All!$V4="P6",All!$AE4="RDP"),Ruler!AB$11,IF(AND(All!$V4="P7",All!$AE4="RDP"),Ruler!AB$12,IF(AND(All!$V4="P8",All!$AE4="RDP"),Ruler!AB$13,IF(AND(All!$V4="P9",All!$AE4="RDP"),Ruler!AB$14,IF(AND(All!$V4="P1",All!$AE4="RMS"),Ruler!AB$6,IF(AND(All!$V4="P2",All!$AE4="RMS"),Ruler!AB$15,IF(AND(All!$V4="P3",All!$AE4="RMS"),Ruler!AB$16,IF(AND(All!$V4="P4",All!$AE4="RMS"),Ruler!AB$17,IF(AND(All!$V4="P5",All!$AE4="RMS"),Ruler!AB$18,IF(AND(All!$V4="P6",All!$AE4="RMS"),Ruler!AB$19,IF(AND(All!$V4="P7",All!$AE4="RMS"),Ruler!AB$20,IF(AND(All!$V4="P8",All!$AE4="RMS"),Ruler!AB$21,IF(AND(All!$V4="P9",All!$AE4="RMS"),Ruler!AB$22,IF(AND(All!$V4="P1",All!$AE4="RSS"),Ruler!AB$6,IF(AND(All!$V4="P2",All!$AE4="RSS"),Ruler!AB$23,IF(AND(All!$V4="P3",All!$AE4="RSS"),Ruler!AB$24,IF(AND(All!$V4="P4",All!$AE4="RSS"),Ruler!AB$25,IF(AND(All!$V4="P5",All!$AE4="RSS"),Ruler!AB$26,IF(AND(All!$V4="P6",All!$AE4="RSS"),Ruler!AB$27,IF(AND(All!$V4="P7",All!$AE4="RSS"),Ruler!AB$28,IF(AND(All!$V4="P8",All!$AE4="RSS"),Ruler!AB$29,IF(AND(All!$V4="P9",All!$AE4="RSS"),Ruler!AB$30,0))))))))))))))))))))))))))) -> 0 | CJ4: =Table9[[#This Row],[R-B1]]-Table9[[#This Row],[B1]] -> 0 | CK4: =Table9[[#This Row],[R-B2]]-Table9[[#This Row],[B2]] -> 1 | CL4: =Table9[[#This Row],[R-B3]]-Table9[[#This Row],[B3]] -> 0 | CM4: =Table9[[#This Row],[R-B4]]-Table9[[#This Row],[B4]] -> 0 | CN4: =Table9[[#This Row],[R-B5]]-Table9[[#This Row],[B5]] -> 0 | CO4: =Table9[[#This Row],[R-B6]]-Table9[[#This Row],[B6]] -> 0 | CP4: =Table9[[#This Row],[R-B7]]-Table9[[#This Row],[B7]] -> 1 | CQ4: =Table9[[#This Row],[R-B8]]-Table9[[#This Row],[B8]] -> 0 | CR4: =Table9[[#This Row],[R-B9]]-Table9[[#This Row],[B9]] -> 1 | CS4: =Table9[[#This Row],[R-B10]]-Table9[[#This Row],[B10]] -> 1 | CT4: =Table9[[#This Row],[R-B11]]-Table9[[#This Row],[B11]] -> 1 | CU4: =Table9[[#This Row],[R-B12]]-Table9[[#This Row],[B12]] -> 1 | CV4: =Table9[[#This Row],[R-K1]]-Table9[[#This Row],[K1]] -> 0 | CW4: =Table9[[#This Row],[R-K2]]-Table9[[#This Row],[K2]] -> 1 | CX4: =Table9[[#This Row],[R-K3]]-Table9[[#This Row],[K3]] -> 1 | CY4: =Table9[[#This Row],[R-K4]]-Table9[[#This Row],[K4]] -> 0 | CZ4: =Table9[[#This Row],[R-K5]]-Table9[[#This Row],[K5]] -> 1 | DA4: =Table9[[#This Row],[R-P1]]-Table9[[#This Row],[P1]] -> 0 | DB4: =Table9[[#This Row],[R-P2]]-Table9[[#This Row],[P2]] -> -1 | DC4: =Table9[[#This Row],[R-P3]]-Table9[[#This Row],[P3]] -> -1 | DD4: =Table9[[#This Row],[R-P4]]-Table9[[#This Row],[P4]] -> -1 | DE4: =Table9[[#This Row],[R-P5]]-Table9[[#This Row],[P5]] -> 1 | DF4: =Table9[[#This Row],[R-E1]]-Table9[[#This Row],[E1]] -> 0 | DG4: =Table9[[#This Row],[R-E2]]-Table9[[#This Row],[E2]] -> 0 | DH4: =COUNTIF(Table9[[#This Row],[G-B1]:[G-B12]],"<=0")/12*100 -> 50 | DI4: =COUNTIF(Table9[[#This Row],[G-K1]:[G-K5]],"<=0")/5*100 -> 40 | DJ4: =COUNTIF(Table9[[#This Row],[G-P1]:[G-P5]],"<=0")/5*100 -> 80 | DK4: =COUNTIF(Table9[[#This Row],[G-E1]:[G-E2]],"<=0")/2*100 -> 100 | DL4: =IF(AE4="RDP",(COUNTIF(Table9[[#This Row],[G-B3]],"<=0")+COUNTIF(Table9[[#This Row],[G-B4]],"<=0")+COUNTIF(Table9[[#This Row],[G-B7]],"<=0")+COUNTIF(Table9[[#This Row],[G-B11]],"<=0")+COUNTIF(Table9[[#This Row],[G-K2]],"<=0"))/5*100,IF(AE4="RMS",(COUNTIF(Table9[[#This Row],[G-B4]],"<=0")+COUNTIF(Table9[[#This Row],[G-B5]],"<=0")+COUNTIF(Table9[[#This Row],[G-B10]],"<=0")+COUNTIF(Table9[[#This Row],[G-B12]],"<=0")+COUNTIF(Table9[[#This Row],[G-K2]],"<=0"))/5*100,IF(AE4="RSS",(COUNTIF(Table9[[#This Row],[G-B1]],"<=0")+COUNTIF(Table9[[#This Row],[G-B2]],"<=0")+COUNTIF(Table9[[#This Row],[G-B6]],"<=0")+COUNTIF(Table9[[#This Row],[G-B11]],"<=0")+COUNTIF(Table9[[#This Row],[G-B12]],"<=0"))/5*100,0))) -> 40 | DM4: 8 | DN4: 0 | DO4: 60 | DP4: 0 | DQ4: 0 | DR4: 0 | DS4: 0 | DT4: 60 | DU4: 0 | DV4: 0 | DW4: 0 | DX4: 0 | DY4: 0 | DZ4: 0 | EA4: 0 | EE4: UPE map to RDP ruler
B5: 2 | C5: Yes | D5: 46146 | E5: Abdul Hakim bin Basri | F5: 1028534 | G5: =($T$1-H5)/365 -> 35.82639 | H5: 33239 | I5: M | J5: Malaysia | K5: IRQ | L5: PE | M5: RMS | N5: Gharaf | O5: Snr RE | P5: hakim.basri@petronas.com.my | Q5: Permanent | S5: 42095 | T5: =YEARFRAC(S5,$T$1) -> 11.552778 | U5: =Table9[[#This Row],[Years in PET]] -> 11.552778 | V5: P4 | X5: =($T$1-Table9[[#This Row],[Date of Appointment to Current Grade]])/365 -> 1.5551569 | Y5: 45748 | Z5: Iraq | AB5: 0.6 | AC5: UPE | AE5: RSS | AF5: High | AH5: ✅ IOR/EOR (Angsi EORC,Bokor IWAG), ✅ Dynamic modeling+ HM, ✅ FDP/FFR brown and greenfield, ✅ Deepwater development concept, ✅ surveillance&optmization | AI5: TPCP self assesssmnet, identify gap and try to address through current job | AJ5: EOR, Modeling | AK5: SMA passed. Not yet decided his path | AL5: Undecided | AM5: Win-win arrangement, | AN5: 3 | AO5: 3 | AP5: 3 | AQ5: 1 | AR5: 2 | AS5: 2 | AT5: 2 | AU5: 3 | AV5: 2 | AW5: 2 | AX5: 2 | AY5: 2 | AZ5: 2 | BA5: 2 | BB5: 1 | BC5: 1 | BD5: 1 | BE5: 1 | BF5: 1 | BG5: 1 | BH5: 1 | BI5: 1 | BJ5: 1 | BK5: 1 | BL5: =IF(AND(All!$V5="P1",All!$AE5="RDP"),Ruler!E$6,IF(AND(All!$V5="P2",All!$AE5="RDP"),Ruler!E$7,IF(AND(All!$V5="P3",All!$AE5="RDP"),Ruler!E$8,IF(AND(All!$V5="P4",All!$AE5="RDP"),Ruler!E$9,IF(AND(All!$V5="P5",All!$AE5="RDP"),Ruler!E$10,IF(AND(All!$V5="P6",All!$AE5="RDP"),Ruler!E$11,IF(AND(All!$V5="P7",All!$AE5="RDP"),Ruler!E$12,IF(AND(All!$V5="P8",All!$AE5="RDP"),Ruler!E$13,IF(AND(All!$V5="P9",All!$AE5="RDP"),Ruler!E$14,IF(AND(All!$V5="P1",All!$AE5="RMS"),Ruler!E$6,IF(AND(All!$V5="P2",All!$AE5="RMS"),Ruler!E$15,IF(AND(All!$V5="P3",All!$AE5="RMS"),Ruler!E$16,IF(AND(All!$V5="P4",All!$AE5="RMS"),Ruler!E$17,IF(AND(All!$V5="P5",All!$AE5="RMS"),Ruler!E$18,IF(AND(All!$V5="P6",All!$AE5="RMS"),Ruler!E$19,IF(AND(All!$V5="P7",All!$AE5="RMS"),Ruler!E$20,IF(AND(All!$V5="P8",All!$AE5="RMS"),Ruler!E$21,IF(AND(All!$V5="P9",All!$AE5="RMS"),Ruler!E$22,IF(AND(All!$V5="P1",All!$AE5="RSS"),Ruler!E$6,IF(AND(All!$V5="P2",All!$AE5="RSS"),Ruler!E$23,IF(AND(All!$V5="P3",All!$AE5="RSS"),Ruler!E$24,IF(AND(All!$V5="P4",All!$AE5="RSS"),Ruler!E$25,IF(AND(All!$V5="P5",All!$AE5="RSS"),Ruler!E$26,IF(AND(All!$V5="P6",All!$AE5="RSS"),Ruler!E$27,IF(AND(All!$V5="P7",All!$AE5="RSS"),Ruler!E$28,IF(AND(All!$V5="P8",All!$AE5="RSS"),Ruler!E$29,IF(AND(All!$V5="P9",All!$AE5="RSS"),Ruler!E$30,0))))))))))))))))))))))))))) -> 3 | BM5: =IF(AND(All!$V5="P1",All!$AE5="RDP"),Ruler!F$6,IF(AND(All!$V5="P2",All!$AE5="RDP"),Ruler!F$7,IF(AND(All!$V5="P3",All!$AE5="RDP"),Ruler!F$8,IF(AND(All!$V5="P4",All!$AE5="RDP"),Ruler!F$9,IF(AND(All!$V5="P5",All!$AE5="RDP"),Ruler!F$10,IF(AND(All!$V5="P6",All!$AE5="RDP"),Ruler!F$11,IF(AND(All!$V5="P7",All!$AE5="RDP"),Ruler!F$12,IF(AND(All!$V5="P8",All!$AE5="RDP"),Ruler!F$13,IF(AND(All!$V5="P9",All!$AE5="RDP"),Ruler!F$14,IF(AND(All!$V5="P1",All!$AE5="RMS"),Ruler!F$6,IF(AND(All!$V5="P2",All!$AE5="RMS"),Ruler!F$15,IF(AND(All!$V5="P3",All!$AE5="RMS"),Ruler!F$16,IF(AND(All!$V5="P4",All!$AE5="RMS"),Ruler!F$17,IF(AND(All!$V5="P5",All!$AE5="RMS"),Ruler!F$18,IF(AND(All!$V5="P6",All!$AE5="RMS"),Ruler!F$19,IF(AND(All!$V5="P7",All!$AE5="RMS"),Ruler!F$20,IF(AND(All!$V5="P8",All!$AE5="RMS"),Ruler!F$21,IF(AND(All!$V5="P9",All!$AE5="RMS"),Ruler!F$22,IF(AND(All!$V5="P1",All!$AE5="RSS"),Ruler!F$6,IF(AND(All!$V5="P2",All!$AE5="RSS"),Ruler!F$23,IF(AND(All!$V5="P3",All!$AE5="RSS"),Ruler!F$24,IF(AND(All!$V5="P4",All!$AE5="RSS"),Ruler!F$25,IF(AND(All!$V5="P5",All!$AE5="RSS"),Ruler!F$26,IF(AND(All!$V5="P6",All!$AE5="RSS"),Ruler!F$27,IF(AND(All!$V5="P7",All!$AE5="RSS"),Ruler!F$28,IF(AND(All!$V5="P8",All!$AE5="RSS"),Ruler!F$29,IF(AND(All!$V5="P9",All!$AE5="RSS"),Ruler!F$30,0))))))))))))))))))))))))))) -> 3 | BN5: =IF(AND(All!$V5="P1",All!$AE5="RDP"),Ruler!G$6,IF(AND(All!$V5="P2",All!$AE5="RDP"),Ruler!G$7,IF(AND(All!$V5="P3",All!$AE5="RDP"),Ruler!G$8,IF(AND(All!$V5="P4",All!$AE5="RDP"),Ruler!G$9,IF(AND(All!$V5="P5",All!$AE5="RDP"),Ruler!G$10,IF(AND(All!$V5="P6",All!$AE5="RDP"),Ruler!G$11,IF(AND(All!$V5="P7",All!$AE5="RDP"),Ruler!G$12,IF(AND(All!$V5="P8",All!$AE5="RDP"),Ruler!G$13,IF(AND(All!$V5="P9",All!$AE5="RDP"),Ruler!G$14,IF(AND(All!$V5="P1",All!$AE5="RMS"),Ruler!G$6,IF(AND(All!$V5="P2",All!$AE5="RMS"),Ruler!G$15,IF(AND(All!$V5="P3",All!$AE5="RMS"),Ruler!G$16,IF(AND(All!$V5="P4",All!$AE5="RMS"),Ruler!G$17,IF(AND(All!$V5="P5",All!$AE5="RMS"),Ruler!G$18,IF(AND(All!$V5="P6",All!$AE5="RMS"),Ruler!G$19,IF(AND(All!$V5="P7",All!$AE5="RMS"),Ruler!G$20,IF(AND(All!$V5="P8",All!$AE5="RMS"),Ruler!G$21,IF(AND(All!$V5="P9",All!$AE5="RMS"),Ruler!G$22,IF(AND(All!$V5="P1",All!$AE5="RSS"),Ruler!G$6,IF(AND(All!$V5="P2",All!$AE5="RSS"),Ruler!G$23,IF(AND(All!$V5="P3",All!$AE5="RSS"),Ruler!G$24,IF(AND(All!$V5="P4",All!$AE5="RSS"),Ruler!G$25,IF(AND(All!$V5="P5",All!$AE5="RSS"),Ruler!G$26,IF(AND(All!$V5="P6",All!$AE5="RSS"),Ruler!G$27,IF(AND(All!$V5="P7",All!$AE5="RSS"),Ruler!G$28,IF(AND(All!$V5="P8",All!$AE5="RSS"),Ruler!G$29,IF(AND(All!$V5="P9",All!$AE5="RSS"),Ruler!G$30,0))))))))))))))))))))))))))) -> 2 | BO5: =IF(AND(All!$V5="P1",All!$AE5="RDP"),Ruler!H$6,IF(AND(All!$V5="P2",All!$AE5="RDP"),Ruler!H$7,IF(AND(All!$V5="P3",All!$AE5="RDP"),Ruler!H$8,IF(AND(All!$V5="P4",All!$AE5="RDP"),Ruler!H$9,IF(AND(All!$V5="P5",All!$AE5="RDP"),Ruler!H$10,IF(AND(All!$V5="P6",All!$AE5="RDP"),Ruler!H$11,IF(AND(All!$V5="P7",All!$AE5="RDP"),Ruler!H$12,IF(AND(All!$V5="P8",All!$AE5="RDP"),Ruler!H$13,IF(AND(All!$V5="P9",All!$AE5="RDP"),Ruler!H$14,IF(AND(All!$V5="P1",All!$AE5="RMS"),Ruler!H$6,IF(AND(All!$V5="P2",All!$AE5="RMS"),Ruler!H$15,IF(AND(All!$V5="P3",All!$AE5="RMS"),Ruler!H$16,IF(AND(All!$V5="P4",All!$AE5="RMS"),Ruler!H$17,IF(AND(All!$V5="P5",All!$AE5="RMS"),Ruler!H$18,IF(AND(All!$V5="P6",All!$AE5="RMS"),Ruler!H$19,IF(AND(All!$V5="P7",All!$AE5="RMS"),Ruler!H$20,IF(AND(All!$V5="P8",All!$AE5="RMS"),Ruler!H$21,IF(AND(All!$V5="P9",All!$AE5="RMS"),Ruler!H$22,IF(AND(All!$V5="P1",All!$AE5="RSS"),Ruler!H$6,IF(AND(All!$V5="P2",All!$AE5="RSS"),Ruler!H$23,IF(AND(All!$V5="P3",All!$AE5="RSS"),Ruler!H$24,IF(AND(All!$V5="P4",All!$AE5="RSS"),Ruler!H$25,IF(AND(All!$V5="P5",All!$AE5="RSS"),Ruler!H$26,IF(AND(All!$V5="P6",All!$AE5="RSS"),Ruler!H$27,IF(AND(All!$V5="P7",All!$AE5="RSS"),Ruler!H$28,IF(AND(All!$V5="P8",All!$AE5="RSS"),Ruler!H$29,IF(AND(All!$V5="P9",All!$AE5="RSS"),Ruler!H$30,0))))))))))))))))))))))))))) -> 3 | BP5: =IF(AND(All!$V5="P1",All!$AE5="RDP"),Ruler!I$6,IF(AND(All!$V5="P2",All!$AE5="RDP"),Ruler!I$7,IF(AND(All!$V5="P3",All!$AE5="RDP"),Ruler!I$8,IF(AND(All!$V5="P4",All!$AE5="RDP"),Ruler!I$9,IF(AND(All!$V5="P5",All!$AE5="RDP"),Ruler!I$10,IF(AND(All!$V5="P6",All!$AE5="RDP"),Ruler!I$11,IF(AND(All!$V5="P7",All!$AE5="RDP"),Ruler!I$12,IF(AND(All!$V5="P8",All!$AE5="RDP"),Ruler!I$13,IF(AND(All!$V5="P9",All!$AE5="RDP"),Ruler!I$14,IF(AND(All!$V5="P1",All!$AE5="RMS"),Ruler!I$6,IF(AND(All!$V5="P2",All!$AE5="RMS"),Ruler!I$15,IF(AND(All!$V5="P3",All!$AE5="RMS"),Ruler!I$16,IF(AND(All!$V5="P4",All!$AE5="RMS"),Ruler!I$17,IF(AND(All!$V5="P5",All!$AE5="RMS"),Ruler!I$18,IF(AND(All!$V5="P6",All!$AE5="RMS"),Ruler!I$19,IF(AND(All!$V5="P7",All!$AE5="RMS"),Ruler!I$20,IF(AND(All!$V5="P8",All!$AE5="RMS"),Ruler!I$21,IF(AND(All!$V5="P9",All!$AE5="RMS"),Ruler!I$22,IF(AND(All!$V5="P1",All!$AE5="RSS"),Ruler!I$6,IF(AND(All!$V5="P2",All!$AE5="RSS"),Ruler!I$23,IF(AND(All!$V5="P3",All!$AE5="RSS"),Ruler!I$24,IF(AND(All!$V5="P4",All!$AE5="RSS"),Ruler!I$25,IF(AND(All!$V5="P5",All!$AE5="RSS"),Ruler!I$26,IF(AND(All!$V5="P6",All!$AE5="RSS"),Ruler!I$27,IF(AND(All!$V5="P7",All!$AE5="RSS"),Ruler!I$28,IF(AND(All!$V5="P8",All!$AE5="RSS"),Ruler!I$29,IF(AND(All!$V5="P9",All!$AE5="RSS"),Ruler!I$30,0))))))))))))))))))))))))))) -> 3 | BQ5: =IF(AND(All!$V5="P1",All!$AE5="RDP"),Ruler!J$6,IF(AND(All!$V5="P2",All!$AE5="RDP"),Ruler!J$7,IF(AND(All!$V5="P3",All!$AE5="RDP"),Ruler!J$8,IF(AND(All!$V5="P4",All!$AE5="RDP"),Ruler!J$9,IF(AND(All!$V5="P5",All!$AE5="RDP"),Ruler!J$10,IF(AND(All!$V5="P6",All!$AE5="RDP"),Ruler!J$11,IF(AND(All!$V5="P7",All!$AE5="RDP"),Ruler!J$12,IF(AND(All!$V5="P8",All!$AE5="RDP"),Ruler!J$13,IF(AND(All!$V5="P9",All!$AE5="RDP"),Ruler!J$14,IF(AND(All!$V5="P1",All!$AE5="RMS"),Ruler!J$6,IF(AND(All!$V5="P2",All!$AE5="RMS"),Ruler!J$15,IF(AND(All!$V5="P3",All!$AE5="RMS"),Ruler!J$16,IF(AND(All!$V5="P4",All!$AE5="RMS"),Ruler!J$17,IF(AND(All!$V5="P5",All!$AE5="RMS"),Ruler!J$18,IF(AND(All!$V5="P6",All!$AE5="RMS"),Ruler!J$19,IF(AND(All!$V5="P7",All!$AE5="RMS"),Ruler!J$20,IF(AND(All!$V5="P8",All!$AE5="RMS"),Ruler!J$21,IF(AND(All!$V5="P9",All!$AE5="RMS"),Ruler!J$22,IF(AND(All!$V5="P1",All!$AE5="RSS"),Ruler!J$6,IF(AND(All!$V5="P2",All!$AE5="RSS"),Ruler!J$23,IF(AND(All!$V5="P3",All!$AE5="RSS"),Ruler!J$24,IF(AND(All!$V5="P4",All!$AE5="RSS"),Ruler!J$25,IF(AND(All!$V5="P5",All!$AE5="RSS"),Ruler!J$26,IF(AND(All!$V5="P6",All!$AE5="RSS"),Ruler!J$27,IF(AND(All!$V5="P7",All!$AE5="RSS"),Ruler!J$28,IF(AND(All!$V5="P8",All!$AE5="RSS"),Ruler!J$29,IF(AND(All!$V5="P9",All!$AE5="RSS"),Ruler!J$30,0))))))))))))))))))))))))))) -> 3 | BR5: =IF(AND(All!$V5="P1",All!$AE5="RDP"),Ruler!K$6,IF(AND(All!$V5="P2",All!$AE5="RDP"),Ruler!K$7,IF(AND(All!$V5="P3",All!$AE5="RDP"),Ruler!K$8,IF(AND(All!$V5="P4",All!$AE5="RDP"),Ruler!K$9,IF(AND(All!$V5="P5",All!$AE5="RDP"),Ruler!K$10,IF(AND(All!$V5="P6",All!$AE5="RDP"),Ruler!K$11,IF(AND(All!$V5="P7",All!$AE5="RDP"),Ruler!K$12,IF(AND(All!$V5="P8",All!$AE5="RDP"),Ruler!K$13,IF(AND(All!$V5="P9",All!$AE5="RDP"),Ruler!K$14,IF(AND(All!$V5="P1",All!$AE5="RMS"),Ruler!K$6,IF(AND(All!$V5="P2",All!$AE5="RMS"),Ruler!K$15,IF(AND(All!$V5="P3",All!$AE5="RMS"),Ruler!K$16,IF(AND(All!$V5="P4",All!$AE5="RMS"),Ruler!K$17,IF(AND(All!$V5="P5",All!$AE5="RMS"),Ruler!K$18,IF(AND(All!$V5="P6",All!$AE5="RMS"),Ruler!K$19,IF(AND(All!$V5="P7",All!$AE5="RMS"),Ruler!K$20,IF(AND(All!$V5="P8",All!$AE5="RMS"),Ruler!K$21,IF(AND(All!$V5="P9",All!$AE5="RMS"),Ruler!K$22,IF(AND(All!$V5="P1",All!$AE5="RSS"),Ruler!K$6,IF(AND(All!$V5="P2",All!$AE5="RSS"),Ruler!K$23,IF(AND(All!$V5="P3",All!$AE5="RSS"),Ruler!K$24,IF(AND(All!$V5="P4",All!$AE5="RSS"),Ruler!K$25,IF(AND(All!$V5="P5",All!$AE5="RSS"),Ruler!K$26,IF(AND(All!$V5="P6",All!$AE5="RSS"),Ruler!K$27,IF(AND(All!$V5="P7",All!$AE5="RSS"),Ruler!K$28,IF(AND(All!$V5="P8",All!$AE5="RSS"),Ruler!K$29,IF(AND(All!$V5="P9",All!$AE5="RSS"),Ruler!K$30,0))))))))))))))))))))))))))) -> 3 | BS5: =IF(AND(All!$V5="P1",All!$AE5="RDP"),Ruler!L$6,IF(AND(All!$V5="P2",All!$AE5="RDP"),Ruler!L$7,IF(AND(All!$V5="P3",All!$AE5="RDP"),Ruler!L$8,IF(AND(All!$V5="P4",All!$AE5="RDP"),Ruler!L$9,IF(AND(All!$V5="P5",All!$AE5="RDP"),Ruler!L$10,IF(AND(All!$V5="P6",All!$AE5="RDP"),Ruler!L$11,IF(AND(All!$V5="P7",All!$AE5="RDP"),Ruler!L$12,IF(AND(All!$V5="P8",All!$AE5="RDP"),Ruler!L$13,IF(AND(All!$V5="P9",All!$AE5="RDP"),Ruler!L$14,IF(AND(All!$V5="P1",All!$AE5="RMS"),Ruler!L$6,IF(AND(All!$V5="P2",All!$AE5="RMS"),Ruler!L$15,IF(AND(All!$V5="P3",All!$AE5="RMS"),Ruler!L$16,IF(AND(All!$V5="P4",All!$AE5="RMS"),Ruler!L$17,IF(AND(All!$V5="P5",All!$AE5="RMS"),Ruler!L$18,IF(AND(All!$V5="P6",All!$AE5="RMS"),Ruler!L$19,IF(AND(All!$V5="P7",All!$AE5="RMS"),Ruler!L$20,IF(AND(All!$V5="P8",All!$AE5="RMS"),Ruler!L$21,IF(AND(All!$V5="P9",All!$AE5="RMS"),Ruler!L$22,IF(AND(All!$V5="P1",All!$AE5="RSS"),Ruler!L$6,IF(AND(All!$V5="P2",All!$AE5="RSS"),Ruler!L$23,IF(AND(All!$V5="P3",All!$AE5="RSS"),Ruler!L$24,IF(AND(All!$V5="P4",All!$AE5="RSS"),Ruler!L$25,IF(AND(All!$V5="P5",All!$AE5="RSS"),Ruler!L$26,IF(AND(All!$V5="P6",All!$AE5="RSS"),Ruler!L$27,IF(AND(All!$V5="P7",All!$AE5="RSS"),Ruler!L$28,IF(AND(All!$V5="P8",All!$AE5="RSS"),Ruler!L$29,IF(AND(All!$V5="P9",All!$AE5="RSS"),Ruler!L$30,0))))))))))))))))))))))))))) -> 2 | ... CI5: =IF(AND(All!$V5="P1",All!$AE5="RDP"),Ruler!AB$6,IF(AND(All!$V5="P2",All!$AE5="RDP"),Ruler!AB$7,IF(AND(All!$V5="P3",All!$AE5="RDP"),Ruler!AB$8,IF(AND(All!$V5="P4",All!$AE5="RDP"),Ruler!AB$9,IF(AND(All!$V5="P5",All!$AE5="RDP"),Ruler!AB$10,IF(AND(All!$V5="P6",All!$AE5="RDP"),Ruler!AB$11,IF(AND(All!$V5="P7",All!$AE5="RDP"),Ruler!AB$12,IF(AND(All!$V5="P8",All!$AE5="RDP"),Ruler!AB$13,IF(AND(All!$V5="P9",All!$AE5="RDP"),Ruler!AB$14,IF(AND(All!$V5="P1",All!$AE5="RMS"),Ruler!AB$6,IF(AND(All!$V5="P2",All!$AE5="RMS"),Ruler!AB$15,IF(AND(All!$V5="P3",All!$AE5="RMS"),Ruler!AB$16,IF(AND(All!$V5="P4",All!$AE5="RMS"),Ruler!AB$17,IF(AND(All!$V5="P5",All!$AE5="RMS"),Ruler!AB$18,IF(AND(All!$V5="P6",All!$AE5="RMS"),Ruler!AB$19,IF(AND(All!$V5="P7",All!$AE5="RMS"),Ruler!AB$20,IF(AND(All!$V5="P8",All!$AE5="RMS"),Ruler!AB$21,IF(AND(All!$V5="P9",All!$AE5="RMS"),Ruler!AB$22,IF(AND(All!$V5="P1",All!$AE5="RSS"),Ruler!AB$6,IF(AND(All!$V5="P2",All!$AE5="RSS"),Ruler!AB$23,IF(AND(All!$V5="P3",All!$AE5="RSS"),Ruler!AB$24,IF(AND(All!$V5="P4",All!$AE5="RSS"),Ruler!AB$25,IF(AND(All!$V5="P5",All!$AE5="RSS"),Ruler!AB$26,IF(AND(All!$V5="P6",All!$AE5="RSS"),Ruler!AB$27,IF(AND(All!$V5="P7",All!$AE5="RSS"),Ruler!AB$28,IF(AND(All!$V5="P8",All!$AE5="RSS"),Ruler!AB$29,IF(AND(All!$V5="P9",All!$AE5="RSS"),Ruler!AB$30,0))))))))))))))))))))))))))) -> 1 | CJ5: =Table9[[#This Row],[R-B1]]-Table9[[#This Row],[B1]] -> 0 | CK5: =Table9[[#This Row],[R-B2]]-Table9[[#This Row],[B2]] -> 0 | CL5: =Table9[[#This Row],[R-B3]]-Table9[[#This Row],[B3]] -> -1 | CM5: =Table9[[#This Row],[R-B4]]-Table9[[#This Row],[B4]] -> 2 | CN5: =Table9[[#This Row],[R-B5]]-Table9[[#This Row],[B5]] -> 1 | CO5: =Table9[[#This Row],[R-B6]]-Table9[[#This Row],[B6]] -> 1 | CP5: =Table9[[#This Row],[R-B7]]-Table9[[#This Row],[B7]] -> 1 | CQ5: =Table9[[#This Row],[R-B8]]-Table9[[#This Row],[B8]] -> -1 | CR5: =Table9[[#This Row],[R-B9]]-Table9[[#This Row],[B9]] -> 1 | CS5: =Table9[[#This Row],[R-B10]]-Table9[[#This Row],[B10]] -> -1 | CT5: =Table9[[#This Row],[R-B11]]-Table9[[#This Row],[B11]] -> 1 | CU5: =Table9[[#This Row],[R-B12]]-Table9[[#This Row],[B12]] -> 0 | CV5: =Table9[[#This Row],[R-K1]]-Table9[[#This Row],[K1]] -> 1 | CW5: =Table9[[#This Row],[R-K2]]-Table9[[#This Row],[K2]] -> 0 | CX5: =Table9[[#This Row],[R-K3]]-Table9[[#This Row],[K3]] -> 1 | CY5: =Table9[[#This Row],[R-K4]]-Table9[[#This Row],[K4]] -> 1 | CZ5: =Table9[[#This Row],[R-K5]]-Table9[[#This Row],[K5]] -> 1 | DA5: =Table9[[#This Row],[R-P1]]-Table9[[#This Row],[P1]] -> 1 | DB5: =Table9[[#This Row],[R-P2]]-Table9[[#This Row],[P2]] -> 1 | DC5: =Table9[[#This Row],[R-P3]]-Table9[[#This Row],[P3]] -> 1 | DD5: =Table9[[#This Row],[R-P4]]-Table9[[#This Row],[P4]] -> 0 | DE5: =Table9[[#This Row],[R-P5]]-Table9[[#This Row],[P5]] -> 1 | DF5: =Table9[[#This Row],[R-E1]]-Table9[[#This Row],[E1]] -> 0 | DG5: =Table9[[#This Row],[R-E2]]-Table9[[#This Row],[E2]] -> 0 | DH5: =COUNTIF(Table9[[#This Row],[G-B1]:[G-B12]],"<=0")/12*100 -> 50 | DI5: =COUNTIF(Table9[[#This Row],[G-K1]:[G-K5]],"<=0")/5*100 -> 20 | DJ5: =COUNTIF(Table9[[#This Row],[G-P1]:[G-P5]],"<=0")/5*100 -> 20 | DK5: =COUNTIF(Table9[[#This Row],[G-E1]:[G-E2]],"<=0")/2*100 -> 100 | DL5: =IF(AE5="RDP",(COUNTIF(Table9[[#This Row],[G-B3]],"<=0")+COUNTIF(Table9[[#This Row],[G-B4]],"<=0")+COUNTIF(Table9[[#This Row],[G-B7]],"<=0")+COUNTIF(Table9[[#This Row],[G-B11]],"<=0")+COUNTIF(Table9[[#This Row],[G-K2]],"<=0"))/5*100,IF(AE5="RMS",(COUNTIF(Table9[[#This Row],[G-B4]],"<=0")+COUNTIF(Table9[[#This Row],[G-B5]],"<=0")+COUNTIF(Table9[[#This Row],[G-B10]],"<=0")+COUNTIF(Table9[[#This Row],[G-B12]],"<=0")+COUNTIF(Table9[[#This Row],[G-K2]],"<=0"))/5*100,IF(AE5="RSS",(COUNTIF(Table9[[#This Row],[G-B1]],"<=0")+COUNTIF(Table9[[#This Row],[G-B2]],"<=0")+COUNTIF(Table9[[#This Row],[G-B6]],"<=0")+COUNTIF(Table9[[#This Row],[G-B11]],"<=0")+COUNTIF(Table9[[#This Row],[G-B12]],"<=0"))/5*100,0))) -> 60 | DM5: 50 | DN5: 20 | DO5: 20 | DP5: 100 | DQ5: 60 | DR5: 25 | DS5: 0 | DT5: 0 | DU5: 0 | DV5: 0 | DW5: 25 | DX5: 0 | DY5: 0 | DZ5: 0 | EA5: 0 | EE5: UPE map to RSS ruler
B6: 3 | C6: Not required | E6: Adi Krishna | G6: =($T$1-H6)/365 -> 36.82639 | H6: 32874 | I6: M | J6: Indonesia | K6: PCINO | L6: PE | M6: JVM | O6: Executive | P6: adi.krishna@petronas.com | Q6: CDH | X6: =($T$1-Table9[[#This Row],[Date of Appointment to Current Grade]])/365 -> 126.89214 | Z6: Indonesia | BL6: =IF(AND(All!$V6="P1",All!$AE6="RDP"),Ruler!E$6,IF(AND(All!$V6="P2",All!$AE6="RDP"),Ruler!E$7,IF(AND(All!$V6="P3",All!$AE6="RDP"),Ruler!E$8,IF(AND(All!$V6="P4",All!$AE6="RDP"),Ruler!E$9,IF(AND(All!$V6="P5",All!$AE6="RDP"),Ruler!E$10,IF(AND(All!$V6="P6",All!$AE6="RDP"),Ruler!E$11,IF(AND(All!$V6="P7",All!$AE6="RDP"),Ruler!E$12,IF(AND(All!$V6="P8",All!$AE6="RDP"),Ruler!E$13,IF(AND(All!$V6="P9",All!$AE6="RDP"),Ruler!E$14,IF(AND(All!$V6="P1",All!$AE6="RMS"),Ruler!E$6,IF(AND(All!$V6="P2",All!$AE6="RMS"),Ruler!E$15,IF(AND(All!$V6="P3",All!$AE6="RMS"),Ruler!E$16,IF(AND(All!$V6="P4",All!$AE6="RMS"),Ruler!E$17,IF(AND(All!$V6="P5",All!$AE6="RMS"),Ruler!E$18,IF(AND(All!$V6="P6",All!$AE6="RMS"),Ruler!E$19,IF(AND(All!$V6="P7",All!$AE6="RMS"),Ruler!E$20,IF(AND(All!$V6="P8",All!$AE6="RMS"),Ruler!E$21,IF(AND(All!$V6="P9",All!$AE6="RMS"),Ruler!E$22,IF(AND(All!$V6="P1",All!$AE6="RSS"),Ruler!E$6,IF(AND(All!$V6="P2",All!$AE6="RSS"),Ruler!E$23,IF(AND(All!$V6="P3",All!$AE6="RSS"),Ruler!E$24,IF(AND(All!$V6="P4",All!$AE6="RSS"),Ruler!E$25,IF(AND(All!$V6="P5",All!$AE6="RSS"),Ruler!E$26,IF(AND(All!$V6="P6",All!$AE6="RSS"),Ruler!E$27,IF(AND(All!$V6="P7",All!$AE6="RSS"),Ruler!E$28,IF(AND(All!$V6="P8",All!$AE6="RSS"),Ruler!E$29,IF(AND(All!$V6="P9",All!$AE6="RSS"),Ruler!E$30,0))))))))))))))))))))))))))) -> 0 | BM6: =IF(AND(All!$V6="P1",All!$AE6="RDP"),Ruler!F$6,IF(AND(All!$V6="P2",All!$AE6="RDP"),Ruler!F$7,IF(AND(All!$V6="P3",All!$AE6="RDP"),Ruler!F$8,IF(AND(All!$V6="P4",All!$AE6="RDP"),Ruler!F$9,IF(AND(All!$V6="P5",All!$AE6="RDP"),Ruler!F$10,IF(AND(All!$V6="P6",All!$AE6="RDP"),Ruler!F$11,IF(AND(All!$V6="P7",All!$AE6="RDP"),Ruler!F$12,IF(AND(All!$V6="P8",All!$AE6="RDP"),Ruler!F$13,IF(AND(All!$V6="P9",All!$AE6="RDP"),Ruler!F$14,IF(AND(All!$V6="P1",All!$AE6="RMS"),Ruler!F$6,IF(AND(All!$V6="P2",All!$AE6="RMS"),Ruler!F$15,IF(AND(All!$V6="P3",All!$AE6="RMS"),Ruler!F$16,IF(AND(All!$V6="P4",All!$AE6="RMS"),Ruler!F$17,IF(AND(All!$V6="P5",All!$AE6="RMS"),Ruler!F$18,IF(AND(All!$V6="P6",All!$AE6="RMS"),Ruler!F$19,IF(AND(All!$V6="P7",All!$AE6="RMS"),Ruler!F$20,IF(AND(All!$V6="P8",All!$AE6="RMS"),Ruler!F$21,IF(AND(All!$V6="P9",All!$AE6="RMS"),Ruler!F$22,IF(AND(All!$V6="P1",All!$AE6="RSS"),Ruler!F$6,IF(AND(All!$V6="P2",All!$AE6="RSS"),Ruler!F$23,IF(AND(All!$V6="P3",All!$AE6="RSS"),Ruler!F$24,IF(AND(All!$V6="P4",All!$AE6="RSS"),Ruler!F$25,IF(AND(All!$V6="P5",All!$AE6="RSS"),Ruler!F$26,IF(AND(All!$V6="P6",All!$AE6="RSS"),Ruler!F$27,IF(AND(All!$V6="P7",All!$AE6="RSS"),Ruler!F$28,IF(AND(All!$V6="P8",All!$AE6="RSS"),Ruler!F$29,IF(AND(All!$V6="P9",All!$AE6="RSS"),Ruler!F$30,0))))))))))))))))))))))))))) -> 0 | BN6: =IF(AND(All!$V6="P1",All!$AE6="RDP"),Ruler!G$6,IF(AND(All!$V6="P2",All!$AE6="RDP"),Ruler!G$7,IF(AND(All!$V6="P3",All!$AE6="RDP"),Ruler!G$8,IF(AND(All!$V6="P4",All!$AE6="RDP"),Ruler!G$9,IF(AND(All!$V6="P5",All!$AE6="RDP"),Ruler!G$10,IF(AND(All!$V6="P6",All!$AE6="RDP"),Ruler!G$11,IF(AND(All!$V6="P7",All!$AE6="RDP"),Ruler!G$12,IF(AND(All!$V6="P8",All!$AE6="RDP"),Ruler!G$13,IF(AND(All!$V6="P9",All!$AE6="RDP"),Ruler!G$14,IF(AND(All!$V6="P1",All!$AE6="RMS"),Ruler!G$6,IF(AND(All!$V6="P2",All!$AE6="RMS"),Ruler!G$15,IF(AND(All!$V6="P3",All!$AE6="RMS"),Ruler!G$16,IF(AND(All!$V6="P4",All!$AE6="RMS"),Ruler!G$17,IF(AND(All!$V6="P5",All!$AE6="RMS"),Ruler!G$18,IF(AND(All!$V6="P6",All!$AE6="RMS"),Ruler!G$19,IF(AND(All!$V6="P7",All!$AE6="RMS"),Ruler!G$20,IF(AND(All!$V6="P8",All!$AE6="RMS"),Ruler!G$21,IF(AND(All!$V6="P9",All!$AE6="RMS"),Ruler!G$22,IF(AND(All!$V6="P1",All!$AE6="RSS"),Ruler!G$6,IF(AND(All!$V6="P2",All!$AE6="RSS"),Ruler!G$23,IF(AND(All!$V6="P3",All!$AE6="RSS"),Ruler!G$24,IF(AND(All!$V6="P4",All!$AE6="RSS"),Ruler!G$25,IF(AND(All!$V6="P5",All!$AE6="RSS"),Ruler!G$26,IF(AND(All!$V6="P6",All!$AE6="RSS"),Ruler!G$27,IF(AND(All!$V6="P7",All!$AE6="RSS"),Ruler!G$28,IF(AND(All!$V6="P8",All!$AE6="RSS"),Ruler!G$29,IF(AND(All!$V6="P9",All!$AE6="RSS"),Ruler!G$30,0))))))))))))))))))))))))))) -> 0 | BO6: =IF(AND(All!$V6="P1",All!$AE6="RDP"),Ruler!H$6,IF(AND(All!$V6="P2",All!$AE6="RDP"),Ruler!H$7,IF(AND(All!$V6="P3",All!$AE6="RDP"),Ruler!H$8,IF(AND(All!$V6="P4",All!$AE6="RDP"),Ruler!H$9,IF(AND(All!$V6="P5",All!$AE6="RDP"),Ruler!H$10,IF(AND(All!$V6="P6",All!$AE6="RDP"),Ruler!H$11,IF(AND(All!$V6="P7",All!$AE6="RDP"),Ruler!H$12,IF(AND(All!$V6="P8",All!$AE6="RDP"),Ruler!H$13,IF(AND(All!$V6="P9",All!$AE6="RDP"),Ruler!H$14,IF(AND(All!$V6="P1",All!$AE6="RMS"),Ruler!H$6,IF(AND(All!$V6="P2",All!$AE6="RMS"),Ruler!H$15,IF(AND(All!$V6="P3",All!$AE6="RMS"),Ruler!H$16,IF(AND(All!$V6="P4",All!$AE6="RMS"),Ruler!H$17,IF(AND(All!$V6="P5",All!$AE6="RMS"),Ruler!H$18,IF(AND(All!$V6="P6",All!$AE6="RMS"),Ruler!H$19,IF(AND(All!$V6="P7",All!$AE6="RMS"),Ruler!H$20,IF(AND(All!$V6="P8",All!$AE6="RMS"),Ruler!H$21,IF(AND(All!$V6="P9",All!$AE6="RMS"),Ruler!H$22,IF(AND(All!$V6="P1",All!$AE6="RSS"),Ruler!H$6,IF(AND(All!$V6="P2",All!$AE6="RSS"),Ruler!H$23,IF(AND(All!$V6="P3",All!$AE6="RSS"),Ruler!H$24,IF(AND(All!$V6="P4",All!$AE6="RSS"),Ruler!H$25,IF(AND(All!$V6="P5",All!$AE6="RSS"),Ruler!H$26,IF(AND(All!$V6="P6",All!$AE6="RSS"),Ruler!H$27,IF(AND(All!$V6="P7",All!$AE6="RSS"),Ruler!H$28,IF(AND(All!$V6="P8",All!$AE6="RSS"),Ruler!H$29,IF(AND(All!$V6="P9",All!$AE6="RSS"),Ruler!H$30,0))))))))))))))))))))))))))) -> 0 | BP6: =IF(AND(All!$V6="P1",All!$AE6="RDP"),Ruler!I$6,IF(AND(All!$V6="P2",All!$AE6="RDP"),Ruler!I$7,IF(AND(All!$V6="P3",All!$AE6="RDP"),Ruler!I$8,IF(AND(All!$V6="P4",All!$AE6="RDP"),Ruler!I$9,IF(AND(All!$V6="P5",All!$AE6="RDP"),Ruler!I$10,IF(AND(All!$V6="P6",All!$AE6="RDP"),Ruler!I$11,IF(AND(All!$V6="P7",All!$AE6="RDP"),Ruler!I$12,IF(AND(All!$V6="P8",All!$AE6="RDP"),Ruler!I$13,IF(AND(All!$V6="P9",All!$AE6="RDP"),Ruler!I$14,IF(AND(All!$V6="P1",All!$AE6="RMS"),Ruler!I$6,IF(AND(All!$V6="P2",All!$AE6="RMS"),Ruler!I$15,IF(AND(All!$V6="P3",All!$AE6="RMS"),Ruler!I$16,IF(AND(All!$V6="P4",All!$AE6="RMS"),Ruler!I$17,IF(AND(All!$V6="P5",All!$AE6="RMS"),Ruler!I$18,IF(AND(All!$V6="P6",All!$AE6="RMS"),Ruler!I$19,IF(AND(All!$V6="P7",All!$AE6="RMS"),Ruler!I$20,IF(AND(All!$V6="P8",All!$AE6="RMS"),Ruler!I$21,IF(AND(All!$V6="P9",All!$AE6="RMS"),Ruler!I$22,IF(AND(All!$V6="P1",All!$AE6="RSS"),Ruler!I$6,IF(AND(All!$V6="P2",All!$AE6="RSS"),Ruler!I$23,IF(AND(All!$V6="P3",All!$AE6="RSS"),Ruler!I$24,IF(AND(All!$V6="P4",All!$AE6="RSS"),Ruler!I$25,IF(AND(All!$V6="P5",All!$AE6="RSS"),Ruler!I$26,IF(AND(All!$V6="P6",All!$AE6="RSS"),Ruler!I$27,IF(AND(All!$V6="P7",All!$AE6="RSS"),Ruler!I$28,IF(AND(All!$V6="P8",All!$AE6="RSS"),Ruler!I$29,IF(AND(All!$V6="P9",All!$AE6="RSS"),Ruler!I$30,0))))))))))))))))))))))))))) -> 0 | BQ6: =IF(AND(All!$V6="P1",All!$AE6="RDP"),Ruler!J$6,IF(AND(All!$V6="P2",All!$AE6="RDP"),Ruler!J$7,IF(AND(All!$V6="P3",All!$AE6="RDP"),Ruler!J$8,IF(AND(All!$V6="P4",All!$AE6="RDP"),Ruler!J$9,IF(AND(All!$V6="P5",All!$AE6="RDP"),Ruler!J$10,IF(AND(All!$V6="P6",All!$AE6="RDP"),Ruler!J$11,IF(AND(All!$V6="P7",All!$AE6="RDP"),Ruler!J$12,IF(AND(All!$V6="P8",All!$AE6="RDP"),Ruler!J$13,IF(AND(All!$V6="P9",All!$AE6="RDP"),Ruler!J$14,IF(AND(All!$V6="P1",All!$AE6="RMS"),Ruler!J$6,IF(AND(All!$V6="P2",All!$AE6="RMS"),Ruler!J$15,IF(AND(All!$V6="P3",All!$AE6="RMS"),Ruler!J$16,IF(AND(All!$V6="P4",All!$AE6="RMS"),Ruler!J$17,IF(AND(All!$V6="P5",All!$AE6="RMS"),Ruler!J$18,IF(AND(All!$V6="P6",All!$AE6="RMS"),Ruler!J$19,IF(AND(All!$V6="P7",All!$AE6="RMS"),Ruler!J$20,IF(AND(All!$V6="P8",All!$AE6="RMS"),Ruler!J$21,IF(AND(All!$V6="P9",All!$AE6="RMS"),Ruler!J$22,IF(AND(All!$V6="P1",All!$AE6="RSS"),Ruler!J$6,IF(AND(All!$V6="P2",All!$AE6="RSS"),Ruler!J$23,IF(AND(All!$V6="P3",All!$AE6="RSS"),Ruler!J$24,IF(AND(All!$V6="P4",All!$AE6="RSS"),Ruler!J$25,IF(AND(All!$V6="P5",All!$AE6="RSS"),Ruler!J$26,IF(AND(All!$V6="P6",All!$AE6="RSS"),Ruler!J$27,IF(AND(All!$V6="P7",All!$AE6="RSS"),Ruler!J$28,IF(AND(All!$V6="P8",All!$AE6="RSS"),Ruler!J$29,IF(AND(All!$V6="P9",All!$AE6="RSS"),Ruler!J$30,0))))))))))))))))))))))))))) -> 0 | BR6: =IF(AND(All!$V6="P1",All!$AE6="RDP"),Ruler!K$6,IF(AND(All!$V6="P2",All!$AE6="RDP"),Ruler!K$7,IF(AND(All!$V6="P3",All!$AE6="RDP"),Ruler!K$8,IF(AND(All!$V6="P4",All!$AE6="RDP"),Ruler!K$9,IF(AND(All!$V6="P5",All!$AE6="RDP"),Ruler!K$10,IF(AND(All!$V6="P6",All!$AE6="RDP"),Ruler!K$11,IF(AND(All!$V6="P7",All!$AE6="RDP"),Ruler!K$12,IF(AND(All!$V6="P8",All!$AE6="RDP"),Ruler!K$13,IF(AND(All!$V6="P9",All!$AE6="RDP"),Ruler!K$14,IF(AND(All!$V6="P1",All!$AE6="RMS"),Ruler!K$6,IF(AND(All!$V6="P2",All!$AE6="RMS"),Ruler!K$15,IF(AND(All!$V6="P3",All!$AE6="RMS"),Ruler!K$16,IF(AND(All!$V6="P4",All!$AE6="RMS"),Ruler!K$17,IF(AND(All!$V6="P5",All!$AE6="RMS"),Ruler!K$18,IF(AND(All!$V6="P6",All!$AE6="RMS"),Ruler!K$19,IF(AND(All!$V6="P7",All!$AE6="RMS"),Ruler!K$20,IF(AND(All!$V6="P8",All!$AE6="RMS"),Ruler!K$21,IF(AND(All!$V6="P9",All!$AE6="RMS"),Ruler!K$22,IF(AND(All!$V6="P1",All!$AE6="RSS"),Ruler!K$6,IF(AND(All!$V6="P2",All!$AE6="RSS"),Ruler!K$23,IF(AND(All!$V6="P3",All!$AE6="RSS"),Ruler!K$24,IF(AND(All!$V6="P4",All!$AE6="RSS"),Ruler!K$25,IF(AND(All!$V6="P5",All!$AE6="RSS"),Ruler!K$26,IF(AND(All!$V6="P6",All!$AE6="RSS"),Ruler!K$27,IF(AND(All!$V6="P7",All!$AE6="RSS"),Ruler!K$28,IF(AND(All!$V6="P8",All!$AE6="RSS"),Ruler!K$29,IF(AND(All!$V6="P9",All!$AE6="RSS"),Ruler!K$30,0))))))))))))))))))))))))))) -> 0 | BS6: =IF(AND(All!$V6="P1",All!$AE6="RDP"),Ruler!L$6,IF(AND(All!$V6="P2",All!$AE6="RDP"),Ruler!L$7,IF(AND(All!$V6="P3",All!$AE6="RDP"),Ruler!L$8,IF(AND(All!$V6="P4",All!$AE6="RDP"),Ruler!L$9,IF(AND(All!$V6="P5",All!$AE6="RDP"),Ruler!L$10,IF(AND(All!$V6="P6",All!$AE6="RDP"),Ruler!L$11,IF(AND(All!$V6="P7",All!$AE6="RDP"),Ruler!L$12,IF(AND(All!$V6="P8",All!$AE6="RDP"),Ruler!L$13,IF(AND(All!$V6="P9",All!$AE6="RDP"),Ruler!L$14,IF(AND(All!$V6="P1",All!$AE6="RMS"),Ruler!L$6,IF(AND(All!$V6="P2",All!$AE6="RMS"),Ruler!L$15,IF(AND(All!$V6="P3",All!$AE6="RMS"),Ruler!L$16,IF(AND(All!$V6="P4",All!$AE6="RMS"),Ruler!L$17,IF(AND(All!$V6="P5",All!$AE6="RMS"),Ruler!L$18,IF(AND(All!$V6="P6",All!$AE6="RMS"),Ruler!L$19,IF(AND(All!$V6="P7",All!$AE6="RMS"),Ruler!L$20,IF(AND(All!$V6="P8",All!$AE6="RMS"),Ruler!L$21,IF(AND(All!$V6="P9",All!$AE6="RMS"),Ruler!L$22,IF(AND(All!$V6="P1",All!$AE6="RSS"),Ruler!L$6,IF(AND(All!$V6="P2",All!$AE6="RSS"),Ruler!L$23,IF(AND(All!$V6="P3",All!$AE6="RSS"),Ruler!L$24,IF(AND(All!$V6="P4",All!$AE6="RSS"),Ruler!L$25,IF(AND(All!$V6="P5",All!$AE6="RSS"),Ruler!L$26,IF(AND(All!$V6="P6",All!$AE6="RSS"),Ruler!L$27,IF(AND(All!$V6="P7",All!$AE6="RSS"),Ruler!L$28,IF(AND(All!$V6="P8",All!$AE6="RSS"),Ruler!L$29,IF(AND(All!$V6="P9",All!$AE6="RSS"),Ruler!L$30,0))))))))))))))))))))))))))) -> 0 | ... CI6: =IF(AND(All!$V6="P1",All!$AE6="RDP"),Ruler!AB$6,IF(AND(All!$V6="P2",All!$AE6="RDP"),Ruler!AB$7,IF(AND(All!$V6="P3",All!$AE6="RDP"),Ruler!AB$8,IF(AND(All!$V6="P4",All!$AE6="RDP"),Ruler!AB$9,IF(AND(All!$V6="P5",All!$AE6="RDP"),Ruler!AB$10,IF(AND(All!$V6="P6",All!$AE6="RDP"),Ruler!AB$11,IF(AND(All!$V6="P7",All!$AE6="RDP"),Ruler!AB$12,IF(AND(All!$V6="P8",All!$AE6="RDP"),Ruler!AB$13,IF(AND(All!$V6="P9",All!$AE6="RDP"),Ruler!AB$14,IF(AND(All!$V6="P1",All!$AE6="RMS"),Ruler!AB$6,IF(AND(All!$V6="P2",All!$AE6="RMS"),Ruler!AB$15,IF(AND(All!$V6="P3",All!$AE6="RMS"),Ruler!AB$16,IF(AND(All!$V6="P4",All!$AE6="RMS"),Ruler!AB$17,IF(AND(All!$V6="P5",All!$AE6="RMS"),Ruler!AB$18,IF(AND(All!$V6="P6",All!$AE6="RMS"),Ruler!AB$19,IF(AND(All!$V6="P7",All!$AE6="RMS"),Ruler!AB$20,IF(AND(All!$V6="P8",All!$AE6="RMS"),Ruler!AB$21,IF(AND(All!$V6="P9",All!$AE6="RMS"),Ruler!AB$22,IF(AND(All!$V6="P1",All!$AE6="RSS"),Ruler!AB$6,IF(AND(All!$V6="P2",All!$AE6="RSS"),Ruler!AB$23,IF(AND(All!$V6="P3",All!$AE6="RSS"),Ruler!AB$24,IF(AND(All!$V6="P4",All!$AE6="RSS"),Ruler!AB$25,IF(AND(All!$V6="P5",All!$AE6="RSS"),Ruler!AB$26,IF(AND(All!$V6="P6",All!$AE6="RSS"),Ruler!AB$27,IF(AND(All!$V6="P7",All!$AE6="RSS"),Ruler!AB$28,IF(AND(All!$V6="P8",All!$AE6="RSS"),Ruler!AB$29,IF(AND(All!$V6="P9",All!$AE6="RSS"),Ruler!AB$30,0))))))))))))))))))))))))))) -> 0 | DH6: =COUNTIF(Table9[[#This Row],[G-B1]:[G-B12]],"<=0")/12*100 -> 0 | DI6: =COUNTIF(Table9[[#This Row],[G-K1]:[G-K5]],"<=0")/5*100 -> 0 | DJ6: =COUNTIF(Table9[[#This Row],[G-P1]:[G-P5]],"<=0")/5*100 -> 0 | DK6: =COUNTIF(Table9[[#This Row],[G-E1]:[G-E2]],"<=0")/2*100 -> 0 | DL6: =IF(AE6="RDP",(COUNTIF(Table9[[#This Row],[G-B3]],"<=0")+COUNTIF(Table9[[#This Row],[G-B4]],"<=0")+COUNTIF(Table9[[#This Row],[G-B7]],"<=0")+COUNTIF(Table9[[#This Row],[G-B11]],"<=0")+COUNTIF(Table9[[#This Row],[G-K2]],"<=0"))/5*100,IF(AE6="RMS",(COUNTIF(Table9[[#This Row],[G-B4]],"<=0")+COUNTIF(Table9[[#This Row],[G-B5]],"<=0")+COUNTIF(Table9[[#This Row],[G-B10]],"<=0")+COUNTIF(Table9[[#This Row],[G-B12]],"<=0")+COUNTIF(Table9[[#This Row],[G-K2]],"<=0"))/5*100,IF(AE6="RSS",(COUNTIF(Table9[[#This Row],[G-B1]],"<=0")+COUNTIF(Table9[[#This Row],[G-B2]],"<=0")+COUNTIF(Table9[[#This Row],[G-B6]],"<=0")+COUNTIF(Table9[[#This Row],[G-B11]],"<=0")+COUNTIF(Table9[[#This Row],[G-B12]],"<=0"))/5*100,0))) -> 0
B7: 4 | C7: Yes | D7: 46092 | E7: Aeishah Rosman | F7: 1063061 | G7: =($T$1-H7)/365 -> 42.831869 | H7: 30682 | I7: F | J7: Malaysia | K7: DPE | L7: IWT | M7: Suriname | N7: Oil | O7: Staff | P7: aeishah.rosman@petronas.com.my | Q7: Permanent | R7: N/A | S7: 44409 | T7: =YEARFRAC(S7,$T$1) -> 5.2194444 | U7: 18 | V7: P6 | W7: =Table9[[#This Row],[Age]]-($T$1-Table9[[#This Row],[Date of Appointment to Current Grade]])/365 -> 39.649315 | X7: =($T$1-Table9[[#This Row],[Date of Appointment to Current Grade]])/365 -> 3.1825542 | Y7: 45154 | Z7: KUL | AA7: 46023 | AB7: =($T$1-Table9[[#This Row],[Date in Position]])/365 -> 0.80173224 | AC7: Staff | AD7: 45070 | AE7: RSS | AF7: Good | AG7: PCSB (07-11) - Seconded to Petrotel for EOR study (WAG) and execute driliing program. (11-15)- moved to Turkmenistan FDP studies for condensate gas fields including compositional model, HM. Shell (15-19) - attached to NOV, resource reporting, asset reference plan, notional dev plan, PE identification. Hess (19-21) - WRM team, MBAL,GAP, PTA, performance monitoring and surveillance activities. PCSB (21-Now) - BA doing simulation model including ResX, RTA, Uncertainity guideline, recently moved to Suriname oil project - modeling using ResX | AH7: ✅ Reservoir Simulation including ResX ✅ FDP (extensive experience in gas) ✅ Risk and uncertainty management | AI7: ✅ Conduct a self‑assessment against the Principal role requirements to identify critical capability gaps. ✅ Identify potential skill gaps that can be addressed through the current job scope and on‑the‑job exposure. ✅ Present/share work to RELT e.g ResX and Suriname project | AJ7: Full Probalistic modeling, ResX | AK7: Exposure in drilling execution phase, Enhance her skill in Probabilisctic Modeling | AL7: TP | AM7: • The Principal role is currently focused primarily on assurance activities, with limited hands‑on technical involvement. • There is a need to clarify and strengthen PPA requirements for staff. • Currently facing some issue with Snr RE in her project. The person need to be guided for every task. Recommend a 1‑to‑1 discussion with that Snr RE to identify specific areas where additional support and development are needed. | AN7: 3 | AO7: 3 | AP7: 2 | AQ7: 3 | AR7: 3 | AS7: 3 | AT7: 3 | AU7: 2 | AV7: 3 | AW7: 1 | AX7: 3 | AY7: 2 | AZ7: 2 | BA7: 2 | BB7: 2 | BC7: 2 | BD7: 2 | BE7: 2 | BF7: 2 | BG7: 2 | BH7: 1 | BI7: 2 | BJ7: 1 | BK7: 1 | BL7: =IF(AND(All!$V7="P1",All!$AE7="RDP"),Ruler!E$6,IF(AND(All!$V7="P2",All!$AE7="RDP"),Ruler!E$7,IF(AND(All!$V7="P3",All!$AE7="RDP"),Ruler!E$8,IF(AND(All!$V7="P4",All!$AE7="RDP"),Ruler!E$9,IF(AND(All!$V7="P5",All!$AE7="RDP"),Ruler!E$10,IF(AND(All!$V7="P6",All!$AE7="RDP"),Ruler!E$11,IF(AND(All!$V7="P7",All!$AE7="RDP"),Ruler!E$12,IF(AND(All!$V7="P8",All!$AE7="RDP"),Ruler!E$13,IF(AND(All!$V7="P9",All!$AE7="RDP"),Ruler!E$14,IF(AND(All!$V7="P1",All!$AE7="RMS"),Ruler!E$6,IF(AND(All!$V7="P2",All!$AE7="RMS"),Ruler!E$15,IF(AND(All!$V7="P3",All!$AE7="RMS"),Ruler!E$16,IF(AND(All!$V7="P4",All!$AE7="RMS"),Ruler!E$17,IF(AND(All!$V7="P5",All!$AE7="RMS"),Ruler!E$18,IF(AND(All!$V7="P6",All!$AE7="RMS"),Ruler!E$19,IF(AND(All!$V7="P7",All!$AE7="RMS"),Ruler!E$20,IF(AND(All!$V7="P8",All!$AE7="RMS"),Ruler!E$21,IF(AND(All!$V7="P9",All!$AE7="RMS"),Ruler!E$22,IF(AND(All!$V7="P1",All!$AE7="RSS"),Ruler!E$6,IF(AND(All!$V7="P2",All!$AE7="RSS"),Ruler!E$23,IF(AND(All!$V7="P3",All!$AE7="RSS"),Ruler!E$24,IF(AND(All!$V7="P4",All!$AE7="RSS"),Ruler!E$25,IF(AND(All!$V7="P5",All!$AE7="RSS"),Ruler!E$26,IF(AND(All!$V7="P6",All!$AE7="RSS"),Ruler!E$27,IF(AND(All!$V7="P7",All!$AE7="RSS"),Ruler!E$28,IF(AND(All!$V7="P8",All!$AE7="RSS"),Ruler!E$29,IF(AND(All!$V7="P9",All!$AE7="RSS"),Ruler!E$30,0))))))))))))))))))))))))))) -> 4 | BM7: =IF(AND(All!$V7="P1",All!$AE7="RDP"),Ruler!F$6,IF(AND(All!$V7="P2",All!$AE7="RDP"),Ruler!F$7,IF(AND(All!$V7="P3",All!$AE7="RDP"),Ruler!F$8,IF(AND(All!$V7="P4",All!$AE7="RDP"),Ruler!F$9,IF(AND(All!$V7="P5",All!$AE7="RDP"),Ruler!F$10,IF(AND(All!$V7="P6",All!$AE7="RDP"),Ruler!F$11,IF(AND(All!$V7="P7",All!$AE7="RDP"),Ruler!F$12,IF(AND(All!$V7="P8",All!$AE7="RDP"),Ruler!F$13,IF(AND(All!$V7="P9",All!$AE7="RDP"),Ruler!F$14,IF(AND(All!$V7="P1",All!$AE7="RMS"),Ruler!F$6,IF(AND(All!$V7="P2",All!$AE7="RMS"),Ruler!F$15,IF(AND(All!$V7="P3",All!$AE7="RMS"),Ruler!F$16,IF(AND(All!$V7="P4",All!$AE7="RMS"),Ruler!F$17,IF(AND(All!$V7="P5",All!$AE7="RMS"),Ruler!F$18,IF(AND(All!$V7="P6",All!$AE7="RMS"),Ruler!F$19,IF(AND(All!$V7="P7",All!$AE7="RMS"),Ruler!F$20,IF(AND(All!$V7="P8",All!$AE7="RMS"),Ruler!F$21,IF(AND(All!$V7="P9",All!$AE7="RMS"),Ruler!F$22,IF(AND(All!$V7="P1",All!$AE7="RSS"),Ruler!F$6,IF(AND(All!$V7="P2",All!$AE7="RSS"),Ruler!F$23,IF(AND(All!$V7="P3",All!$AE7="RSS"),Ruler!F$24,IF(AND(All!$V7="P4",All!$AE7="RSS"),Ruler!F$25,IF(AND(All!$V7="P5",All!$AE7="RSS"),Ruler!F$26,IF(AND(All!$V7="P6",All!$AE7="RSS"),Ruler!F$27,IF(AND(All!$V7="P7",All!$AE7="RSS"),Ruler!F$28,IF(AND(All!$V7="P8",All!$AE7="RSS"),Ruler!F$29,IF(AND(All!$V7="P9",All!$AE7="RSS"),Ruler!F$30,0))))))))))))))))))))))))))) -> 4 | BN7: =IF(AND(All!$V7="P1",All!$AE7="RDP"),Ruler!G$6,IF(AND(All!$V7="P2",All!$AE7="RDP"),Ruler!G$7,IF(AND(All!$V7="P3",All!$AE7="RDP"),Ruler!G$8,IF(AND(All!$V7="P4",All!$AE7="RDP"),Ruler!G$9,IF(AND(All!$V7="P5",All!$AE7="RDP"),Ruler!G$10,IF(AND(All!$V7="P6",All!$AE7="RDP"),Ruler!G$11,IF(AND(All!$V7="P7",All!$AE7="RDP"),Ruler!G$12,IF(AND(All!$V7="P8",All!$AE7="RDP"),Ruler!G$13,IF(AND(All!$V7="P9",All!$AE7="RDP"),Ruler!G$14,IF(AND(All!$V7="P1",All!$AE7="RMS"),Ruler!G$6,IF(AND(All!$V7="P2",All!$AE7="RMS"),Ruler!G$15,IF(AND(All!$V7="P3",All!$AE7="RMS"),Ruler!G$16,IF(AND(All!$V7="P4",All!$AE7="RMS"),Ruler!G$17,IF(AND(All!$V7="P5",All!$AE7="RMS"),Ruler!G$18,IF(AND(All!$V7="P6",All!$AE7="RMS"),Ruler!G$19,IF(AND(All!$V7="P7",All!$AE7="RMS"),Ruler!G$20,IF(AND(All!$V7="P8",All!$AE7="RMS"),Ruler!G$21,IF(AND(All!$V7="P9",All!$AE7="RMS"),Ruler!G$22,IF(AND(All!$V7="P1",All!$AE7="RSS"),Ruler!G$6,IF(AND(All!$V7="P2",All!$AE7="RSS"),Ruler!G$23,IF(AND(All!$V7="P3",All!$AE7="RSS"),Ruler!G$24,IF(AND(All!$V7="P4",All!$AE7="RSS"),Ruler!G$25,IF(AND(All!$V7="P5",All!$AE7="RSS"),Ruler!G$26,IF(AND(All!$V7="P6",All!$AE7="RSS"),Ruler!G$27,IF(AND(All!$V7="P7",All!$AE7="RSS"),Ruler!G$28,IF(AND(All!$V7="P8",All!$AE7="RSS"),Ruler!G$29,IF(AND(All!$V7="P9",All!$AE7="RSS"),Ruler!G$30,0))))))))))))))))))))))))))) -> 3 | BO7: =IF(AND(All!$V7="P1",All!$AE7="RDP"),Ruler!H$6,IF(AND(All!$V7="P2",All!$AE7="RDP"),Ruler!H$7,IF(AND(All!$V7="P3",All!$AE7="RDP"),Ruler!H$8,IF(AND(All!$V7="P4",All!$AE7="RDP"),Ruler!H$9,IF(AND(All!$V7="P5",All!$AE7="RDP"),Ruler!H$10,IF(AND(All!$V7="P6",All!$AE7="RDP"),Ruler!H$11,IF(AND(All!$V7="P7",All!$AE7="RDP"),Ruler!H$12,IF(AND(All!$V7="P8",All!$AE7="RDP"),Ruler!H$13,IF(AND(All!$V7="P9",All!$AE7="RDP"),Ruler!H$14,IF(AND(All!$V7="P1",All!$AE7="RMS"),Ruler!H$6,IF(AND(All!$V7="P2",All!$AE7="RMS"),Ruler!H$15,IF(AND(All!$V7="P3",All!$AE7="RMS"),Ruler!H$16,IF(AND(All!$V7="P4",All!$AE7="RMS"),Ruler!H$17,IF(AND(All!$V7="P5",All!$AE7="RMS"),Ruler!H$18,IF(AND(All!$V7="P6",All!$AE7="RMS"),Ruler!H$19,IF(AND(All!$V7="P7",All!$AE7="RMS"),Ruler!H$20,IF(AND(All!$V7="P8",All!$AE7="RMS"),Ruler!H$21,IF(AND(All!$V7="P9",All!$AE7="RMS"),Ruler!H$22,IF(AND(All!$V7="P1",All!$AE7="RSS"),Ruler!H$6,IF(AND(All!$V7="P2",All!$AE7="RSS"),Ruler!H$23,IF(AND(All!$V7="P3",All!$AE7="RSS"),Ruler!H$24,IF(AND(All!$V7="P4",All!$AE7="RSS"),Ruler!H$25,IF(AND(All!$V7="P5",All!$AE7="RSS"),Ruler!H$26,IF(AND(All!$V7="P6",All!$AE7="RSS"),Ruler!H$27,IF(AND(All!$V7="P7",All!$AE7="RSS"),Ruler!H$28,IF(AND(All!$V7="P8",All!$AE7="RSS"),Ruler!H$29,IF(AND(All!$V7="P9",All!$AE7="RSS"),Ruler!H$30,0))))))))))))))))))))))))))) -> 3 | BP7: =IF(AND(All!$V7="P1",All!$AE7="RDP"),Ruler!I$6,IF(AND(All!$V7="P2",All!$AE7="RDP"),Ruler!I$7,IF(AND(All!$V7="P3",All!$AE7="RDP"),Ruler!I$8,IF(AND(All!$V7="P4",All!$AE7="RDP"),Ruler!I$9,IF(AND(All!$V7="P5",All!$AE7="RDP"),Ruler!I$10,IF(AND(All!$V7="P6",All!$AE7="RDP"),Ruler!I$11,IF(AND(All!$V7="P7",All!$AE7="RDP"),Ruler!I$12,IF(AND(All!$V7="P8",All!$AE7="RDP"),Ruler!I$13,IF(AND(All!$V7="P9",All!$AE7="RDP"),Ruler!I$14,IF(AND(All!$V7="P1",All!$AE7="RMS"),Ruler!I$6,IF(AND(All!$V7="P2",All!$AE7="RMS"),Ruler!I$15,IF(AND(All!$V7="P3",All!$AE7="RMS"),Ruler!I$16,IF(AND(All!$V7="P4",All!$AE7="RMS"),Ruler!I$17,IF(AND(All!$V7="P5",All!$AE7="RMS"),Ruler!I$18,IF(AND(All!$V7="P6",All!$AE7="RMS"),Ruler!I$19,IF(AND(All!$V7="P7",All!$AE7="RMS"),Ruler!I$20,IF(AND(All!$V7="P8",All!$AE7="RMS"),Ruler!I$21,IF(AND(All!$V7="P9",All!$AE7="RMS"),Ruler!I$22,IF(AND(All!$V7="P1",All!$AE7="RSS"),Ruler!I$6,IF(AND(All!$V7="P2",All!$AE7="RSS"),Ruler!I$23,IF(AND(All!$V7="P3",All!$AE7="RSS"),Ruler!I$24,IF(AND(All!$V7="P4",All!$AE7="RSS"),Ruler!I$25,IF(AND(All!$V7="P5",All!$AE7="RSS"),Ruler!I$26,IF(AND(All!$V7="P6",All!$AE7="RSS"),Ruler!I$27,IF(AND(All!$V7="P7",All!$AE7="RSS"),Ruler!I$28,IF(AND(All!$V7="P8",All!$AE7="RSS"),Ruler!I$29,IF(AND(All!$V7="P9",All!$AE7="RSS"),Ruler!I$30,0))))))))))))))))))))))))))) -> 3 | BQ7: =IF(AND(All!$V7="P1",All!$AE7="RDP"),Ruler!J$6,IF(AND(All!$V7="P2",All!$AE7="RDP"),Ruler!J$7,IF(AND(All!$V7="P3",All!$AE7="RDP"),Ruler!J$8,IF(AND(All!$V7="P4",All!$AE7="RDP"),Ruler!J$9,IF(AND(All!$V7="P5",All!$AE7="RDP"),Ruler!J$10,IF(AND(All!$V7="P6",All!$AE7="RDP"),Ruler!J$11,IF(AND(All!$V7="P7",All!$AE7="RDP"),Ruler!J$12,IF(AND(All!$V7="P8",All!$AE7="RDP"),Ruler!J$13,IF(AND(All!$V7="P9",All!$AE7="RDP"),Ruler!J$14,IF(AND(All!$V7="P1",All!$AE7="RMS"),Ruler!J$6,IF(AND(All!$V7="P2",All!$AE7="RMS"),Ruler!J$15,IF(AND(All!$V7="P3",All!$AE7="RMS"),Ruler!J$16,IF(AND(All!$V7="P4",All!$AE7="RMS"),Ruler!J$17,IF(AND(All!$V7="P5",All!$AE7="RMS"),Ruler!J$18,IF(AND(All!$V7="P6",All!$AE7="RMS"),Ruler!J$19,IF(AND(All!$V7="P7",All!$AE7="RMS"),Ruler!J$20,IF(AND(All!$V7="P8",All!$AE7="RMS"),Ruler!J$21,IF(AND(All!$V7="P9",All!$AE7="RMS"),Ruler!J$22,IF(AND(All!$V7="P1",All!$AE7="RSS"),Ruler!J$6,IF(AND(All!$V7="P2",All!$AE7="RSS"),Ruler!J$23,IF(AND(All!$V7="P3",All!$AE7="RSS"),Ruler!J$24,IF(AND(All!$V7="P4",All!$AE7="RSS"),Ruler!J$25,IF(AND(All!$V7="P5",All!$AE7="RSS"),Ruler!J$26,IF(AND(All!$V7="P6",All!$AE7="RSS"),Ruler!J$27,IF(AND(All!$V7="P7",All!$AE7="RSS"),Ruler!J$28,IF(AND(All!$V7="P8",All!$AE7="RSS"),Ruler!J$29,IF(AND(All!$V7="P9",All!$AE7="RSS"),Ruler!J$30,0))))))))))))))))))))))))))) -> 4 | BR7: =IF(AND(All!$V7="P1",All!$AE7="RDP"),Ruler!K$6,IF(AND(All!$V7="P2",All!$AE7="RDP"),Ruler!K$7,IF(AND(All!$V7="P3",All!$AE7="RDP"),Ruler!K$8,IF(AND(All!$V7="P4",All!$AE7="RDP"),Ruler!K$9,IF(AND(All!$V7="P5",All!$AE7="RDP"),Ruler!K$10,IF(AND(All!$V7="P6",All!$AE7="RDP"),Ruler!K$11,IF(AND(All!$V7="P7",All!$AE7="RDP"),Ruler!K$12,IF(AND(All!$V7="P8",All!$AE7="RDP"),Ruler!K$13,IF(AND(All!$V7="P9",All!$AE7="RDP"),Ruler!K$14,IF(AND(All!$V7="P1",All!$AE7="RMS"),Ruler!K$6,IF(AND(All!$V7="P2",All!$AE7="RMS"),Ruler!K$15,IF(AND(All!$V7="P3",All!$AE7="RMS"),Ruler!K$16,IF(AND(All!$V7="P4",All!$AE7="RMS"),Ruler!K$17,IF(AND(All!$V7="P5",All!$AE7="RMS"),Ruler!K$18,IF(AND(All!$V7="P6",All!$AE7="RMS"),Ruler!K$19,IF(AND(All!$V7="P7",All!$AE7="RMS"),Ruler!K$20,IF(AND(All!$V7="P8",All!$AE7="RMS"),Ruler!K$21,IF(AND(All!$V7="P9",All!$AE7="RMS"),Ruler!K$22,IF(AND(All!$V7="P1",All!$AE7="RSS"),Ruler!K$6,IF(AND(All!$V7="P2",All!$AE7="RSS"),Ruler!K$23,IF(AND(All!$V7="P3",All!$AE7="RSS"),Ruler!K$24,IF(AND(All!$V7="P4",All!$AE7="RSS"),Ruler!K$25,IF(AND(All!$V7="P5",All!$AE7="RSS"),Ruler!K$26,IF(AND(All!$V7="P6",All!$AE7="RSS"),Ruler!K$27,IF(AND(All!$V7="P7",All!$AE7="RSS"),Ruler!K$28,IF(AND(All!$V7="P8",All!$AE7="RSS"),Ruler!K$29,IF(AND(All!$V7="P9",All!$AE7="RSS"),Ruler!K$30,0))))))))))))))))))))))))))) -> 4 | BS7: =IF(AND(All!$V7="P1",All!$AE7="RDP"),Ruler!L$6,IF(AND(All!$V7="P2",All!$AE7="RDP"),Ruler!L$7,IF(AND(All!$V7="P3",All!$AE7="RDP"),Ruler!L$8,IF(AND(All!$V7="P4",All!$AE7="RDP"),Ruler!L$9,IF(AND(All!$V7="P5",All!$AE7="RDP"),Ruler!L$10,IF(AND(All!$V7="P6",All!$AE7="RDP"),Ruler!L$11,IF(AND(All!$V7="P7",All!$AE7="RDP"),Ruler!L$12,IF(AND(All!$V7="P8",All!$AE7="RDP"),Ruler!L$13,IF(AND(All!$V7="P9",All!$AE7="RDP"),Ruler!L$14,IF(AND(All!$V7="P1",All!$AE7="RMS"),Ruler!L$6,IF(AND(All!$V7="P2",All!$AE7="RMS"),Ruler!L$15,IF(AND(All!$V7="P3",All!$AE7="RMS"),Ruler!L$16,IF(AND(All!$V7="P4",All!$AE7="RMS"),Ruler!L$17,IF(AND(All!$V7="P5",All!$AE7="RMS"),Ruler!L$18,IF(AND(All!$V7="P6",All!$AE7="RMS"),Ruler!L$19,IF(AND(All!$V7="P7",All!$AE7="RMS"),Ruler!L$20,IF(AND(All!$V7="P8",All!$AE7="RMS"),Ruler!L$21,IF(AND(All!$V7="P9",All!$AE7="RMS"),Ruler!L$22,IF(AND(All!$V7="P1",All!$AE7="RSS"),Ruler!L$6,IF(AND(All!$V7="P2",All!$AE7="RSS"),Ruler!L$23,IF(AND(All!$V7="P3",All!$AE7="RSS"),Ruler!L$24,IF(AND(All!$V7="P4",All!$AE7="RSS"),Ruler!L$25,IF(AND(All!$V7="P5",All!$AE7="RSS"),Ruler!L$26,IF(AND(All!$V7="P6",All!$AE7="RSS"),Ruler!L$27,IF(AND(All!$V7="P7",All!$AE7="RSS"),Ruler!L$28,IF(AND(All!$V7="P8",All!$AE7="RSS"),Ruler!L$29,IF(AND(All!$V7="P9",All!$AE7="RSS"),Ruler!L$30,0))))))))))))))))))))))))))) -> 3 | ... CI7: =IF(AND(All!$V7="P1",All!$AE7="RDP"),Ruler!AB$6,IF(AND(All!$V7="P2",All!$AE7="RDP"),Ruler!AB$7,IF(AND(All!$V7="P3",All!$AE7="RDP"),Ruler!AB$8,IF(AND(All!$V7="P4",All!$AE7="RDP"),Ruler!AB$9,IF(AND(All!$V7="P5",All!$AE7="RDP"),Ruler!AB$10,IF(AND(All!$V7="P6",All!$AE7="RDP"),Ruler!AB$11,IF(AND(All!$V7="P7",All!$AE7="RDP"),Ruler!AB$12,IF(AND(All!$V7="P8",All!$AE7="RDP"),Ruler!AB$13,IF(AND(All!$V7="P9",All!$AE7="RDP"),Ruler!AB$14,IF(AND(All!$V7="P1",All!$AE7="RMS"),Ruler!AB$6,IF(AND(All!$V7="P2",All!$AE7="RMS"),Ruler!AB$15,IF(AND(All!$V7="P3",All!$AE7="RMS"),Ruler!AB$16,IF(AND(All!$V7="P4",All!$AE7="RMS"),Ruler!AB$17,IF(AND(All!$V7="P5",All!$AE7="RMS"),Ruler!AB$18,IF(AND(All!$V7="P6",All!$AE7="RMS"),Ruler!AB$19,IF(AND(All!$V7="P7",All!$AE7="RMS"),Ruler!AB$20,IF(AND(All!$V7="P8",All!$AE7="RMS"),Ruler!AB$21,IF(AND(All!$V7="P9",All!$AE7="RMS"),Ruler!AB$22,IF(AND(All!$V7="P1",All!$AE7="RSS"),Ruler!AB$6,IF(AND(All!$V7="P2",All!$AE7="RSS"),Ruler!AB$23,IF(AND(All!$V7="P3",All!$AE7="RSS"),Ruler!AB$24,IF(AND(All!$V7="P4",All!$AE7="RSS"),Ruler!AB$25,IF(AND(All!$V7="P5",All!$AE7="RSS"),Ruler!AB$26,IF(AND(All!$V7="P6",All!$AE7="RSS"),Ruler!AB$27,IF(AND(All!$V7="P7",All!$AE7="RSS"),Ruler!AB$28,IF(AND(All!$V7="P8",All!$AE7="RSS"),Ruler!AB$29,IF(AND(All!$V7="P9",All!$AE7="RSS"),Ruler!AB$30,0))))))))))))))))))))))))))) -> 2 | CJ7: =Table9[[#This Row],[R-B1]]-Table9[[#This Row],[B1]] -> 1 | CK7: =Table9[[#This Row],[R-B2]]-Table9[[#This Row],[B2]] -> 1 | CL7: =Table9[[#This Row],[R-B3]]-Table9[[#This Row],[B3]] -> 1 | CM7: =Table9[[#This Row],[R-B4]]-Table9[[#This Row],[B4]] -> 0 | CN7: =Table9[[#This Row],[R-B5]]-Table9[[#This Row],[B5]] -> 0 | CO7: =Table9[[#This Row],[R-B6]]-Table9[[#This Row],[B6]] -> 1 | CP7: =Table9[[#This Row],[R-B7]]-Table9[[#This Row],[B7]] -> 1 | CQ7: =Table9[[#This Row],[R-B8]]-Table9[[#This Row],[B8]] -> 1 | CR7: =Table9[[#This Row],[R-B9]]-Table9[[#This Row],[B9]] -> 0 | CS7: =Table9[[#This Row],[R-B10]]-Table9[[#This Row],[B10]] -> 1 | CT7: =Table9[[#This Row],[R-B11]]-Table9[[#This Row],[B11]] -> 1 | CU7: =Table9[[#This Row],[R-B12]]-Table9[[#This Row],[B12]] -> 1 | CV7: =Table9[[#This Row],[R-K1]]-Table9[[#This Row],[K1]] -> 1 | CW7: =Table9[[#This Row],[R-K2]]-Table9[[#This Row],[K2]] -> 1 | CX7: =Table9[[#This Row],[R-K3]]-Table9[[#This Row],[K3]] -> 1 | CY7: =Table9[[#This Row],[R-K4]]-Table9[[#This Row],[K4]] -> 0 | CZ7: =Table9[[#This Row],[R-K5]]-Table9[[#This Row],[K5]] -> 1 | DA7: =Table9[[#This Row],[R-P1]]-Table9[[#This Row],[P1]] -> 1 | DB7: =Table9[[#This Row],[R-P2]]-Table9[[#This Row],[P2]] -> 0 | DC7: =Table9[[#This Row],[R-P3]]-Table9[[#This Row],[P3]] -> 0 | DD7: =Table9[[#This Row],[R-P4]]-Table9[[#This Row],[P4]] -> 1 | DE7: =Table9[[#This Row],[R-P5]]-Table9[[#This Row],[P5]] -> 0 | DF7: =Table9[[#This Row],[R-E1]]-Table9[[#This Row],[E1]] -> 1 | DG7: =Table9[[#This Row],[R-E2]]-Table9[[#This Row],[E2]] -> 1 | DH7: =COUNTIF(Table9[[#This Row],[G-B1]:[G-B12]],"<=0")/12*100 -> 25 | DI7: =COUNTIF(Table9[[#This Row],[G-K1]:[G-K5]],"<=0")/5*100 -> 20 | DJ7: =COUNTIF(Table9[[#This Row],[G-P1]:[G-P5]],"<=0")/5*100 -> 60 | DK7: =COUNTIF(Table9[[#This Row],[G-E1]:[G-E2]],"<=0")/2*100 -> 0 | DL7: =IF(AE7="RDP",(COUNTIF(Table9[[#This Row],[G-B3]],"<=0")+COUNTIF(Table9[[#This Row],[G-B4]],"<=0")+COUNTIF(Table9[[#This Row],[G-B7]],"<=0")+COUNTIF(Table9[[#This Row],[G-B11]],"<=0")+COUNTIF(Table9[[#This Row],[G-K2]],"<=0"))/5*100,IF(AE7="RMS",(COUNTIF(Table9[[#This Row],[G-B4]],"<=0")+COUNTIF(Table9[[#This Row],[G-B5]],"<=0")+COUNTIF(Table9[[#This Row],[G-B10]],"<=0")+COUNTIF(Table9[[#This Row],[G-B12]],"<=0")+COUNTIF(Table9[[#This Row],[G-K2]],"<=0"))/5*100,IF(AE7="RSS",(COUNTIF(Table9[[#This Row],[G-B1]],"<=0")+COUNTIF(Table9[[#This Row],[G-B2]],"<=0")+COUNTIF(Table9[[#This Row],[G-B6]],"<=0")+COUNTIF(Table9[[#This Row],[G-B11]],"<=0")+COUNTIF(Table9[[#This Row],[G-B12]],"<=0"))/5*100,0))) -> 0 | DM7: 100 | DN7: 80 | DO7: 100 | DP7: 100 | DQ7: 100 | DR7: 25 | DS7: 20 | DT7: 60 | DU7: 0 | DV7: 0 | DW7: 25 | DX7: 0 | DY7: 20 | DZ7: 0 | EA7: 0 | EB7: Subrat Kumar Dhal | EC7: Rakesh Ranjan | ED7: Norhana Harun
B8: 5 | C8: No | E8: Ahmad Aiman Kamarul Bahrin | G8: =($T$1-H8)/365 -> 26.82091 | H8: 36526 | I8: M | J8: Malaysia | K8: DPE | L8: SBA | M8: SBA | O8: UPTREX | Q8: Permanent | V8: P1 | X8: =($T$1-Table9[[#This Row],[Date of Appointment to Current Grade]])/365 -> 126.89214 | BL8: =IF(AND(All!$V8="P1",All!$AE8="RDP"),Ruler!E$6,IF(AND(All!$V8="P2",All!$AE8="RDP"),Ruler!E$7,IF(AND(All!$V8="P3",All!$AE8="RDP"),Ruler!E$8,IF(AND(All!$V8="P4",All!$AE8="RDP"),Ruler!E$9,IF(AND(All!$V8="P5",All!$AE8="RDP"),Ruler!E$10,IF(AND(All!$V8="P6",All!$AE8="RDP"),Ruler!E$11,IF(AND(All!$V8="P7",All!$AE8="RDP"),Ruler!E$12,IF(AND(All!$V8="P8",All!$AE8="RDP"),Ruler!E$13,IF(AND(All!$V8="P9",All!$AE8="RDP"),Ruler!E$14,IF(AND(All!$V8="P1",All!$AE8="RMS"),Ruler!E$6,IF(AND(All!$V8="P2",All!$AE8="RMS"),Ruler!E$15,IF(AND(All!$V8="P3",All!$AE8="RMS"),Ruler!E$16,IF(AND(All!$V8="P4",All!$AE8="RMS"),Ruler!E$17,IF(AND(All!$V8="P5",All!$AE8="RMS"),Ruler!E$18,IF(AND(All!$V8="P6",All!$AE8="RMS"),Ruler!E$19,IF(AND(All!$V8="P7",All!$AE8="RMS"),Ruler!E$20,IF(AND(All!$V8="P8",All!$AE8="RMS"),Ruler!E$21,IF(AND(All!$V8="P9",All!$AE8="RMS"),Ruler!E$22,IF(AND(All!$V8="P1",All!$AE8="RSS"),Ruler!E$6,IF(AND(All!$V8="P2",All!$AE8="RSS"),Ruler!E$23,IF(AND(All!$V8="P3",All!$AE8="RSS"),Ruler!E$24,IF(AND(All!$V8="P4",All!$AE8="RSS"),Ruler!E$25,IF(AND(All!$V8="P5",All!$AE8="RSS"),Ruler!E$26,IF(AND(All!$V8="P6",All!$AE8="RSS"),Ruler!E$27,IF(AND(All!$V8="P7",All!$AE8="RSS"),Ruler!E$28,IF(AND(All!$V8="P8",All!$AE8="RSS"),Ruler!E$29,IF(AND(All!$V8="P9",All!$AE8="RSS"),Ruler!E$30,0))))))))))))))))))))))))))) -> 0 | BM8: =IF(AND(All!$V8="P1",All!$AE8="RDP"),Ruler!F$6,IF(AND(All!$V8="P2",All!$AE8="RDP"),Ruler!F$7,IF(AND(All!$V8="P3",All!$AE8="RDP"),Ruler!F$8,IF(AND(All!$V8="P4",All!$AE8="RDP"),Ruler!F$9,IF(AND(All!$V8="P5",All!$AE8="RDP"),Ruler!F$10,IF(AND(All!$V8="P6",All!$AE8="RDP"),Ruler!F$11,IF(AND(All!$V8="P7",All!$AE8="RDP"),Ruler!F$12,IF(AND(All!$V8="P8",All!$AE8="RDP"),Ruler!F$13,IF(AND(All!$V8="P9",All!$AE8="RDP"),Ruler!F$14,IF(AND(All!$V8="P1",All!$AE8="RMS"),Ruler!F$6,IF(AND(All!$V8="P2",All!$AE8="RMS"),Ruler!F$15,IF(AND(All!$V8="P3",All!$AE8="RMS"),Ruler!F$16,IF(AND(All!$V8="P4",All!$AE8="RMS"),Ruler!F$17,IF(AND(All!$V8="P5",All!$AE8="RMS"),Ruler!F$18,IF(AND(All!$V8="P6",All!$AE8="RMS"),Ruler!F$19,IF(AND(All!$V8="P7",All!$AE8="RMS"),Ruler!F$20,IF(AND(All!$V8="P8",All!$AE8="RMS"),Ruler!F$21,IF(AND(All!$V8="P9",All!$AE8="RMS"),Ruler!F$22,IF(AND(All!$V8="P1",All!$AE8="RSS"),Ruler!F$6,IF(AND(All!$V8="P2",All!$AE8="RSS"),Ruler!F$23,IF(AND(All!$V8="P3",All!$AE8="RSS"),Ruler!F$24,IF(AND(All!$V8="P4",All!$AE8="RSS"),Ruler!F$25,IF(AND(All!$V8="P5",All!$AE8="RSS"),Ruler!F$26,IF(AND(All!$V8="P6",All!$AE8="RSS"),Ruler!F$27,IF(AND(All!$V8="P7",All!$AE8="RSS"),Ruler!F$28,IF(AND(All!$V8="P8",All!$AE8="RSS"),Ruler!F$29,IF(AND(All!$V8="P9",All!$AE8="RSS"),Ruler!F$30,0))))))))))))))))))))))))))) -> 0 | BN8: =IF(AND(All!$V8="P1",All!$AE8="RDP"),Ruler!G$6,IF(AND(All!$V8="P2",All!$AE8="RDP"),Ruler!G$7,IF(AND(All!$V8="P3",All!$AE8="RDP"),Ruler!G$8,IF(AND(All!$V8="P4",All!$AE8="RDP"),Ruler!G$9,IF(AND(All!$V8="P5",All!$AE8="RDP"),Ruler!G$10,IF(AND(All!$V8="P6",All!$AE8="RDP"),Ruler!G$11,IF(AND(All!$V8="P7",All!$AE8="RDP"),Ruler!G$12,IF(AND(All!$V8="P8",All!$AE8="RDP"),Ruler!G$13,IF(AND(All!$V8="P9",All!$AE8="RDP"),Ruler!G$14,IF(AND(All!$V8="P1",All!$AE8="RMS"),Ruler!G$6,IF(AND(All!$V8="P2",All!$AE8="RMS"),Ruler!G$15,IF(AND(All!$V8="P3",All!$AE8="RMS"),Ruler!G$16,IF(AND(All!$V8="P4",All!$AE8="RMS"),Ruler!G$17,IF(AND(All!$V8="P5",All!$AE8="RMS"),Ruler!G$18,IF(AND(All!$V8="P6",All!$AE8="RMS"),Ruler!G$19,IF(AND(All!$V8="P7",All!$AE8="RMS"),Ruler!G$20,IF(AND(All!$V8="P8",All!$AE8="RMS"),Ruler!G$21,IF(AND(All!$V8="P9",All!$AE8="RMS"),Ruler!G$22,IF(AND(All!$V8="P1",All!$AE8="RSS"),Ruler!G$6,IF(AND(All!$V8="P2",All!$AE8="RSS"),Ruler!G$23,IF(AND(All!$V8="P3",All!$AE8="RSS"),Ruler!G$24,IF(AND(All!$V8="P4",All!$AE8="RSS"),Ruler!G$25,IF(AND(All!$V8="P5",All!$AE8="RSS"),Ruler!G$26,IF(AND(All!$V8="P6",All!$AE8="RSS"),Ruler!G$27,IF(AND(All!$V8="P7",All!$AE8="RSS"),Ruler!G$28,IF(AND(All!$V8="P8",All!$AE8="RSS"),Ruler!G$29,IF(AND(All!$V8="P9",All!$AE8="RSS"),Ruler!G$30,0))))))))))))))))))))))))))) -> 0 | BO8: =IF(AND(All!$V8="P1",All!$AE8="RDP"),Ruler!H$6,IF(AND(All!$V8="P2",All!$AE8="RDP"),Ruler!H$7,IF(AND(All!$V8="P3",All!$AE8="RDP"),Ruler!H$8,IF(AND(All!$V8="P4",All!$AE8="RDP"),Ruler!H$9,IF(AND(All!$V8="P5",All!$AE8="RDP"),Ruler!H$10,IF(AND(All!$V8="P6",All!$AE8="RDP"),Ruler!H$11,IF(AND(All!$V8="P7",All!$AE8="RDP"),Ruler!H$12,IF(AND(All!$V8="P8",All!$AE8="RDP"),Ruler!H$13,IF(AND(All!$V8="P9",All!$AE8="RDP"),Ruler!H$14,IF(AND(All!$V8="P1",All!$AE8="RMS"),Ruler!H$6,IF(AND(All!$V8="P2",All!$AE8="RMS"),Ruler!H$15,IF(AND(All!$V8="P3",All!$AE8="RMS"),Ruler!H$16,IF(AND(All!$V8="P4",All!$AE8="RMS"),Ruler!H$17,IF(AND(All!$V8="P5",All!$AE8="RMS"),Ruler!H$18,IF(AND(All!$V8="P6",All!$AE8="RMS"),Ruler!H$19,IF(AND(All!$V8="P7",All!$AE8="RMS"),Ruler!H$20,IF(AND(All!$V8="P8",All!$AE8="RMS"),Ruler!H$21,IF(AND(All!$V8="P9",All!$AE8="RMS"),Ruler!H$22,IF(AND(All!$V8="P1",All!$AE8="RSS"),Ruler!H$6,IF(AND(All!$V8="P2",All!$AE8="RSS"),Ruler!H$23,IF(AND(All!$V8="P3",All!$AE8="RSS"),Ruler!H$24,IF(AND(All!$V8="P4",All!$AE8="RSS"),Ruler!H$25,IF(AND(All!$V8="P5",All!$AE8="RSS"),Ruler!H$26,IF(AND(All!$V8="P6",All!$AE8="RSS"),Ruler!H$27,IF(AND(All!$V8="P7",All!$AE8="RSS"),Ruler!H$28,IF(AND(All!$V8="P8",All!$AE8="RSS"),Ruler!H$29,IF(AND(All!$V8="P9",All!$AE8="RSS"),Ruler!H$30,0))))))))))))))))))))))))))) -> 0 | BP8: =IF(AND(All!$V8="P1",All!$AE8="RDP"),Ruler!I$6,IF(AND(All!$V8="P2",All!$AE8="RDP"),Ruler!I$7,IF(AND(All!$V8="P3",All!$AE8="RDP"),Ruler!I$8,IF(AND(All!$V8="P4",All!$AE8="RDP"),Ruler!I$9,IF(AND(All!$V8="P5",All!$AE8="RDP"),Ruler!I$10,IF(AND(All!$V8="P6",All!$AE8="RDP"),Ruler!I$11,IF(AND(All!$V8="P7",All!$AE8="RDP"),Ruler!I$12,IF(AND(All!$V8="P8",All!$AE8="RDP"),Ruler!I$13,IF(AND(All!$V8="P9",All!$AE8="RDP"),Ruler!I$14,IF(AND(All!$V8="P1",All!$AE8="RMS"),Ruler!I$6,IF(AND(All!$V8="P2",All!$AE8="RMS"),Ruler!I$15,IF(AND(All!$V8="P3",All!$AE8="RMS"),Ruler!I$16,IF(AND(All!$V8="P4",All!$AE8="RMS"),Ruler!I$17,IF(AND(All!$V8="P5",All!$AE8="RMS"),Ruler!I$18,IF(AND(All!$V8="P6",All!$AE8="RMS"),Ruler!I$19,IF(AND(All!$V8="P7",All!$AE8="RMS"),Ruler!I$20,IF(AND(All!$V8="P8",All!$AE8="RMS"),Ruler!I$21,IF(AND(All!$V8="P9",All!$AE8="RMS"),Ruler!I$22,IF(AND(All!$V8="P1",All!$AE8="RSS"),Ruler!I$6,IF(AND(All!$V8="P2",All!$AE8="RSS"),Ruler!I$23,IF(AND(All!$V8="P3",All!$AE8="RSS"),Ruler!I$24,IF(AND(All!$V8="P4",All!$AE8="RSS"),Ruler!I$25,IF(AND(All!$V8="P5",All!$AE8="RSS"),Ruler!I$26,IF(AND(All!$V8="P6",All!$AE8="RSS"),Ruler!I$27,IF(AND(All!$V8="P7",All!$AE8="RSS"),Ruler!I$28,IF(AND(All!$V8="P8",All!$AE8="RSS"),Ruler!I$29,IF(AND(All!$V8="P9",All!$AE8="RSS"),Ruler!I$30,0))))))))))))))))))))))))))) -> 0 | BQ8: =IF(AND(All!$V8="P1",All!$AE8="RDP"),Ruler!J$6,IF(AND(All!$V8="P2",All!$AE8="RDP"),Ruler!J$7,IF(AND(All!$V8="P3",All!$AE8="RDP"),Ruler!J$8,IF(AND(All!$V8="P4",All!$AE8="RDP"),Ruler!J$9,IF(AND(All!$V8="P5",All!$AE8="RDP"),Ruler!J$10,IF(AND(All!$V8="P6",All!$AE8="RDP"),Ruler!J$11,IF(AND(All!$V8="P7",All!$AE8="RDP"),Ruler!J$12,IF(AND(All!$V8="P8",All!$AE8="RDP"),Ruler!J$13,IF(AND(All!$V8="P9",All!$AE8="RDP"),Ruler!J$14,IF(AND(All!$V8="P1",All!$AE8="RMS"),Ruler!J$6,IF(AND(All!$V8="P2",All!$AE8="RMS"),Ruler!J$15,IF(AND(All!$V8="P3",All!$AE8="RMS"),Ruler!J$16,IF(AND(All!$V8="P4",All!$AE8="RMS"),Ruler!J$17,IF(AND(All!$V8="P5",All!$AE8="RMS"),Ruler!J$18,IF(AND(All!$V8="P6",All!$AE8="RMS"),Ruler!J$19,IF(AND(All!$V8="P7",All!$AE8="RMS"),Ruler!J$20,IF(AND(All!$V8="P8",All!$AE8="RMS"),Ruler!J$21,IF(AND(All!$V8="P9",All!$AE8="RMS"),Ruler!J$22,IF(AND(All!$V8="P1",All!$AE8="RSS"),Ruler!J$6,IF(AND(All!$V8="P2",All!$AE8="RSS"),Ruler!J$23,IF(AND(All!$V8="P3",All!$AE8="RSS"),Ruler!J$24,IF(AND(All!$V8="P4",All!$AE8="RSS"),Ruler!J$25,IF(AND(All!$V8="P5",All!$AE8="RSS"),Ruler!J$26,IF(AND(All!$V8="P6",All!$AE8="RSS"),Ruler!J$27,IF(AND(All!$V8="P7",All!$AE8="RSS"),Ruler!J$28,IF(AND(All!$V8="P8",All!$AE8="RSS"),Ruler!J$29,IF(AND(All!$V8="P9",All!$AE8="RSS"),Ruler!J$30,0))))))))))))))))))))))))))) -> 0 | BR8: =IF(AND(All!$V8="P1",All!$AE8="RDP"),Ruler!K$6,IF(AND(All!$V8="P2",All!$AE8="RDP"),Ruler!K$7,IF(AND(All!$V8="P3",All!$AE8="RDP"),Ruler!K$8,IF(AND(All!$V8="P4",All!$AE8="RDP"),Ruler!K$9,IF(AND(All!$V8="P5",All!$AE8="RDP"),Ruler!K$10,IF(AND(All!$V8="P6",All!$AE8="RDP"),Ruler!K$11,IF(AND(All!$V8="P7",All!$AE8="RDP"),Ruler!K$12,IF(AND(All!$V8="P8",All!$AE8="RDP"),Ruler!K$13,IF(AND(All!$V8="P9",All!$AE8="RDP"),Ruler!K$14,IF(AND(All!$V8="P1",All!$AE8="RMS"),Ruler!K$6,IF(AND(All!$V8="P2",All!$AE8="RMS"),Ruler!K$15,IF(AND(All!$V8="P3",All!$AE8="RMS"),Ruler!K$16,IF(AND(All!$V8="P4",All!$AE8="RMS"),Ruler!K$17,IF(AND(All!$V8="P5",All!$AE8="RMS"),Ruler!K$18,IF(AND(All!$V8="P6",All!$AE8="RMS"),Ruler!K$19,IF(AND(All!$V8="P7",All!$AE8="RMS"),Ruler!K$20,IF(AND(All!$V8="P8",All!$AE8="RMS"),Ruler!K$21,IF(AND(All!$V8="P9",All!$AE8="RMS"),Ruler!K$22,IF(AND(All!$V8="P1",All!$AE8="RSS"),Ruler!K$6,IF(AND(All!$V8="P2",All!$AE8="RSS"),Ruler!K$23,IF(AND(All!$V8="P3",All!$AE8="RSS"),Ruler!K$24,IF(AND(All!$V8="P4",All!$AE8="RSS"),Ruler!K$25,IF(AND(All!$V8="P5",All!$AE8="RSS"),Ruler!K$26,IF(AND(All!$V8="P6",All!$AE8="RSS"),Ruler!K$27,IF(AND(All!$V8="P7",All!$AE8="RSS"),Ruler!K$28,IF(AND(All!$V8="P8",All!$AE8="RSS"),Ruler!K$29,IF(AND(All!$V8="P9",All!$AE8="RSS"),Ruler!K$30,0))))))))))))))))))))))))))) -> 0 | BS8: =IF(AND(All!$V8="P1",All!$AE8="RDP"),Ruler!L$6,IF(AND(All!$V8="P2",All!$AE8="RDP"),Ruler!L$7,IF(AND(All!$V8="P3",All!$AE8="RDP"),Ruler!L$8,IF(AND(All!$V8="P4",All!$AE8="RDP"),Ruler!L$9,IF(AND(All!$V8="P5",All!$AE8="RDP"),Ruler!L$10,IF(AND(All!$V8="P6",All!$AE8="RDP"),Ruler!L$11,IF(AND(All!$V8="P7",All!$AE8="RDP"),Ruler!L$12,IF(AND(All!$V8="P8",All!$AE8="RDP"),Ruler!L$13,IF(AND(All!$V8="P9",All!$AE8="RDP"),Ruler!L$14,IF(AND(All!$V8="P1",All!$AE8="RMS"),Ruler!L$6,IF(AND(All!$V8="P2",All!$AE8="RMS"),Ruler!L$15,IF(AND(All!$V8="P3",All!$AE8="RMS"),Ruler!L$16,IF(AND(All!$V8="P4",All!$AE8="RMS"),Ruler!L$17,IF(AND(All!$V8="P5",All!$AE8="RMS"),Ruler!L$18,IF(AND(All!$V8="P6",All!$AE8="RMS"),Ruler!L$19,IF(AND(All!$V8="P7",All!$AE8="RMS"),Ruler!L$20,IF(AND(All!$V8="P8",All!$AE8="RMS"),Ruler!L$21,IF(AND(All!$V8="P9",All!$AE8="RMS"),Ruler!L$22,IF(AND(All!$V8="P1",All!$AE8="RSS"),Ruler!L$6,IF(AND(All!$V8="P2",All!$AE8="RSS"),Ruler!L$23,IF(AND(All!$V8="P3",All!$AE8="RSS"),Ruler!L$24,IF(AND(All!$V8="P4",All!$AE8="RSS"),Ruler!L$25,IF(AND(All!$V8="P5",All!$AE8="RSS"),Ruler!L$26,IF(AND(All!$V8="P6",All!$AE8="RSS"),Ruler!L$27,IF(AND(All!$V8="P7",All!$AE8="RSS"),Ruler!L$28,IF(AND(All!$V8="P8",All!$AE8="RSS"),Ruler!L$29,IF(AND(All!$V8="P9",All!$AE8="RSS"),Ruler!L$30,0))))))))))))))))))))))))))) -> 0 | ... CI8: =IF(AND(All!$V8="P1",All!$AE8="RDP"),Ruler!AB$6,IF(AND(All!$V8="P2",All!$AE8="RDP"),Ruler!AB$7,IF(AND(All!$V8="P3",All!$AE8="RDP"),Ruler!AB$8,IF(AND(All!$V8="P4",All!$AE8="RDP"),Ruler!AB$9,IF(AND(All!$V8="P5",All!$AE8="RDP"),Ruler!AB$10,IF(AND(All!$V8="P6",All!$AE8="RDP"),Ruler!AB$11,IF(AND(All!$V8="P7",All!$AE8="RDP"),Ruler!AB$12,IF(AND(All!$V8="P8",All!$AE8="RDP"),Ruler!AB$13,IF(AND(All!$V8="P9",All!$AE8="RDP"),Ruler!AB$14,IF(AND(All!$V8="P1",All!$AE8="RMS"),Ruler!AB$6,IF(AND(All!$V8="P2",All!$AE8="RMS"),Ruler!AB$15,IF(AND(All!$V8="P3",All!$AE8="RMS"),Ruler!AB$16,IF(AND(All!$V8="P4",All!$AE8="RMS"),Ruler!AB$17,IF(AND(All!$V8="P5",All!$AE8="RMS"),Ruler!AB$18,IF(AND(All!$V8="P6",All!$AE8="RMS"),Ruler!AB$19,IF(AND(All!$V8="P7",All!$AE8="RMS"),Ruler!AB$20,IF(AND(All!$V8="P8",All!$AE8="RMS"),Ruler!AB$21,IF(AND(All!$V8="P9",All!$AE8="RMS"),Ruler!AB$22,IF(AND(All!$V8="P1",All!$AE8="RSS"),Ruler!AB$6,IF(AND(All!$V8="P2",All!$AE8="RSS"),Ruler!AB$23,IF(AND(All!$V8="P3",All!$AE8="RSS"),Ruler!AB$24,IF(AND(All!$V8="P4",All!$AE8="RSS"),Ruler!AB$25,IF(AND(All!$V8="P5",All!$AE8="RSS"),Ruler!AB$26,IF(AND(All!$V8="P6",All!$AE8="RSS"),Ruler!AB$27,IF(AND(All!$V8="P7",All!$AE8="RSS"),Ruler!AB$28,IF(AND(All!$V8="P8",All!$AE8="RSS"),Ruler!AB$29,IF(AND(All!$V8="P9",All!$AE8="RSS"),Ruler!AB$30,0))))))))))))))))))))))))))) -> 0 | CJ8: =Table9[[#This Row],[R-B1]]-Table9[[#This Row],[B1]] -> 0 | CK8: =Table9[[#This Row],[R-B2]]-Table9[[#This Row],[B2]] -> 0 | CL8: =Table9[[#This Row],[R-B3]]-Table9[[#This Row],[B3]] -> 0 | CM8: =Table9[[#This Row],[R-B4]]-Table9[[#This Row],[B4]] -> 0 | CN8: =Table9[[#This Row],[R-B5]]-Table9[[#This Row],[B5]] -> 0 | CO8: =Table9[[#This Row],[R-B6]]-Table9[[#This Row],[B6]] -> 0 | CP8: =Table9[[#This Row],[R-B7]]-Table9[[#This Row],[B7]] -> 0 | CQ8: =Table9[[#This Row],[R-B8]]-Table9[[#This Row],[B8]] -> 0 | CR8: =Table9[[#This Row],[R-B9]]-Table9[[#This Row],[B9]] -> 0 | CS8: =Table9[[#This Row],[R-B10]]-Table9[[#This Row],[B10]] -> 0 | CT8: =Table9[[#This Row],[R-B11]]-Table9[[#This Row],[B11]] -> 0 | CU8: =Table9[[#This Row],[R-B12]]-Table9[[#This Row],[B12]] -> 0 | CV8: =Table9[[#This Row],[R-K1]]-Table9[[#This Row],[K1]] -> 0 | CW8: =Table9[[#This Row],[R-K2]]-Table9[[#This Row],[K2]] -> 0 | CX8: =Table9[[#This Row],[R-K3]]-Table9[[#This Row],[K3]] -> 0 | CY8: =Table9[[#This Row],[R-K4]]-Table9[[#This Row],[K4]] -> 0 | CZ8: =Table9[[#This Row],[R-K5]]-Table9[[#This Row],[K5]] -> 0 | DA8: =Table9[[#This Row],[R-P1]]-Table9[[#This Row],[P1]] -> 0 | DB8: =Table9[[#This Row],[R-P2]]-Table9[[#This Row],[P2]] -> 0 | DC8: =Table9[[#This Row],[R-P3]]-Table9[[#This Row],[P3]] -> 0 | DD8: =Table9[[#This Row],[R-P4]]-Table9[[#This Row],[P4]] -> 0 | DE8: =Table9[[#This Row],[R-P5]]-Table9[[#This Row],[P5]] -> 0 | DF8: =Table9[[#This Row],[R-E1]]-Table9[[#This Row],[E1]] -> 0 | DG8: =Table9[[#This Row],[R-E2]]-Table9[[#This Row],[E2]] -> 0 | DH8: =COUNTIF(Table9[[#This Row],[G-B1]:[G-B12]],"<=0")/12*100 -> 100 | DI8: =COUNTIF(Table9[[#This Row],[G-K1]:[G-K5]],"<=0")/5*100 -> 100 | DJ8: =COUNTIF(Table9[[#This Row],[G-P1]:[G-P5]],"<=0")/5*100 -> 100 | DK8: =COUNTIF(Table9[[#This Row],[G-E1]:[G-E2]],"<=0")/2*100 -> 100 | DL8: =IF(AE8="RDP",(COUNTIF(Table9[[#This Row],[G-B3]],"<=0")+COUNTIF(Table9[[#This Row],[G-B4]],"<=0")+COUNTIF(Table9[[#This Row],[G-B7]],"<=0")+COUNTIF(Table9[[#This Row],[G-B11]],"<=0")+COUNTIF(Table9[[#This Row],[G-K2]],"<=0"))/5*100,IF(AE8="RMS",(COUNTIF(Table9[[#This Row],[G-B4]],"<=0")+COUNTIF(Table9[[#This Row],[G-B5]],"<=0")+COUNTIF(Table9[[#This Row],[G-B10]],"<=0")+COUNTIF(Table9[[#This Row],[G-B12]],"<=0")+COUNTIF(Table9[[#This Row],[G-K2]],"<=0"))/5*100,IF(AE8="RSS",(COUNTIF(Table9[[#This Row],[G-B1]],"<=0")+COUNTIF(Table9[[#This Row],[G-B2]],"<=0")+COUNTIF(Table9[[#This Row],[G-B6]],"<=0")+COUNTIF(Table9[[#This Row],[G-B11]],"<=0")+COUNTIF(Table9[[#This Row],[G-B12]],"<=0"))/5*100,0))) -> 0
B9: 6 | C9: No | E9: Ahmad Anas Ahmad Yunus | G9: =($T$1-H9)/365 -> 26.82091 | H9: 36526 | I9: M | J9: Malaysia | K9: DPE | L9: RMS | M9: PMA | O9: UPTREX | Q9: Permanent | V9: P1 | X9: =($T$1-Table9[[#This Row],[Date of Appointment to Current Grade]])/365 -> 126.89214 | Z9: PMA | BL9: =IF(AND(All!$V9="P1",All!$AE9="RDP"),Ruler!E$6,IF(AND(All!$V9="P2",All!$AE9="RDP"),Ruler!E$7,IF(AND(All!$V9="P3",All!$AE9="RDP"),Ruler!E$8,IF(AND(All!$V9="P4",All!$AE9="RDP"),Ruler!E$9,IF(AND(All!$V9="P5",All!$AE9="RDP"),Ruler!E$10,IF(AND(All!$V9="P6",All!$AE9="RDP"),Ruler!E$11,IF(AND(All!$V9="P7",All!$AE9="RDP"),Ruler!E$12,IF(AND(All!$V9="P8",All!$AE9="RDP"),Ruler!E$13,IF(AND(All!$V9="P9",All!$AE9="RDP"),Ruler!E$14,IF(AND(All!$V9="P1",All!$AE9="RMS"),Ruler!E$6,IF(AND(All!$V9="P2",All!$AE9="RMS"),Ruler!E$15,IF(AND(All!$V9="P3",All!$AE9="RMS"),Ruler!E$16,IF(AND(All!$V9="P4",All!$AE9="RMS"),Ruler!E$17,IF(AND(All!$V9="P5",All!$AE9="RMS"),Ruler!E$18,IF(AND(All!$V9="P6",All!$AE9="RMS"),Ruler!E$19,IF(AND(All!$V9="P7",All!$AE9="RMS"),Ruler!E$20,IF(AND(All!$V9="P8",All!$AE9="RMS"),Ruler!E$21,IF(AND(All!$V9="P9",All!$AE9="RMS"),Ruler!E$22,IF(AND(All!$V9="P1",All!$AE9="RSS"),Ruler!E$6,IF(AND(All!$V9="P2",All!$AE9="RSS"),Ruler!E$23,IF(AND(All!$V9="P3",All!$AE9="RSS"),Ruler!E$24,IF(AND(All!$V9="P4",All!$AE9="RSS"),Ruler!E$25,IF(AND(All!$V9="P5",All!$AE9="RSS"),Ruler!E$26,IF(AND(All!$V9="P6",All!$AE9="RSS"),Ruler!E$27,IF(AND(All!$V9="P7",All!$AE9="RSS"),Ruler!E$28,IF(AND(All!$V9="P8",All!$AE9="RSS"),Ruler!E$29,IF(AND(All!$V9="P9",All!$AE9="RSS"),Ruler!E$30,0))))))))))))))))))))))))))) -> 0 | BM9: =IF(AND(All!$V9="P1",All!$AE9="RDP"),Ruler!F$6,IF(AND(All!$V9="P2",All!$AE9="RDP"),Ruler!F$7,IF(AND(All!$V9="P3",All!$AE9="RDP"),Ruler!F$8,IF(AND(All!$V9="P4",All!$AE9="RDP"),Ruler!F$9,IF(AND(All!$V9="P5",All!$AE9="RDP"),Ruler!F$10,IF(AND(All!$V9="P6",All!$AE9="RDP"),Ruler!F$11,IF(AND(All!$V9="P7",All!$AE9="RDP"),Ruler!F$12,IF(AND(All!$V9="P8",All!$AE9="RDP"),Ruler!F$13,IF(AND(All!$V9="P9",All!$AE9="RDP"),Ruler!F$14,IF(AND(All!$V9="P1",All!$AE9="RMS"),Ruler!F$6,IF(AND(All!$V9="P2",All!$AE9="RMS"),Ruler!F$15,IF(AND(All!$V9="P3",All!$AE9="RMS"),Ruler!F$16,IF(AND(All!$V9="P4",All!$AE9="RMS"),Ruler!F$17,IF(AND(All!$V9="P5",All!$AE9="RMS"),Ruler!F$18,IF(AND(All!$V9="P6",All!$AE9="RMS"),Ruler!F$19,IF(AND(All!$V9="P7",All!$AE9="RMS"),Ruler!F$20,IF(AND(All!$V9="P8",All!$AE9="RMS"),Ruler!F$21,IF(AND(All!$V9="P9",All!$AE9="RMS"),Ruler!F$22,IF(AND(All!$V9="P1",All!$AE9="RSS"),Ruler!F$6,IF(AND(All!$V9="P2",All!$AE9="RSS"),Ruler!F$23,IF(AND(All!$V9="P3",All!$AE9="RSS"),Ruler!F$24,IF(AND(All!$V9="P4",All!$AE9="RSS"),Ruler!F$25,IF(AND(All!$V9="P5",All!$AE9="RSS"),Ruler!F$26,IF(AND(All!$V9="P6",All!$AE9="RSS"),Ruler!F$27,IF(AND(All!$V9="P7",All!$AE9="RSS"),Ruler!F$28,IF(AND(All!$V9="P8",All!$AE9="RSS"),Ruler!F$29,IF(AND(All!$V9="P9",All!$AE9="RSS"),Ruler!F$30,0))))))))))))))))))))))))))) -> 0 | BN9: =IF(AND(All!$V9="P1",All!$AE9="RDP"),Ruler!G$6,IF(AND(All!$V9="P2",All!$AE9="RDP"),Ruler!G$7,IF(AND(All!$V9="P3",All!$AE9="RDP"),Ruler!G$8,IF(AND(All!$V9="P4",All!$AE9="RDP"),Ruler!G$9,IF(AND(All!$V9="P5",All!$AE9="RDP"),Ruler!G$10,IF(AND(All!$V9="P6",All!$AE9="RDP"),Ruler!G$11,IF(AND(All!$V9="P7",All!$AE9="RDP"),Ruler!G$12,IF(AND(All!$V9="P8",All!$AE9="RDP"),Ruler!G$13,IF(AND(All!$V9="P9",All!$AE9="RDP"),Ruler!G$14,IF(AND(All!$V9="P1",All!$AE9="RMS"),Ruler!G$6,IF(AND(All!$V9="P2",All!$AE9="RMS"),Ruler!G$15,IF(AND(All!$V9="P3",All!$AE9="RMS"),Ruler!G$16,IF(AND(All!$V9="P4",All!$AE9="RMS"),Ruler!G$17,IF(AND(All!$V9="P5",All!$AE9="RMS"),Ruler!G$18,IF(AND(All!$V9="P6",All!$AE9="RMS"),Ruler!G$19,IF(AND(All!$V9="P7",All!$AE9="RMS"),Ruler!G$20,IF(AND(All!$V9="P8",All!$AE9="RMS"),Ruler!G$21,IF(AND(All!$V9="P9",All!$AE9="RMS"),Ruler!G$22,IF(AND(All!$V9="P1",All!$AE9="RSS"),Ruler!G$6,IF(AND(All!$V9="P2",All!$AE9="RSS"),Ruler!G$23,IF(AND(All!$V9="P3",All!$AE9="RSS"),Ruler!G$24,IF(AND(All!$V9="P4",All!$AE9="RSS"),Ruler!G$25,IF(AND(All!$V9="P5",All!$AE9="RSS"),Ruler!G$26,IF(AND(All!$V9="P6",All!$AE9="RSS"),Ruler!G$27,IF(AND(All!$V9="P7",All!$AE9="RSS"),Ruler!G$28,IF(AND(All!$V9="P8",All!$AE9="RSS"),Ruler!G$29,IF(AND(All!$V9="P9",All!$AE9="RSS"),Ruler!G$30,0))))))))))))))))))))))))))) -> 0 | BO9: =IF(AND(All!$V9="P1",All!$AE9="RDP"),Ruler!H$6,IF(AND(All!$V9="P2",All!$AE9="RDP"),Ruler!H$7,IF(AND(All!$V9="P3",All!$AE9="RDP"),Ruler!H$8,IF(AND(All!$V9="P4",All!$AE9="RDP"),Ruler!H$9,IF(AND(All!$V9="P5",All!$AE9="RDP"),Ruler!H$10,IF(AND(All!$V9="P6",All!$AE9="RDP"),Ruler!H$11,IF(AND(All!$V9="P7",All!$AE9="RDP"),Ruler!H$12,IF(AND(All!$V9="P8",All!$AE9="RDP"),Ruler!H$13,IF(AND(All!$V9="P9",All!$AE9="RDP"),Ruler!H$14,IF(AND(All!$V9="P1",All!$AE9="RMS"),Ruler!H$6,IF(AND(All!$V9="P2",All!$AE9="RMS"),Ruler!H$15,IF(AND(All!$V9="P3",All!$AE9="RMS"),Ruler!H$16,IF(AND(All!$V9="P4",All!$AE9="RMS"),Ruler!H$17,IF(AND(All!$V9="P5",All!$AE9="RMS"),Ruler!H$18,IF(AND(All!$V9="P6",All!$AE9="RMS"),Ruler!H$19,IF(AND(All!$V9="P7",All!$AE9="RMS"),Ruler!H$20,IF(AND(All!$V9="P8",All!$AE9="RMS"),Ruler!H$21,IF(AND(All!$V9="P9",All!$AE9="RMS"),Ruler!H$22,IF(AND(All!$V9="P1",All!$AE9="RSS"),Ruler!H$6,IF(AND(All!$V9="P2",All!$AE9="RSS"),Ruler!H$23,IF(AND(All!$V9="P3",All!$AE9="RSS"),Ruler!H$24,IF(AND(All!$V9="P4",All!$AE9="RSS"),Ruler!H$25,IF(AND(All!$V9="P5",All!$AE9="RSS"),Ruler!H$26,IF(AND(All!$V9="P6",All!$AE9="RSS"),Ruler!H$27,IF(AND(All!$V9="P7",All!$AE9="RSS"),Ruler!H$28,IF(AND(All!$V9="P8",All!$AE9="RSS"),Ruler!H$29,IF(AND(All!$V9="P9",All!$AE9="RSS"),Ruler!H$30,0))))))))))))))))))))))))))) -> 0 | BP9: =IF(AND(All!$V9="P1",All!$AE9="RDP"),Ruler!I$6,IF(AND(All!$V9="P2",All!$AE9="RDP"),Ruler!I$7,IF(AND(All!$V9="P3",All!$AE9="RDP"),Ruler!I$8,IF(AND(All!$V9="P4",All!$AE9="RDP"),Ruler!I$9,IF(AND(All!$V9="P5",All!$AE9="RDP"),Ruler!I$10,IF(AND(All!$V9="P6",All!$AE9="RDP"),Ruler!I$11,IF(AND(All!$V9="P7",All!$AE9="RDP"),Ruler!I$12,IF(AND(All!$V9="P8",All!$AE9="RDP"),Ruler!I$13,IF(AND(All!$V9="P9",All!$AE9="RDP"),Ruler!I$14,IF(AND(All!$V9="P1",All!$AE9="RMS"),Ruler!I$6,IF(AND(All!$V9="P2",All!$AE9="RMS"),Ruler!I$15,IF(AND(All!$V9="P3",All!$AE9="RMS"),Ruler!I$16,IF(AND(All!$V9="P4",All!$AE9="RMS"),Ruler!I$17,IF(AND(All!$V9="P5",All!$AE9="RMS"),Ruler!I$18,IF(AND(All!$V9="P6",All!$AE9="RMS"),Ruler!I$19,IF(AND(All!$V9="P7",All!$AE9="RMS"),Ruler!I$20,IF(AND(All!$V9="P8",All!$AE9="RMS"),Ruler!I$21,IF(AND(All!$V9="P9",All!$AE9="RMS"),Ruler!I$22,IF(AND(All!$V9="P1",All!$AE9="RSS"),Ruler!I$6,IF(AND(All!$V9="P2",All!$AE9="RSS"),Ruler!I$23,IF(AND(All!$V9="P3",All!$AE9="RSS"),Ruler!I$24,IF(AND(All!$V9="P4",All!$AE9="RSS"),Ruler!I$25,IF(AND(All!$V9="P5",All!$AE9="RSS"),Ruler!I$26,IF(AND(All!$V9="P6",All!$AE9="RSS"),Ruler!I$27,IF(AND(All!$V9="P7",All!$AE9="RSS"),Ruler!I$28,IF(AND(All!$V9="P8",All!$AE9="RSS"),Ruler!I$29,IF(AND(All!$V9="P9",All!$AE9="RSS"),Ruler!I$30,0))))))))))))))))))))))))))) -> 0 | BQ9: =IF(AND(All!$V9="P1",All!$AE9="RDP"),Ruler!J$6,IF(AND(All!$V9="P2",All!$AE9="RDP"),Ruler!J$7,IF(AND(All!$V9="P3",All!$AE9="RDP"),Ruler!J$8,IF(AND(All!$V9="P4",All!$AE9="RDP"),Ruler!J$9,IF(AND(All!$V9="P5",All!$AE9="RDP"),Ruler!J$10,IF(AND(All!$V9="P6",All!$AE9="RDP"),Ruler!J$11,IF(AND(All!$V9="P7",All!$AE9="RDP"),Ruler!J$12,IF(AND(All!$V9="P8",All!$AE9="RDP"),Ruler!J$13,IF(AND(All!$V9="P9",All!$AE9="RDP"),Ruler!J$14,IF(AND(All!$V9="P1",All!$AE9="RMS"),Ruler!J$6,IF(AND(All!$V9="P2",All!$AE9="RMS"),Ruler!J$15,IF(AND(All!$V9="P3",All!$AE9="RMS"),Ruler!J$16,IF(AND(All!$V9="P4",All!$AE9="RMS"),Ruler!J$17,IF(AND(All!$V9="P5",All!$AE9="RMS"),Ruler!J$18,IF(AND(All!$V9="P6",All!$AE9="RMS"),Ruler!J$19,IF(AND(All!$V9="P7",All!$AE9="RMS"),Ruler!J$20,IF(AND(All!$V9="P8",All!$AE9="RMS"),Ruler!J$21,IF(AND(All!$V9="P9",All!$AE9="RMS"),Ruler!J$22,IF(AND(All!$V9="P1",All!$AE9="RSS"),Ruler!J$6,IF(AND(All!$V9="P2",All!$AE9="RSS"),Ruler!J$23,IF(AND(All!$V9="P3",All!$AE9="RSS"),Ruler!J$24,IF(AND(All!$V9="P4",All!$AE9="RSS"),Ruler!J$25,IF(AND(All!$V9="P5",All!$AE9="RSS"),Ruler!J$26,IF(AND(All!$V9="P6",All!$AE9="RSS"),Ruler!J$27,IF(AND(All!$V9="P7",All!$AE9="RSS"),Ruler!J$28,IF(AND(All!$V9="P8",All!$AE9="RSS"),Ruler!J$29,IF(AND(All!$V9="P9",All!$AE9="RSS"),Ruler!J$30,0))))))))))))))))))))))))))) -> 0 | BR9: =IF(AND(All!$V9="P1",All!$AE9="RDP"),Ruler!K$6,IF(AND(All!$V9="P2",All!$AE9="RDP"),Ruler!K$7,IF(AND(All!$V9="P3",All!$AE9="RDP"),Ruler!K$8,IF(AND(All!$V9="P4",All!$AE9="RDP"),Ruler!K$9,IF(AND(All!$V9="P5",All!$AE9="RDP"),Ruler!K$10,IF(AND(All!$V9="P6",All!$AE9="RDP"),Ruler!K$11,IF(AND(All!$V9="P7",All!$AE9="RDP"),Ruler!K$12,IF(AND(All!$V9="P8",All!$AE9="RDP"),Ruler!K$13,IF(AND(All!$V9="P9",All!$AE9="RDP"),Ruler!K$14,IF(AND(All!$V9="P1",All!$AE9="RMS"),Ruler!K$6,IF(AND(All!$V9="P2",All!$AE9="RMS"),Ruler!K$15,IF(AND(All!$V9="P3",All!$AE9="RMS"),Ruler!K$16,IF(AND(All!$V9="P4",All!$AE9="RMS"),Ruler!K$17,IF(AND(All!$V9="P5",All!$AE9="RMS"),Ruler!K$18,IF(AND(All!$V9="P6",All!$AE9="RMS"),Ruler!K$19,IF(AND(All!$V9="P7",All!$AE9="RMS"),Ruler!K$20,IF(AND(All!$V9="P8",All!$AE9="RMS"),Ruler!K$21,IF(AND(All!$V9="P9",All!$AE9="RMS"),Ruler!K$22,IF(AND(All!$V9="P1",All!$AE9="RSS"),Ruler!K$6,IF(AND(All!$V9="P2",All!$AE9="RSS"),Ruler!K$23,IF(AND(All!$V9="P3",All!$AE9="RSS"),Ruler!K$24,IF(AND(All!$V9="P4",All!$AE9="RSS"),Ruler!K$25,IF(AND(All!$V9="P5",All!$AE9="RSS"),Ruler!K$26,IF(AND(All!$V9="P6",All!$AE9="RSS"),Ruler!K$27,IF(AND(All!$V9="P7",All!$AE9="RSS"),Ruler!K$28,IF(AND(All!$V9="P8",All!$AE9="RSS"),Ruler!K$29,IF(AND(All!$V9="P9",All!$AE9="RSS"),Ruler!K$30,0))))))))))))))))))))))))))) -> 0 | BS9: =IF(AND(All!$V9="P1",All!$AE9="RDP"),Ruler!L$6,IF(AND(All!$V9="P2",All!$AE9="RDP"),Ruler!L$7,IF(AND(All!$V9="P3",All!$AE9="RDP"),Ruler!L$8,IF(AND(All!$V9="P4",All!$AE9="RDP"),Ruler!L$9,IF(AND(All!$V9="P5",All!$AE9="RDP"),Ruler!L$10,IF(AND(All!$V9="P6",All!$AE9="RDP"),Ruler!L$11,IF(AND(All!$V9="P7",All!$AE9="RDP"),Ruler!L$12,IF(AND(All!$V9="P8",All!$AE9="RDP"),Ruler!L$13,IF(AND(All!$V9="P9",All!$AE9="RDP"),Ruler!L$14,IF(AND(All!$V9="P1",All!$AE9="RMS"),Ruler!L$6,IF(AND(All!$V9="P2",All!$AE9="RMS"),Ruler!L$15,IF(AND(All!$V9="P3",All!$AE9="RMS"),Ruler!L$16,IF(AND(All!$V9="P4",All!$AE9="RMS"),Ruler!L$17,IF(AND(All!$V9="P5",All!$AE9="RMS"),Ruler!L$18,IF(AND(All!$V9="P6",All!$AE9="RMS"),Ruler!L$19,IF(AND(All!$V9="P7",All!$AE9="RMS"),Ruler!L$20,IF(AND(All!$V9="P8",All!$AE9="RMS"),Ruler!L$21,IF(AND(All!$V9="P9",All!$AE9="RMS"),Ruler!L$22,IF(AND(All!$V9="P1",All!$AE9="RSS"),Ruler!L$6,IF(AND(All!$V9="P2",All!$AE9="RSS"),Ruler!L$23,IF(AND(All!$V9="P3",All!$AE9="RSS"),Ruler!L$24,IF(AND(All!$V9="P4",All!$AE9="RSS"),Ruler!L$25,IF(AND(All!$V9="P5",All!$AE9="RSS"),Ruler!L$26,IF(AND(All!$V9="P6",All!$AE9="RSS"),Ruler!L$27,IF(AND(All!$V9="P7",All!$AE9="RSS"),Ruler!L$28,IF(AND(All!$V9="P8",All!$AE9="RSS"),Ruler!L$29,IF(AND(All!$V9="P9",All!$AE9="RSS"),Ruler!L$30,0))))))))))))))))))))))))))) -> 0 | ... CI9: =IF(AND(All!$V9="P1",All!$AE9="RDP"),Ruler!AB$6,IF(AND(All!$V9="P2",All!$AE9="RDP"),Ruler!AB$7,IF(AND(All!$V9="P3",All!$AE9="RDP"),Ruler!AB$8,IF(AND(All!$V9="P4",All!$AE9="RDP"),Ruler!AB$9,IF(AND(All!$V9="P5",All!$AE9="RDP"),Ruler!AB$10,IF(AND(All!$V9="P6",All!$AE9="RDP"),Ruler!AB$11,IF(AND(All!$V9="P7",All!$AE9="RDP"),Ruler!AB$12,IF(AND(All!$V9="P8",All!$AE9="RDP"),Ruler!AB$13,IF(AND(All!$V9="P9",All!$AE9="RDP"),Ruler!AB$14,IF(AND(All!$V9="P1",All!$AE9="RMS"),Ruler!AB$6,IF(AND(All!$V9="P2",All!$AE9="RMS"),Ruler!AB$15,IF(AND(All!$V9="P3",All!$AE9="RMS"),Ruler!AB$16,IF(AND(All!$V9="P4",All!$AE9="RMS"),Ruler!AB$17,IF(AND(All!$V9="P5",All!$AE9="RMS"),Ruler!AB$18,IF(AND(All!$V9="P6",All!$AE9="RMS"),Ruler!AB$19,IF(AND(All!$V9="P7",All!$AE9="RMS"),Ruler!AB$20,IF(AND(All!$V9="P8",All!$AE9="RMS"),Ruler!AB$21,IF(AND(All!$V9="P9",All!$AE9="RMS"),Ruler!AB$22,IF(AND(All!$V9="P1",All!$AE9="RSS"),Ruler!AB$6,IF(AND(All!$V9="P2",All!$AE9="RSS"),Ruler!AB$23,IF(AND(All!$V9="P3",All!$AE9="RSS"),Ruler!AB$24,IF(AND(All!$V9="P4",All!$AE9="RSS"),Ruler!AB$25,IF(AND(All!$V9="P5",All!$AE9="RSS"),Ruler!AB$26,IF(AND(All!$V9="P6",All!$AE9="RSS"),Ruler!AB$27,IF(AND(All!$V9="P7",All!$AE9="RSS"),Ruler!AB$28,IF(AND(All!$V9="P8",All!$AE9="RSS"),Ruler!AB$29,IF(AND(All!$V9="P9",All!$AE9="RSS"),Ruler!AB$30,0))))))))))))))))))))))))))) -> 0 | CJ9: =Table9[[#This Row],[R-B1]]-Table9[[#This Row],[B1]] -> 0 | CK9: =Table9[[#This Row],[R-B2]]-Table9[[#This Row],[B2]] -> 0 | CL9: =Table9[[#This Row],[R-B3]]-Table9[[#This Row],[B3]] -> 0 | CM9: =Table9[[#This Row],[R-B4]]-Table9[[#This Row],[B4]] -> 0 | CN9: =Table9[[#This Row],[R-B5]]-Table9[[#This Row],[B5]] -> 0 | CO9: =Table9[[#This Row],[R-B6]]-Table9[[#This Row],[B6]] -> 0 | CP9: =Table9[[#This Row],[R-B7]]-Table9[[#This Row],[B7]] -> 0 | CQ9: =Table9[[#This Row],[R-B8]]-Table9[[#This Row],[B8]] -> 0 | CR9: =Table9[[#This Row],[R-B9]]-Table9[[#This Row],[B9]] -> 0 | CS9: =Table9[[#This Row],[R-B10]]-Table9[[#This Row],[B10]] -> 0 | CT9: =Table9[[#This Row],[R-B11]]-Table9[[#This Row],[B11]] -> 0 | CU9: =Table9[[#This Row],[R-B12]]-Table9[[#This Row],[B12]] -> 0 | CV9: =Table9[[#This Row],[R-K1]]-Table9[[#This Row],[K1]] -> 0 | CW9: =Table9[[#This Row],[R-K2]]-Table9[[#This Row],[K2]] -> 0 | CX9: =Table9[[#This Row],[R-K3]]-Table9[[#This Row],[K3]] -> 0 | CY9: =Table9[[#This Row],[R-K4]]-Table9[[#This Row],[K4]] -> 0 | CZ9: =Table9[[#This Row],[R-K5]]-Table9[[#This Row],[K5]] -> 0 | DA9: =Table9[[#This Row],[R-P1]]-Table9[[#This Row],[P1]] -> 0 | DB9: =Table9[[#This Row],[R-P2]]-Table9[[#This Row],[P2]] -> 0 | DC9: =Table9[[#This Row],[R-P3]]-Table9[[#This Row],[P3]] -> 0 | DD9: =Table9[[#This Row],[R-P4]]-Table9[[#This Row],[P4]] -> 0 | DE9: =Table9[[#This Row],[R-P5]]-Table9[[#This Row],[P5]] -> 0 | DF9: =Table9[[#This Row],[R-E1]]-Table9[[#This Row],[E1]] -> 0 | DG9: =Table9[[#This Row],[R-E2]]-Table9[[#This Row],[E2]] -> 0 | DH9: =COUNTIF(Table9[[#This Row],[G-B1]:[G-B12]],"<=0")/12*100 -> 100 | DI9: =COUNTIF(Table9[[#This Row],[G-K1]:[G-K5]],"<=0")/5*100 -> 100 | DJ9: =COUNTIF(Table9[[#This Row],[G-P1]:[G-P5]],"<=0")/5*100 -> 100 | DK9: =COUNTIF(Table9[[#This Row],[G-E1]:[G-E2]],"<=0")/2*100 -> 100 | DL9: =IF(AE9="RDP",(COUNTIF(Table9[[#This Row],[G-B3]],"<=0")+COUNTIF(Table9[[#This Row],[G-B4]],"<=0")+COUNTIF(Table9[[#This Row],[G-B7]],"<=0")+COUNTIF(Table9[[#This Row],[G-B11]],"<=0")+COUNTIF(Table9[[#This Row],[G-K2]],"<=0"))/5*100,IF(AE9="RMS",(COUNTIF(Table9[[#This Row],[G-B4]],"<=0")+COUNTIF(Table9[[#This Row],[G-B5]],"<=0")+COUNTIF(Table9[[#This Row],[G-B10]],"<=0")+COUNTIF(Table9[[#This Row],[G-B12]],"<=0")+COUNTIF(Table9[[#This Row],[G-K2]],"<=0"))/5*100,IF(AE9="RSS",(COUNTIF(Table9[[#This Row],[G-B1]],"<=0")+COUNTIF(Table9[[#This Row],[G-B2]],"<=0")+COUNTIF(Table9[[#This Row],[G-B6]],"<=0")+COUNTIF(Table9[[#This Row],[G-B11]],"<=0")+COUNTIF(Table9[[#This Row],[G-B12]],"<=0"))/5*100,0))) -> 0
B10: 7 | C10: Yes | D10: 46196 | E10: Ahmad Hassan bin Arsat | F10: 135606 | G10: =($T$1-H10)/365 -> 43.040088 | H10: 30606 | I10: M | J10: Malaysia | K10: DPE | L10: IWT | M10: PEI | N10: Exploration | O10: Snr RE | P10: hassan_arsat@petronas.com.my | Q10: Permanent | S10: 38901 | T10: =YEARFRAC(S10,$T$1) -> 20.297222 | U10: =T10 -> 20.297222 | V10: P4 | X10: =($T$1-Table9[[#This Row],[Date of Appointment to Current Grade]])/365 -> 9.3113213 | Y10: 42917 | Z10: KUL | AA10: 45383 | AB10: =($T$1-Table9[[#This Row],[Date in Position]])/365 -> 2.5551569 | AC10: Staff | AE10: RSS | AF10: Average | AG10: UTM. Joined PMU (8 years)- EOR & CO2 Storage, built mega model for SK gas.PCSB- RRSS (4yrs). PAE-SAGA Project. SK FDP - Anjung, Binjan. Iraq - 2.5years.PEI-Expl | AH10: ✅ Resource Estimation | AI10: Use the recent TPCP assessment as guide to map a plan to address his gap. Move to FDP project as soon as possible to improve his technical skill, prefereably to join team at early stage and comple whle project cycle. | AJ10: Resource Classification | AK10: To continue improving his technical skill and build confident in technical skill | AL10: TP | AM10: • Data base is not well manage or not available to certain extent. RPC example - not working well for Sabah area. Request him to check with RPC focal to confirm and fix the problem. • The guideline for DST decision-making (whether to conduct or not conduct a DST) requires justification to management in both cases. This has created some confusion among team members. | AN10: 3 | AO10: 2 | AP10: 2 | AQ10: 3 | AR10: 2 | AS10: 3 | AT10: 2 | AU10: 2 | AV10: 3 | AW10: 1 | AX10: 3 | AY10: 2 | AZ10: 3 | BA10: 2 | BB10: 1 | BC10: 2 | BD10: 1 | BE10: 2 | BF10: 1 | BG10: 2 | BH10: 1 | BI10: 1 | BJ10: 1 | BK10: 1 | BL10: =IF(AND(All!$V10="P1",All!$AE10="RDP"),Ruler!E$6,IF(AND(All!$V10="P2",All!$AE10="RDP"),Ruler!E$7,IF(AND(All!$V10="P3",All!$AE10="RDP"),Ruler!E$8,IF(AND(All!$V10="P4",All!$AE10="RDP"),Ruler!E$9,IF(AND(All!$V10="P5",All!$AE10="RDP"),Ruler!E$10,IF(AND(All!$V10="P6",All!$AE10="RDP"),Ruler!E$11,IF(AND(All!$V10="P7",All!$AE10="RDP"),Ruler!E$12,IF(AND(All!$V10="P8",All!$AE10="RDP"),Ruler!E$13,IF(AND(All!$V10="P9",All!$AE10="RDP"),Ruler!E$14,IF(AND(All!$V10="P1",All!$AE10="RMS"),Ruler!E$6,IF(AND(All!$V10="P2",All!$AE10="RMS"),Ruler!E$15,IF(AND(All!$V10="P3",All!$AE10="RMS"),Ruler!E$16,IF(AND(All!$V10="P4",All!$AE10="RMS"),Ruler!E$17,IF(AND(All!$V10="P5",All!$AE10="RMS"),Ruler!E$18,IF(AND(All!$V10="P6",All!$AE10="RMS"),Ruler!E$19,IF(AND(All!$V10="P7",All!$AE10="RMS"),Ruler!E$20,IF(AND(All!$V10="P8",All!$AE10="RMS"),Ruler!E$21,IF(AND(All!$V10="P9",All!$AE10="RMS"),Ruler!E$22,IF(AND(All!$V10="P1",All!$AE10="RSS"),Ruler!E$6,IF(AND(All!$V10="P2",All!$AE10="RSS"),Ruler!E$23,IF(AND(All!$V10="P3",All!$AE10="RSS"),Ruler!E$24,IF(AND(All!$V10="P4",All!$AE10="RSS"),Ruler!E$25,IF(AND(All!$V10="P5",All!$AE10="RSS"),Ruler!E$26,IF(AND(All!$V10="P6",All!$AE10="RSS"),Ruler!E$27,IF(AND(All!$V10="P7",All!$AE10="RSS"),Ruler!E$28,IF(AND(All!$V10="P8",All!$AE10="RSS"),Ruler!E$29,IF(AND(All!$V10="P9",All!$AE10="RSS"),Ruler!E$30,0))))))))))))))))))))))))))) -> 3 | BM10: =IF(AND(All!$V10="P1",All!$AE10="RDP"),Ruler!F$6,IF(AND(All!$V10="P2",All!$AE10="RDP"),Ruler!F$7,IF(AND(All!$V10="P3",All!$AE10="RDP"),Ruler!F$8,IF(AND(All!$V10="P4",All!$AE10="RDP"),Ruler!F$9,IF(AND(All!$V10="P5",All!$AE10="RDP"),Ruler!F$10,IF(AND(All!$V10="P6",All!$AE10="RDP"),Ruler!F$11,IF(AND(All!$V10="P7",All!$AE10="RDP"),Ruler!F$12,IF(AND(All!$V10="P8",All!$AE10="RDP"),Ruler!F$13,IF(AND(All!$V10="P9",All!$AE10="RDP"),Ruler!F$14,IF(AND(All!$V10="P1",All!$AE10="RMS"),Ruler!F$6,IF(AND(All!$V10="P2",All!$AE10="RMS"),Ruler!F$15,IF(AND(All!$V10="P3",All!$AE10="RMS"),Ruler!F$16,IF(AND(All!$V10="P4",All!$AE10="RMS"),Ruler!F$17,IF(AND(All!$V10="P5",All!$AE10="RMS"),Ruler!F$18,IF(AND(All!$V10="P6",All!$AE10="RMS"),Ruler!F$19,IF(AND(All!$V10="P7",All!$AE10="RMS"),Ruler!F$20,IF(AND(All!$V10="P8",All!$AE10="RMS"),Ruler!F$21,IF(AND(All!$V10="P9",All!$AE10="RMS"),Ruler!F$22,IF(AND(All!$V10="P1",All!$AE10="RSS"),Ruler!F$6,IF(AND(All!$V10="P2",All!$AE10="RSS"),Ruler!F$23,IF(AND(All!$V10="P3",All!$AE10="RSS"),Ruler!F$24,IF(AND(All!$V10="P4",All!$AE10="RSS"),Ruler!F$25,IF(AND(All!$V10="P5",All!$AE10="RSS"),Ruler!F$26,IF(AND(All!$V10="P6",All!$AE10="RSS"),Ruler!F$27,IF(AND(All!$V10="P7",All!$AE10="RSS"),Ruler!F$28,IF(AND(All!$V10="P8",All!$AE10="RSS"),Ruler!F$29,IF(AND(All!$V10="P9",All!$AE10="RSS"),Ruler!F$30,0))))))))))))))))))))))))))) -> 3 | BN10: =IF(AND(All!$V10="P1",All!$AE10="RDP"),Ruler!G$6,IF(AND(All!$V10="P2",All!$AE10="RDP"),Ruler!G$7,IF(AND(All!$V10="P3",All!$AE10="RDP"),Ruler!G$8,IF(AND(All!$V10="P4",All!$AE10="RDP"),Ruler!G$9,IF(AND(All!$V10="P5",All!$AE10="RDP"),Ruler!G$10,IF(AND(All!$V10="P6",All!$AE10="RDP"),Ruler!G$11,IF(AND(All!$V10="P7",All!$AE10="RDP"),Ruler!G$12,IF(AND(All!$V10="P8",All!$AE10="RDP"),Ruler!G$13,IF(AND(All!$V10="P9",All!$AE10="RDP"),Ruler!G$14,IF(AND(All!$V10="P1",All!$AE10="RMS"),Ruler!G$6,IF(AND(All!$V10="P2",All!$AE10="RMS"),Ruler!G$15,IF(AND(All!$V10="P3",All!$AE10="RMS"),Ruler!G$16,IF(AND(All!$V10="P4",All!$AE10="RMS"),Ruler!G$17,IF(AND(All!$V10="P5",All!$AE10="RMS"),Ruler!G$18,IF(AND(All!$V10="P6",All!$AE10="RMS"),Ruler!G$19,IF(AND(All!$V10="P7",All!$AE10="RMS"),Ruler!G$20,IF(AND(All!$V10="P8",All!$AE10="RMS"),Ruler!G$21,IF(AND(All!$V10="P9",All!$AE10="RMS"),Ruler!G$22,IF(AND(All!$V10="P1",All!$AE10="RSS"),Ruler!G$6,IF(AND(All!$V10="P2",All!$AE10="RSS"),Ruler!G$23,IF(AND(All!$V10="P3",All!$AE10="RSS"),Ruler!G$24,IF(AND(All!$V10="P4",All!$AE10="RSS"),Ruler!G$25,IF(AND(All!$V10="P5",All!$AE10="RSS"),Ruler!G$26,IF(AND(All!$V10="P6",All!$AE10="RSS"),Ruler!G$27,IF(AND(All!$V10="P7",All!$AE10="RSS"),Ruler!G$28,IF(AND(All!$V10="P8",All!$AE10="RSS"),Ruler!G$29,IF(AND(All!$V10="P9",All!$AE10="RSS"),Ruler!G$30,0))))))))))))))))))))))))))) -> 2 | BO10: =IF(AND(All!$V10="P1",All!$AE10="RDP"),Ruler!H$6,IF(AND(All!$V10="P2",All!$AE10="RDP"),Ruler!H$7,IF(AND(All!$V10="P3",All!$AE10="RDP"),Ruler!H$8,IF(AND(All!$V10="P4",All!$AE10="RDP"),Ruler!H$9,IF(AND(All!$V10="P5",All!$AE10="RDP"),Ruler!H$10,IF(AND(All!$V10="P6",All!$AE10="RDP"),Ruler!H$11,IF(AND(All!$V10="P7",All!$AE10="RDP"),Ruler!H$12,IF(AND(All!$V10="P8",All!$AE10="RDP"),Ruler!H$13,IF(AND(All!$V10="P9",All!$AE10="RDP"),Ruler!H$14,IF(AND(All!$V10="P1",All!$AE10="RMS"),Ruler!H$6,IF(AND(All!$V10="P2",All!$AE10="RMS"),Ruler!H$15,IF(AND(All!$V10="P3",All!$AE10="RMS"),Ruler!H$16,IF(AND(All!$V10="P4",All!$AE10="RMS"),Ruler!H$17,IF(AND(All!$V10="P5",All!$AE10="RMS"),Ruler!H$18,IF(AND(All!$V10="P6",All!$AE10="RMS"),Ruler!H$19,IF(AND(All!$V10="P7",All!$AE10="RMS"),Ruler!H$20,IF(AND(All!$V10="P8",All!$AE10="RMS"),Ruler!H$21,IF(AND(All!$V10="P9",All!$AE10="RMS"),Ruler!H$22,IF(AND(All!$V10="P1",All!$AE10="RSS"),Ruler!H$6,IF(AND(All!$V10="P2",All!$AE10="RSS"),Ruler!H$23,IF(AND(All!$V10="P3",All!$AE10="RSS"),Ruler!H$24,IF(AND(All!$V10="P4",All!$AE10="RSS"),Ruler!H$25,IF(AND(All!$V10="P5",All!$AE10="RSS"),Ruler!H$26,IF(AND(All!$V10="P6",All!$AE10="RSS"),Ruler!H$27,IF(AND(All!$V10="P7",All!$AE10="RSS"),Ruler!H$28,IF(AND(All!$V10="P8",All!$AE10="RSS"),Ruler!H$29,IF(AND(All!$V10="P9",All!$AE10="RSS"),Ruler!H$30,0))))))))))))))))))))))))))) -> 3 | BP10: =IF(AND(All!$V10="P1",All!$AE10="RDP"),Ruler!I$6,IF(AND(All!$V10="P2",All!$AE10="RDP"),Ruler!I$7,IF(AND(All!$V10="P3",All!$AE10="RDP"),Ruler!I$8,IF(AND(All!$V10="P4",All!$AE10="RDP"),Ruler!I$9,IF(AND(All!$V10="P5",All!$AE10="RDP"),Ruler!I$10,IF(AND(All!$V10="P6",All!$AE10="RDP"),Ruler!I$11,IF(AND(All!$V10="P7",All!$AE10="RDP"),Ruler!I$12,IF(AND(All!$V10="P8",All!$AE10="RDP"),Ruler!I$13,IF(AND(All!$V10="P9",All!$AE10="RDP"),Ruler!I$14,IF(AND(All!$V10="P1",All!$AE10="RMS"),Ruler!I$6,IF(AND(All!$V10="P2",All!$AE10="RMS"),Ruler!I$15,IF(AND(All!$V10="P3",All!$AE10="RMS"),Ruler!I$16,IF(AND(All!$V10="P4",All!$AE10="RMS"),Ruler!I$17,IF(AND(All!$V10="P5",All!$AE10="RMS"),Ruler!I$18,IF(AND(All!$V10="P6",All!$AE10="RMS"),Ruler!I$19,IF(AND(All!$V10="P7",All!$AE10="RMS"),Ruler!I$20,IF(AND(All!$V10="P8",All!$AE10="RMS"),Ruler!I$21,IF(AND(All!$V10="P9",All!$AE10="RMS"),Ruler!I$22,IF(AND(All!$V10="P1",All!$AE10="RSS"),Ruler!I$6,IF(AND(All!$V10="P2",All!$AE10="RSS"),Ruler!I$23,IF(AND(All!$V10="P3",All!$AE10="RSS"),Ruler!I$24,IF(AND(All!$V10="P4",All!$AE10="RSS"),Ruler!I$25,IF(AND(All!$V10="P5",All!$AE10="RSS"),Ruler!I$26,IF(AND(All!$V10="P6",All!$AE10="RSS"),Ruler!I$27,IF(AND(All!$V10="P7",All!$AE10="RSS"),Ruler!I$28,IF(AND(All!$V10="P8",All!$AE10="RSS"),Ruler!I$29,IF(AND(All!$V10="P9",All!$AE10="RSS"),Ruler!I$30,0))))))))))))))))))))))))))) -> 3 | BQ10: =IF(AND(All!$V10="P1",All!$AE10="RDP"),Ruler!J$6,IF(AND(All!$V10="P2",All!$AE10="RDP"),Ruler!J$7,IF(AND(All!$V10="P3",All!$AE10="RDP"),Ruler!J$8,IF(AND(All!$V10="P4",All!$AE10="RDP"),Ruler!J$9,IF(AND(All!$V10="P5",All!$AE10="RDP"),Ruler!J$10,IF(AND(All!$V10="P6",All!$AE10="RDP"),Ruler!J$11,IF(AND(All!$V10="P7",All!$AE10="RDP"),Ruler!J$12,IF(AND(All!$V10="P8",All!$AE10="RDP"),Ruler!J$13,IF(AND(All!$V10="P9",All!$AE10="RDP"),Ruler!J$14,IF(AND(All!$V10="P1",All!$AE10="RMS"),Ruler!J$6,IF(AND(All!$V10="P2",All!$AE10="RMS"),Ruler!J$15,IF(AND(All!$V10="P3",All!$AE10="RMS"),Ruler!J$16,IF(AND(All!$V10="P4",All!$AE10="RMS"),Ruler!J$17,IF(AND(All!$V10="P5",All!$AE10="RMS"),Ruler!J$18,IF(AND(All!$V10="P6",All!$AE10="RMS"),Ruler!J$19,IF(AND(All!$V10="P7",All!$AE10="RMS"),Ruler!J$20,IF(AND(All!$V10="P8",All!$AE10="RMS"),Ruler!J$21,IF(AND(All!$V10="P9",All!$AE10="RMS"),Ruler!J$22,IF(AND(All!$V10="P1",All!$AE10="RSS"),Ruler!J$6,IF(AND(All!$V10="P2",All!$AE10="RSS"),Ruler!J$23,IF(AND(All!$V10="P3",All!$AE10="RSS"),Ruler!J$24,IF(AND(All!$V10="P4",All!$AE10="RSS"),Ruler!J$25,IF(AND(All!$V10="P5",All!$AE10="RSS"),Ruler!J$26,IF(AND(All!$V10="P6",All!$AE10="RSS"),Ruler!J$27,IF(AND(All!$V10="P7",All!$AE10="RSS"),Ruler!J$28,IF(AND(All!$V10="P8",All!$AE10="RSS"),Ruler!J$29,IF(AND(All!$V10="P9",All!$AE10="RSS"),Ruler!J$30,0))))))))))))))))))))))))))) -> 3 | BR10: =IF(AND(All!$V10="P1",All!$AE10="RDP"),Ruler!K$6,IF(AND(All!$V10="P2",All!$AE10="RDP"),Ruler!K$7,IF(AND(All!$V10="P3",All!$AE10="RDP"),Ruler!K$8,IF(AND(All!$V10="P4",All!$AE10="RDP"),Ruler!K$9,IF(AND(All!$V10="P5",All!$AE10="RDP"),Ruler!K$10,IF(AND(All!$V10="P6",All!$AE10="RDP"),Ruler!K$11,IF(AND(All!$V10="P7",All!$AE10="RDP"),Ruler!K$12,IF(AND(All!$V10="P8",All!$AE10="RDP"),Ruler!K$13,IF(AND(All!$V10="P9",All!$AE10="RDP"),Ruler!K$14,IF(AND(All!$V10="P1",All!$AE10="RMS"),Ruler!K$6,IF(AND(All!$V10="P2",All!$AE10="RMS"),Ruler!K$15,IF(AND(All!$V10="P3",All!$AE10="RMS"),Ruler!K$16,IF(AND(All!$V10="P4",All!$AE10="RMS"),Ruler!K$17,IF(AND(All!$V10="P5",All!$AE10="RMS"),Ruler!K$18,IF(AND(All!$V10="P6",All!$AE10="RMS"),Ruler!K$19,IF(AND(All!$V10="P7",All!$AE10="RMS"),Ruler!K$20,IF(AND(All!$V10="P8",All!$AE10="RMS"),Ruler!K$21,IF(AND(All!$V10="P9",All!$AE10="RMS"),Ruler!K$22,IF(AND(All!$V10="P1",All!$AE10="RSS"),Ruler!K$6,IF(AND(All!$V10="P2",All!$AE10="RSS"),Ruler!K$23,IF(AND(All!$V10="P3",All!$AE10="RSS"),Ruler!K$24,IF(AND(All!$V10="P4",All!$AE10="RSS"),Ruler!K$25,IF(AND(All!$V10="P5",All!$AE10="RSS"),Ruler!K$26,IF(AND(All!$V10="P6",All!$AE10="RSS"),Ruler!K$27,IF(AND(All!$V10="P7",All!$AE10="RSS"),Ruler!K$28,IF(AND(All!$V10="P8",All!$AE10="RSS"),Ruler!K$29,IF(AND(All!$V10="P9",All!$AE10="RSS"),Ruler!K$30,0))))))))))))))))))))))))))) -> 3 | BS10: =IF(AND(All!$V10="P1",All!$AE10="RDP"),Ruler!L$6,IF(AND(All!$V10="P2",All!$AE10="RDP"),Ruler!L$7,IF(AND(All!$V10="P3",All!$AE10="RDP"),Ruler!L$8,IF(AND(All!$V10="P4",All!$AE10="RDP"),Ruler!L$9,IF(AND(All!$V10="P5",All!$AE10="RDP"),Ruler!L$10,IF(AND(All!$V10="P6",All!$AE10="RDP"),Ruler!L$11,IF(AND(All!$V10="P7",All!$AE10="RDP"),Ruler!L$12,IF(AND(All!$V10="P8",All!$AE10="RDP"),Ruler!L$13,IF(AND(All!$V10="P9",All!$AE10="RDP"),Ruler!L$14,IF(AND(All!$V10="P1",All!$AE10="RMS"),Ruler!L$6,IF(AND(All!$V10="P2",All!$AE10="RMS"),Ruler!L$15,IF(AND(All!$V10="P3",All!$AE10="RMS"),Ruler!L$16,IF(AND(All!$V10="P4",All!$AE10="RMS"),Ruler!L$17,IF(AND(All!$V10="P5",All!$AE10="RMS"),Ruler!L$18,IF(AND(All!$V10="P6",All!$AE10="RMS"),Ruler!L$19,IF(AND(All!$V10="P7",All!$AE10="RMS"),Ruler!L$20,IF(AND(All!$V10="P8",All!$AE10="RMS"),Ruler!L$21,IF(AND(All!$V10="P9",All!$AE10="RMS"),Ruler!L$22,IF(AND(All!$V10="P1",All!$AE10="RSS"),Ruler!L$6,IF(AND(All!$V10="P2",All!$AE10="RSS"),Ruler!L$23,IF(AND(All!$V10="P3",All!$AE10="RSS"),Ruler!L$24,IF(AND(All!$V10="P4",All!$AE10="RSS"),Ruler!L$25,IF(AND(All!$V10="P5",All!$AE10="RSS"),Ruler!L$26,IF(AND(All!$V10="P6",All!$AE10="RSS"),Ruler!L$27,IF(AND(All!$V10="P7",All!$AE10="RSS"),Ruler!L$28,IF(AND(All!$V10="P8",All!$AE10="RSS"),Ruler!L$29,IF(AND(All!$V10="P9",All!$AE10="RSS"),Ruler!L$30,0))))))))))))))))))))))))))) -> 2 | ... CI10: =IF(AND(All!$V10="P1",All!$AE10="RDP"),Ruler!AB$6,IF(AND(All!$V10="P2",All!$AE10="RDP"),Ruler!AB$7,IF(AND(All!$V10="P3",All!$AE10="RDP"),Ruler!AB$8,IF(AND(All!$V10="P4",All!$AE10="RDP"),Ruler!AB$9,IF(AND(All!$V10="P5",All!$AE10="RDP"),Ruler!AB$10,IF(AND(All!$V10="P6",All!$AE10="RDP"),Ruler!AB$11,IF(AND(All!$V10="P7",All!$AE10="RDP"),Ruler!AB$12,IF(AND(All!$V10="P8",All!$AE10="RDP"),Ruler!AB$13,IF(AND(All!$V10="P9",All!$AE10="RDP"),Ruler!AB$14,IF(AND(All!$V10="P1",All!$AE10="RMS"),Ruler!AB$6,IF(AND(All!$V10="P2",All!$AE10="RMS"),Ruler!AB$15,IF(AND(All!$V10="P3",All!$AE10="RMS"),Ruler!AB$16,IF(AND(All!$V10="P4",All!$AE10="RMS"),Ruler!AB$17,IF(AND(All!$V10="P5",All!$AE10="RMS"),Ruler!AB$18,IF(AND(All!$V10="P6",All!$AE10="RMS"),Ruler!AB$19,IF(AND(All!$V10="P7",All!$AE10="RMS"),Ruler!AB$20,IF(AND(All!$V10="P8",All!$AE10="RMS"),Ruler!AB$21,IF(AND(All!$V10="P9",All!$AE10="RMS"),Ruler!AB$22,IF(AND(All!$V10="P1",All!$AE10="RSS"),Ruler!AB$6,IF(AND(All!$V10="P2",All!$AE10="RSS"),Ruler!AB$23,IF(AND(All!$V10="P3",All!$AE10="RSS"),Ruler!AB$24,IF(AND(All!$V10="P4",All!$AE10="RSS"),Ruler!AB$25,IF(AND(All!$V10="P5",All!$AE10="RSS"),Ruler!AB$26,IF(AND(All!$V10="P6",All!$AE10="RSS"),Ruler!AB$27,IF(AND(All!$V10="P7",All!$AE10="RSS"),Ruler!AB$28,IF(AND(All!$V10="P8",All!$AE10="RSS"),Ruler!AB$29,IF(AND(All!$V10="P9",All!$AE10="RSS"),Ruler!AB$30,0))))))))))))))))))))))))))) -> 1 | CJ10: =Table9[[#This Row],[R-B1]]-Table9[[#This Row],[B1]] -> 0 | CK10: =Table9[[#This Row],[R-B2]]-Table9[[#This Row],[B2]] -> 1 | CL10: =Table9[[#This Row],[R-B3]]-Table9[[#This Row],[B3]] -> 0 | CM10: =Table9[[#This Row],[R-B4]]-Table9[[#This Row],[B4]] -> 0 | CN10: =Table9[[#This Row],[R-B5]]-Table9[[#This Row],[B5]] -> 1 | CO10: =Table9[[#This Row],[R-B6]]-Table9[[#This Row],[B6]] -> 0 | CP10: =Table9[[#This Row],[R-B7]]-Table9[[#This Row],[B7]] -> 1 | CQ10: =Table9[[#This Row],[R-B8]]-Table9[[#This Row],[B8]] -> 0 | CR10: =Table9[[#This Row],[R-B9]]-Table9[[#This Row],[B9]] -> 0 | CS10: =Table9[[#This Row],[R-B10]]-Table9[[#This Row],[B10]] -> 0 | CT10: =Table9[[#This Row],[R-B11]]-Table9[[#This Row],[B11]] -> 0 | CU10: =Table9[[#This Row],[R-B12]]-Table9[[#This Row],[B12]] -> 0 | CV10: =Table9[[#This Row],[R-K1]]-Table9[[#This Row],[K1]] -> 0 | CW10: =Table9[[#This Row],[R-K2]]-Table9[[#This Row],[K2]] -> 0 | CX10: =Table9[[#This Row],[R-K3]]-Table9[[#This Row],[K3]] -> 1 | CY10: =Table9[[#This Row],[R-K4]]-Table9[[#This Row],[K4]] -> 0 | CZ10: =Table9[[#This Row],[R-K5]]-Table9[[#This Row],[K5]] -> 1 | DA10: =Table9[[#This Row],[R-P1]]-Table9[[#This Row],[P1]] -> 0 | DB10: =Table9[[#This Row],[R-P2]]-Table9[[#This Row],[P2]] -> 1 | DC10: =Table9[[#This Row],[R-P3]]-Table9[[#This Row],[P3]] -> 0 | DD10: =Table9[[#This Row],[R-P4]]-Table9[[#This Row],[P4]] -> 0 | DE10: =Table9[[#This Row],[R-P5]]-Table9[[#This Row],[P5]] -> 1 | DF10: =Table9[[#This Row],[R-E1]]-Table9[[#This Row],[E1]] -> 0 | DG10: =Table9[[#This Row],[R-E2]]-Table9[[#This Row],[E2]] -> 0 | DH10: =COUNTIF(Table9[[#This Row],[G-B1]:[G-B12]],"<=0")/12*100 -> 75 | DI10: =COUNTIF(Table9[[#This Row],[G-K1]:[G-K5]],"<=0")/5*100 -> 60 | DJ10: =COUNTIF(Table9[[#This Row],[G-P1]:[G-P5]],"<=0")/5*100 -> 60 | DK10: =COUNTIF(Table9[[#This Row],[G-E1]:[G-E2]],"<=0")/2*100 -> 100 | DL10: =IF(AE10="RDP",(COUNTIF(Table9[[#This Row],[G-B3]],"<=0")+COUNTIF(Table9[[#This Row],[G-B4]],"<=0")+COUNTIF(Table9[[#This Row],[G-B7]],"<=0")+COUNTIF(Table9[[#This Row],[G-B11]],"<=0")+COUNTIF(Table9[[#This Row],[G-K2]],"<=0"))/5*100,IF(AE10="RMS",(COUNTIF(Table9[[#This Row],[G-B4]],"<=0")+COUNTIF(Table9[[#This Row],[G-B5]],"<=0")+COUNTIF(Table9[[#This Row],[G-B10]],"<=0")+COUNTIF(Table9[[#This Row],[G-B12]],"<=0")+COUNTIF(Table9[[#This Row],[G-K2]],"<=0"))/5*100,IF(AE10="RSS",(COUNTIF(Table9[[#This Row],[G-B1]],"<=0")+COUNTIF(Table9[[#This Row],[G-B2]],"<=0")+COUNTIF(Table9[[#This Row],[G-B6]],"<=0")+COUNTIF(Table9[[#This Row],[G-B11]],"<=0")+COUNTIF(Table9[[#This Row],[G-B12]],"<=0"))/5*100,0))) -> 80 | DM10: 75 | DN10: 60 | DO10: 60 | DP10: 100 | DQ10: 80 | DR10: 17 | DS10: 40 | DT10: 20 | DU10: 0 | DV10: 0 | DW10: 17 | DX10: 20 | DY10: 0 | DZ10: 0 | EA10: 0 | EB10: Abd Rahman Harun | ED10: Mohd Amir Shah
B11: 8 | C11: Yes | D11: 46212 | E11: Ahmad Ikhwan Che Rasli | G11: =($T$1-H11)/365 -> 36.598993 | H11: 32957 | I11: M | J11: Malaysia | K11: PSR | L11: GFC | O11: Executive | P11: ahmadikhwan.cherasli@petronas.com.my | Q11: Permanent | S11: 45505 | T11: =YEARFRAC(S11,$T$1) -> 2.2194444 | U11: 12 | V11: P3 | X11: =($T$1-Table9[[#This Row],[Date of Appointment to Current Grade]])/365 -> 2.2209103 | Y11: 45505 | Z11: PSR | AA11: 45505 | AB11: =($T$1-Table9[[#This Row],[Date in Position]])/365 -> 2.2209103 | AC11: UPE | AD11: Ongoing | AE11: RMS | AF11: Good | AG11: UTP PE-Drilling. Carigali-Hess(13-22) joined as planner. Forecasting, WPB, ADP, sand mgt. GAP. Surveillance (20-22) - Bumi field. PE job and RMP, managing water production. Exxon (22-23) - Surveillance and reserves for gas field (Lawit, Jernih Bintang). CPOC (23-24) -surveillance, production optimization and data acquisition and corporate planning. PSR (24-now)- ARPR coordinator for PTTEP, Vestigo, Storage | AH11: ✅ Gas surveillance ✅ GAP modelling and coupling ✅ Reserves estimation | AI11: Self assessment to gauge his gap and focus on critical gap to achive P4 requirement. Conduct SMA assessment as per plan but may be to change the priority to the critical item. He need and exposure on oil field surveillance and FDP. | AK11: Surveillance at region or FDP. Max. 3 years at PSR. Already initiate talk with Afzan of his intention | AL11: TP | AM11: Raised a concern on PSR assignment not too long. Open for any position outside PSR to broaden his skill | BL11: =IF(AND(All!$V11="P1",All!$AE11="RDP"),Ruler!E$6,IF(AND(All!$V11="P2",All!$AE11="RDP"),Ruler!E$7,IF(AND(All!$V11="P3",All!$AE11="RDP"),Ruler!E$8,IF(AND(All!$V11="P4",All!$AE11="RDP"),Ruler!E$9,IF(AND(All!$V11="P5",All!$AE11="RDP"),Ruler!E$10,IF(AND(All!$V11="P6",All!$AE11="RDP"),Ruler!E$11,IF(AND(All!$V11="P7",All!$AE11="RDP"),Ruler!E$12,IF(AND(All!$V11="P8",All!$AE11="RDP"),Ruler!E$13,IF(AND(All!$V11="P9",All!$AE11="RDP"),Ruler!E$14,IF(AND(All!$V11="P1",All!$AE11="RMS"),Ruler!E$6,IF(AND(All!$V11="P2",All!$AE11="RMS"),Ruler!E$15,IF(AND(All!$V11="P3",All!$AE11="RMS"),Ruler!E$16,IF(AND(All!$V11="P4",All!$AE11="RMS"),Ruler!E$17,IF(AND(All!$V11="P5",All!$AE11="RMS"),Ruler!E$18,IF(AND(All!$V11="P6",All!$AE11="RMS"),Ruler!E$19,IF(AND(All!$V11="P7",All!$AE11="RMS"),Ruler!E$20,IF(AND(All!$V11="P8",All!$AE11="RMS"),Ruler!E$21,IF(AND(All!$V11="P9",All!$AE11="RMS"),Ruler!E$22,IF(AND(All!$V11="P1",All!$AE11="RSS"),Ruler!E$6,IF(AND(All!$V11="P2",All!$AE11="RSS"),Ruler!E$23,IF(AND(All!$V11="P3",All!$AE11="RSS"),Ruler!E$24,IF(AND(All!$V11="P4",All!$AE11="RSS"),Ruler!E$25,IF(AND(All!$V11="P5",All!$AE11="RSS"),Ruler!E$26,IF(AND(All!$V11="P6",All!$AE11="RSS"),Ruler!E$27,IF(AND(All!$V11="P7",All!$AE11="RSS"),Ruler!E$28,IF(AND(All!$V11="P8",All!$AE11="RSS"),Ruler!E$29,IF(AND(All!$V11="P9",All!$AE11="RSS"),Ruler!E$30,0))))))))))))))))))))))))))) -> 2 | BM11: =IF(AND(All!$V11="P1",All!$AE11="RDP"),Ruler!F$6,IF(AND(All!$V11="P2",All!$AE11="RDP"),Ruler!F$7,IF(AND(All!$V11="P3",All!$AE11="RDP"),Ruler!F$8,IF(AND(All!$V11="P4",All!$AE11="RDP"),Ruler!F$9,IF(AND(All!$V11="P5",All!$AE11="RDP"),Ruler!F$10,IF(AND(All!$V11="P6",All!$AE11="RDP"),Ruler!F$11,IF(AND(All!$V11="P7",All!$AE11="RDP"),Ruler!F$12,IF(AND(All!$V11="P8",All!$AE11="RDP"),Ruler!F$13,IF(AND(All!$V11="P9",All!$AE11="RDP"),Ruler!F$14,IF(AND(All!$V11="P1",All!$AE11="RMS"),Ruler!F$6,IF(AND(All!$V11="P2",All!$AE11="RMS"),Ruler!F$15,IF(AND(All!$V11="P3",All!$AE11="RMS"),Ruler!F$16,IF(AND(All!$V11="P4",All!$AE11="RMS"),Ruler!F$17,IF(AND(All!$V11="P5",All!$AE11="RMS"),Ruler!F$18,IF(AND(All!$V11="P6",All!$AE11="RMS"),Ruler!F$19,IF(AND(All!$V11="P7",All!$AE11="RMS"),Ruler!F$20,IF(AND(All!$V11="P8",All!$AE11="RMS"),Ruler!F$21,IF(AND(All!$V11="P9",All!$AE11="RMS"),Ruler!F$22,IF(AND(All!$V11="P1",All!$AE11="RSS"),Ruler!F$6,IF(AND(All!$V11="P2",All!$AE11="RSS"),Ruler!F$23,IF(AND(All!$V11="P3",All!$AE11="RSS"),Ruler!F$24,IF(AND(All!$V11="P4",All!$AE11="RSS"),Ruler!F$25,IF(AND(All!$V11="P5",All!$AE11="RSS"),Ruler!F$26,IF(AND(All!$V11="P6",All!$AE11="RSS"),Ruler!F$27,IF(AND(All!$V11="P7",All!$AE11="RSS"),Ruler!F$28,IF(AND(All!$V11="P8",All!$AE11="RSS"),Ruler!F$29,IF(AND(All!$V11="P9",All!$AE11="RSS"),Ruler!F$30,0))))))))))))))))))))))))))) -> 2 | BN11: =IF(AND(All!$V11="P1",All!$AE11="RDP"),Ruler!G$6,IF(AND(All!$V11="P2",All!$AE11="RDP"),Ruler!G$7,IF(AND(All!$V11="P3",All!$AE11="RDP"),Ruler!G$8,IF(AND(All!$V11="P4",All!$AE11="RDP"),Ruler!G$9,IF(AND(All!$V11="P5",All!$AE11="RDP"),Ruler!G$10,IF(AND(All!$V11="P6",All!$AE11="RDP"),Ruler!G$11,IF(AND(All!$V11="P7",All!$AE11="RDP"),Ruler!G$12,IF(AND(All!$V11="P8",All!$AE11="RDP"),Ruler!G$13,IF(AND(All!$V11="P9",All!$AE11="RDP"),Ruler!G$14,IF(AND(All!$V11="P1",All!$AE11="RMS"),Ruler!G$6,IF(AND(All!$V11="P2",All!$AE11="RMS"),Ruler!G$15,IF(AND(All!$V11="P3",All!$AE11="RMS"),Ruler!G$16,IF(AND(All!$V11="P4",All!$AE11="RMS"),Ruler!G$17,IF(AND(All!$V11="P5",All!$AE11="RMS"),Ruler!G$18,IF(AND(All!$V11="P6",All!$AE11="RMS"),Ruler!G$19,IF(AND(All!$V11="P7",All!$AE11="RMS"),Ruler!G$20,IF(AND(All!$V11="P8",All!$AE11="RMS"),Ruler!G$21,IF(AND(All!$V11="P9",All!$AE11="RMS"),Ruler!G$22,IF(AND(All!$V11="P1",All!$AE11="RSS"),Ruler!G$6,IF(AND(All!$V11="P2",All!$AE11="RSS"),Ruler!G$23,IF(AND(All!$V11="P3",All!$AE11="RSS"),Ruler!G$24,IF(AND(All!$V11="P4",All!$AE11="RSS"),Ruler!G$25,IF(AND(All!$V11="P5",All!$AE11="RSS"),Ruler!G$26,IF(AND(All!$V11="P6",All!$AE11="RSS"),Ruler!G$27,IF(AND(All!$V11="P7",All!$AE11="RSS"),Ruler!G$28,IF(AND(All!$V11="P8",All!$AE11="RSS"),Ruler!G$29,IF(AND(All!$V11="P9",All!$AE11="RSS"),Ruler!G$30,0))))))))))))))))))))))))))) -> 2 | BO11: =IF(AND(All!$V11="P1",All!$AE11="RDP"),Ruler!H$6,IF(AND(All!$V11="P2",All!$AE11="RDP"),Ruler!H$7,IF(AND(All!$V11="P3",All!$AE11="RDP"),Ruler!H$8,IF(AND(All!$V11="P4",All!$AE11="RDP"),Ruler!H$9,IF(AND(All!$V11="P5",All!$AE11="RDP"),Ruler!H$10,IF(AND(All!$V11="P6",All!$AE11="RDP"),Ruler!H$11,IF(AND(All!$V11="P7",All!$AE11="RDP"),Ruler!H$12,IF(AND(All!$V11="P8",All!$AE11="RDP"),Ruler!H$13,IF(AND(All!$V11="P9",All!$AE11="RDP"),Ruler!H$14,IF(AND(All!$V11="P1",All!$AE11="RMS"),Ruler!H$6,IF(AND(All!$V11="P2",All!$AE11="RMS"),Ruler!H$15,IF(AND(All!$V11="P3",All!$AE11="RMS"),Ruler!H$16,IF(AND(All!$V11="P4",All!$AE11="RMS"),Ruler!H$17,IF(AND(All!$V11="P5",All!$AE11="RMS"),Ruler!H$18,IF(AND(All!$V11="P6",All!$AE11="RMS"),Ruler!H$19,IF(AND(All!$V11="P7",All!$AE11="RMS"),Ruler!H$20,IF(AND(All!$V11="P8",All!$AE11="RMS"),Ruler!H$21,IF(AND(All!$V11="P9",All!$AE11="RMS"),Ruler!H$22,IF(AND(All!$V11="P1",All!$AE11="RSS"),Ruler!H$6,IF(AND(All!$V11="P2",All!$AE11="RSS"),Ruler!H$23,IF(AND(All!$V11="P3",All!$AE11="RSS"),Ruler!H$24,IF(AND(All!$V11="P4",All!$AE11="RSS"),Ruler!H$25,IF(AND(All!$V11="P5",All!$AE11="RSS"),Ruler!H$26,IF(AND(All!$V11="P6",All!$AE11="RSS"),Ruler!H$27,IF(AND(All!$V11="P7",All!$AE11="RSS"),Ruler!H$28,IF(AND(All!$V11="P8",All!$AE11="RSS"),Ruler!H$29,IF(AND(All!$V11="P9",All!$AE11="RSS"),Ruler!H$30,0))))))))))))))))))))))))))) -> 2 | BP11: =IF(AND(All!$V11="P1",All!$AE11="RDP"),Ruler!I$6,IF(AND(All!$V11="P2",All!$AE11="RDP"),Ruler!I$7,IF(AND(All!$V11="P3",All!$AE11="RDP"),Ruler!I$8,IF(AND(All!$V11="P4",All!$AE11="RDP"),Ruler!I$9,IF(AND(All!$V11="P5",All!$AE11="RDP"),Ruler!I$10,IF(AND(All!$V11="P6",All!$AE11="RDP"),Ruler!I$11,IF(AND(All!$V11="P7",All!$AE11="RDP"),Ruler!I$12,IF(AND(All!$V11="P8",All!$AE11="RDP"),Ruler!I$13,IF(AND(All!$V11="P9",All!$AE11="RDP"),Ruler!I$14,IF(AND(All!$V11="P1",All!$AE11="RMS"),Ruler!I$6,IF(AND(All!$V11="P2",All!$AE11="RMS"),Ruler!I$15,IF(AND(All!$V11="P3",All!$AE11="RMS"),Ruler!I$16,IF(AND(All!$V11="P4",All!$AE11="RMS"),Ruler!I$17,IF(AND(All!$V11="P5",All!$AE11="RMS"),Ruler!I$18,IF(AND(All!$V11="P6",All!$AE11="RMS"),Ruler!I$19,IF(AND(All!$V11="P7",All!$AE11="RMS"),Ruler!I$20,IF(AND(All!$V11="P8",All!$AE11="RMS"),Ruler!I$21,IF(AND(All!$V11="P9",All!$AE11="RMS"),Ruler!I$22,IF(AND(All!$V11="P1",All!$AE11="RSS"),Ruler!I$6,IF(AND(All!$V11="P2",All!$AE11="RSS"),Ruler!I$23,IF(AND(All!$V11="P3",All!$AE11="RSS"),Ruler!I$24,IF(AND(All!$V11="P4",All!$AE11="RSS"),Ruler!I$25,IF(AND(All!$V11="P5",All!$AE11="RSS"),Ruler!I$26,IF(AND(All!$V11="P6",All!$AE11="RSS"),Ruler!I$27,IF(AND(All!$V11="P7",All!$AE11="RSS"),Ruler!I$28,IF(AND(All!$V11="P8",All!$AE11="RSS"),Ruler!I$29,IF(AND(All!$V11="P9",All!$AE11="RSS"),Ruler!I$30,0))))))))))))))))))))))))))) -> 3 | BQ11: =IF(AND(All!$V11="P1",All!$AE11="RDP"),Ruler!J$6,IF(AND(All!$V11="P2",All!$AE11="RDP"),Ruler!J$7,IF(AND(All!$V11="P3",All!$AE11="RDP"),Ruler!J$8,IF(AND(All!$V11="P4",All!$AE11="RDP"),Ruler!J$9,IF(AND(All!$V11="P5",All!$AE11="RDP"),Ruler!J$10,IF(AND(All!$V11="P6",All!$AE11="RDP"),Ruler!J$11,IF(AND(All!$V11="P7",All!$AE11="RDP"),Ruler!J$12,IF(AND(All!$V11="P8",All!$AE11="RDP"),Ruler!J$13,IF(AND(All!$V11="P9",All!$AE11="RDP"),Ruler!J$14,IF(AND(All!$V11="P1",All!$AE11="RMS"),Ruler!J$6,IF(AND(All!$V11="P2",All!$AE11="RMS"),Ruler!J$15,IF(AND(All!$V11="P3",All!$AE11="RMS"),Ruler!J$16,IF(AND(All!$V11="P4",All!$AE11="RMS"),Ruler!J$17,IF(AND(All!$V11="P5",All!$AE11="RMS"),Ruler!J$18,IF(AND(All!$V11="P6",All!$AE11="RMS"),Ruler!J$19,IF(AND(All!$V11="P7",All!$AE11="RMS"),Ruler!J$20,IF(AND(All!$V11="P8",All!$AE11="RMS"),Ruler!J$21,IF(AND(All!$V11="P9",All!$AE11="RMS"),Ruler!J$22,IF(AND(All!$V11="P1",All!$AE11="RSS"),Ruler!J$6,IF(AND(All!$V11="P2",All!$AE11="RSS"),Ruler!J$23,IF(AND(All!$V11="P3",All!$AE11="RSS"),Ruler!J$24,IF(AND(All!$V11="P4",All!$AE11="RSS"),Ruler!J$25,IF(AND(All!$V11="P5",All!$AE11="RSS"),Ruler!J$26,IF(AND(All!$V11="P6",All!$AE11="RSS"),Ruler!J$27,IF(AND(All!$V11="P7",All!$AE11="RSS"),Ruler!J$28,IF(AND(All!$V11="P8",All!$AE11="RSS"),Ruler!J$29,IF(AND(All!$V11="P9",All!$AE11="RSS"),Ruler!J$30,0))))))))))))))))))))))))))) -> 1 | BR11: =IF(AND(All!$V11="P1",All!$AE11="RDP"),Ruler!K$6,IF(AND(All!$V11="P2",All!$AE11="RDP"),Ruler!K$7,IF(AND(All!$V11="P3",All!$AE11="RDP"),Ruler!K$8,IF(AND(All!$V11="P4",All!$AE11="RDP"),Ruler!K$9,IF(AND(All!$V11="P5",All!$AE11="RDP"),Ruler!K$10,IF(AND(All!$V11="P6",All!$AE11="RDP"),Ruler!K$11,IF(AND(All!$V11="P7",All!$AE11="RDP"),Ruler!K$12,IF(AND(All!$V11="P8",All!$AE11="RDP"),Ruler!K$13,IF(AND(All!$V11="P9",All!$AE11="RDP"),Ruler!K$14,IF(AND(All!$V11="P1",All!$AE11="RMS"),Ruler!K$6,IF(AND(All!$V11="P2",All!$AE11="RMS"),Ruler!K$15,IF(AND(All!$V11="P3",All!$AE11="RMS"),Ruler!K$16,IF(AND(All!$V11="P4",All!$AE11="RMS"),Ruler!K$17,IF(AND(All!$V11="P5",All!$AE11="RMS"),Ruler!K$18,IF(AND(All!$V11="P6",All!$AE11="RMS"),Ruler!K$19,IF(AND(All!$V11="P7",All!$AE11="RMS"),Ruler!K$20,IF(AND(All!$V11="P8",All!$AE11="RMS"),Ruler!K$21,IF(AND(All!$V11="P9",All!$AE11="RMS"),Ruler!K$22,IF(AND(All!$V11="P1",All!$AE11="RSS"),Ruler!K$6,IF(AND(All!$V11="P2",All!$AE11="RSS"),Ruler!K$23,IF(AND(All!$V11="P3",All!$AE11="RSS"),Ruler!K$24,IF(AND(All!$V11="P4",All!$AE11="RSS"),Ruler!K$25,IF(AND(All!$V11="P5",All!$AE11="RSS"),Ruler!K$26,IF(AND(All!$V11="P6",All!$AE11="RSS"),Ruler!K$27,IF(AND(All!$V11="P7",All!$AE11="RSS"),Ruler!K$28,IF(AND(All!$V11="P8",All!$AE11="RSS"),Ruler!K$29,IF(AND(All!$V11="P9",All!$AE11="RSS"),Ruler!K$30,0))))))))))))))))))))))))))) -> 2 | BS11: =IF(AND(All!$V11="P1",All!$AE11="RDP"),Ruler!L$6,IF(AND(All!$V11="P2",All!$AE11="RDP"),Ruler!L$7,IF(AND(All!$V11="P3",All!$AE11="RDP"),Ruler!L$8,IF(AND(All!$V11="P4",All!$AE11="RDP"),Ruler!L$9,IF(AND(All!$V11="P5",All!$AE11="RDP"),Ruler!L$10,IF(AND(All!$V11="P6",All!$AE11="RDP"),Ruler!L$11,IF(AND(All!$V11="P7",All!$AE11="RDP"),Ruler!L$12,IF(AND(All!$V11="P8",All!$AE11="RDP"),Ruler!L$13,IF(AND(All!$V11="P9",All!$AE11="RDP"),Ruler!L$14,IF(AND(All!$V11="P1",All!$AE11="RMS"),Ruler!L$6,IF(AND(All!$V11="P2",All!$AE11="RMS"),Ruler!L$15,IF(AND(All!$V11="P3",All!$AE11="RMS"),Ruler!L$16,IF(AND(All!$V11="P4",All!$AE11="RMS"),Ruler!L$17,IF(AND(All!$V11="P5",All!$AE11="RMS"),Ruler!L$18,IF(AND(All!$V11="P6",All!$AE11="RMS"),Ruler!L$19,IF(AND(All!$V11="P7",All!$AE11="RMS"),Ruler!L$20,IF(AND(All!$V11="P8",All!$AE11="RMS"),Ruler!L$21,IF(AND(All!$V11="P9",All!$AE11="RMS"),Ruler!L$22,IF(AND(All!$V11="P1",All!$AE11="RSS"),Ruler!L$6,IF(AND(All!$V11="P2",All!$AE11="RSS"),Ruler!L$23,IF(AND(All!$V11="P3",All!$AE11="RSS"),Ruler!L$24,IF(AND(All!$V11="P4",All!$AE11="RSS"),Ruler!L$25,IF(AND(All!$V11="P5",All!$AE11="RSS"),Ruler!L$26,IF(AND(All!$V11="P6",All!$AE11="RSS"),Ruler!L$27,IF(AND(All!$V11="P7",All!$AE11="RSS"),Ruler!L$28,IF(AND(All!$V11="P8",All!$AE11="RSS"),Ruler!L$29,IF(AND(All!$V11="P9",All!$AE11="RSS"),Ruler!L$30,0))))))))))))))))))))))))))) -> 2 | ... CI11: =IF(AND(All!$V11="P1",All!$AE11="RDP"),Ruler!AB$6,IF(AND(All!$V11="P2",All!$AE11="RDP"),Ruler!AB$7,IF(AND(All!$V11="P3",All!$AE11="RDP"),Ruler!AB$8,IF(AND(All!$V11="P4",All!$AE11="RDP"),Ruler!AB$9,IF(AND(All!$V11="P5",All!$AE11="RDP"),Ruler!AB$10,IF(AND(All!$V11="P6",All!$AE11="RDP"),Ruler!AB$11,IF(AND(All!$V11="P7",All!$AE11="RDP"),Ruler!AB$12,IF(AND(All!$V11="P8",All!$AE11="RDP"),Ruler!AB$13,IF(AND(All!$V11="P9",All!$AE11="RDP"),Ruler!AB$14,IF(AND(All!$V11="P1",All!$AE11="RMS"),Ruler!AB$6,IF(AND(All!$V11="P2",All!$AE11="RMS"),Ruler!AB$15,IF(AND(All!$V11="P3",All!$AE11="RMS"),Ruler!AB$16,IF(AND(All!$V11="P4",All!$AE11="RMS"),Ruler!AB$17,IF(AND(All!$V11="P5",All!$AE11="RMS"),Ruler!AB$18,IF(AND(All!$V11="P6",All!$AE11="RMS"),Ruler!AB$19,IF(AND(All!$V11="P7",All!$AE11="RMS"),Ruler!AB$20,IF(AND(All!$V11="P8",All!$AE11="RMS"),Ruler!AB$21,IF(AND(All!$V11="P9",All!$AE11="RMS"),Ruler!AB$22,IF(AND(All!$V11="P1",All!$AE11="RSS"),Ruler!AB$6,IF(AND(All!$V11="P2",All!$AE11="RSS"),Ruler!AB$23,IF(AND(All!$V11="P3",All!$AE11="RSS"),Ruler!AB$24,IF(AND(All!$V11="P4",All!$AE11="RSS"),Ruler!AB$25,IF(AND(All!$V11="P5",All!$AE11="RSS"),Ruler!AB$26,IF(AND(All!$V11="P6",All!$AE11="RSS"),Ruler!AB$27,IF(AND(All!$V11="P7",All!$AE11="RSS"),Ruler!AB$28,IF(AND(All!$V11="P8",All!$AE11="RSS"),Ruler!AB$29,IF(AND(All!$V11="P9",All!$AE11="RSS"),Ruler!AB$30,0))))))))))))))))))))))))))) -> 0 | DH11: =COUNTIF(Table9[[#This Row],[G-B1]:[G-B12]],"<=0")/12*100 -> 0 | DI11: =COUNTIF(Table9[[#This Row],[G-K1]:[G-K5]],"<=0")/5*100 -> 0 | DJ11: =COUNTIF(Table9[[#This Row],[G-P1]:[G-P5]],"<=0")/5*100 -> 0 | DK11: =COUNTIF(Table9[[#This Row],[G-E1]:[G-E2]],"<=0")/2*100 -> 0 | DL11: =IF(AE11="RDP",(COUNTIF(Table9[[#This Row],[G-B3]],"<=0")+COUNTIF(Table9[[#This Row],[G-B4]],"<=0")+COUNTIF(Table9[[#This Row],[G-B7]],"<=0")+COUNTIF(Table9[[#This Row],[G-B11]],"<=0")+COUNTIF(Table9[[#This Row],[G-K2]],"<=0"))/5*100,IF(AE11="RMS",(COUNTIF(Table9[[#This Row],[G-B4]],"<=0")+COUNTIF(Table9[[#This Row],[G-B5]],"<=0")+COUNTIF(Table9[[#This Row],[G-B10]],"<=0")+COUNTIF(Table9[[#This Row],[G-B12]],"<=0")+COUNTIF(Table9[[#This Row],[G-K2]],"<=0"))/5*100,IF(AE11="RSS",(COUNTIF(Table9[[#This Row],[G-B1]],"<=0")+COUNTIF(Table9[[#This Row],[G-B2]],"<=0")+COUNTIF(Table9[[#This Row],[G-B6]],"<=0")+COUNTIF(Table9[[#This Row],[G-B11]],"<=0")+COUNTIF(Table9[[#This Row],[G-B12]],"<=0"))/5*100,0))) -> 0 | EE11: To follow-up
B12: 9 | C12: Yes | D12: 46120 | E12: Ahmad Khanifar | F12: 1018659 | G12: =($T$1-H12)/365 -> 49.834609 | H12: 28126 | I12: M | J12: Iran | K12: DPE | L12: RSS | M12: Line | O12: Principal | P12: ahmad.khanifar@petronas.com | Q12: Permanent | R12: N/A | S12: 41599 | T12: =YEARFRAC(S12,$T$1) -> 12.913889 | U12: 26 | V12: P7 | W12: =Table9[[#This Row],[Age]]-($T$1-Table9[[#This Row],[Date of Appointment to Current Grade]])/365 -> 49.194521 | X12: =($T$1-Table9[[#This Row],[Date of Appointment to Current Grade]])/365 -> 0.6400884 | Y12: 46082 | Z12: KUL | AA12: 46082 | AB12: =($T$1-Table9[[#This Row],[Date in Position]])/365 -> 0.6400884 | AC12: Principal | AD12: 45334 | AE12: RSS | AF12: High | AG12: NISOC Iran (01-10) - fracturing dynamic model, HM, fluid and rock characterisation, reserve estimation. UTP (10-13) - research officer, EOR project, laboratory experiments coreflooding, PVT, slim coil, SCAL. PCSB (12-21) - Special study - Baram Gas EOR, IWAG coreflood experiments, dynamic modeling, hysteresis modeling, SMRG GASWAG full-field model, Angsi chemical EOR,infill drilling study. Technology TL (21-23) - lead technology project inception to full deplyment such as AI HGOR well control, Oil rim mgt system, Novel Scale inhibitor, Nano pre-flush, AI/ML downhole data interpretation, geothermal/green hydrogen, saline aqufer storage. SDP (23-25) - SDP TL, developed CCS master plan, manage subsurface team, supervise CO2 sequestration modeling. RSS (25-now) - continue on CCS project as TA | AH12: ✅EOR, asphaltene, WAG and Chemical ✅ Advanced modeling (fracture, compositional, coupling with Geomechanic) ✅ PVT laboratory and characterisation ✅ SCAL - lab and analysis ✅ CCS/MMV | AI12: • Conduct a self‑assessment against the Principal role requirements to identify critical capability gaps. • Identify potential skill gaps that can be addressed through the current job scope and on‑the‑job exposure. | AJ12: CCS/MMV | AK12: MMV | AL12: TP | AM12: Improve engagement with Custodian | AN12: 4 | AO12: 4 | AP12: 3 | AQ12: 3 | AR12: 3 | AS12: 4 | AT12: 4 | AU12: 3 | AV12: 3 | AW12: 2 | AX12: 4 | AY12: 3 | AZ12: 3 | BA12: 2 | BB12: 3 | BC12: 3 | BD12: 3 | BE12: 3 | BF12: 3 | BG12: 3 | BH12: 2 | BI12: 1 | BJ12: 2 | BK12: 2 | BL12: =IF(AND(All!$V12="P1",All!$AE12="RDP"),Ruler!E$6,IF(AND(All!$V12="P2",All!$AE12="RDP"),Ruler!E$7,IF(AND(All!$V12="P3",All!$AE12="RDP"),Ruler!E$8,IF(AND(All!$V12="P4",All!$AE12="RDP"),Ruler!E$9,IF(AND(All!$V12="P5",All!$AE12="RDP"),Ruler!E$10,IF(AND(All!$V12="P6",All!$AE12="RDP"),Ruler!E$11,IF(AND(All!$V12="P7",All!$AE12="RDP"),Ruler!E$12,IF(AND(All!$V12="P8",All!$AE12="RDP"),Ruler!E$13,IF(AND(All!$V12="P9",All!$AE12="RDP"),Ruler!E$14,IF(AND(All!$V12="P1",All!$AE12="RMS"),Ruler!E$6,IF(AND(All!$V12="P2",All!$AE12="RMS"),Ruler!E$15,IF(AND(All!$V12="P3",All!$AE12="RMS"),Ruler!E$16,IF(AND(All!$V12="P4",All!$AE12="RMS"),Ruler!E$17,IF(AND(All!$V12="P5",All!$AE12="RMS"),Ruler!E$18,IF(AND(All!$V12="P6",All!$AE12="RMS"),Ruler!E$19,IF(AND(All!$V12="P7",All!$AE12="RMS"),Ruler!E$20,IF(AND(All!$V12="P8",All!$AE12="RMS"),Ruler!E$21,IF(AND(All!$V12="P9",All!$AE12="RMS"),Ruler!E$22,IF(AND(All!$V12="P1",All!$AE12="RSS"),Ruler!E$6,IF(AND(All!$V12="P2",All!$AE12="RSS"),Ruler!E$23,IF(AND(All!$V12="P3",All!$AE12="RSS"),Ruler!E$24,IF(AND(All!$V12="P4",All!$AE12="RSS"),Ruler!E$25,IF(AND(All!$V12="P5",All!$AE12="RSS"),Ruler!E$26,IF(AND(All!$V12="P6",All!$AE12="RSS"),Ruler!E$27,IF(AND(All!$V12="P7",All!$AE12="RSS"),Ruler!E$28,IF(AND(All!$V12="P8",All!$AE12="RSS"),Ruler!E$29,IF(AND(All!$V12="P9",All!$AE12="RSS"),Ruler!E$30,0))))))))))))))))))))))))))) -> 4 | BM12: =IF(AND(All!$V12="P1",All!$AE12="RDP"),Ruler!F$6,IF(AND(All!$V12="P2",All!$AE12="RDP"),Ruler!F$7,IF(AND(All!$V12="P3",All!$AE12="RDP"),Ruler!F$8,IF(AND(All!$V12="P4",All!$AE12="RDP"),Ruler!F$9,IF(AND(All!$V12="P5",All!$AE12="RDP"),Ruler!F$10,IF(AND(All!$V12="P6",All!$AE12="RDP"),Ruler!F$11,IF(AND(All!$V12="P7",All!$AE12="RDP"),Ruler!F$12,IF(AND(All!$V12="P8",All!$AE12="RDP"),Ruler!F$13,IF(AND(All!$V12="P9",All!$AE12="RDP"),Ruler!F$14,IF(AND(All!$V12="P1",All!$AE12="RMS"),Ruler!F$6,IF(AND(All!$V12="P2",All!$AE12="RMS"),Ruler!F$15,IF(AND(All!$V12="P3",All!$AE12="RMS"),Ruler!F$16,IF(AND(All!$V12="P4",All!$AE12="RMS"),Ruler!F$17,IF(AND(All!$V12="P5",All!$AE12="RMS"),Ruler!F$18,IF(AND(All!$V12="P6",All!$AE12="RMS"),Ruler!F$19,IF(AND(All!$V12="P7",All!$AE12="RMS"),Ruler!F$20,IF(AND(All!$V12="P8",All!$AE12="RMS"),Ruler!F$21,IF(AND(All!$V12="P9",All!$AE12="RMS"),Ruler!F$22,IF(AND(All!$V12="P1",All!$AE12="RSS"),Ruler!F$6,IF(AND(All!$V12="P2",All!$AE12="RSS"),Ruler!F$23,IF(AND(All!$V12="P3",All!$AE12="RSS"),Ruler!F$24,IF(AND(All!$V12="P4",All!$AE12="RSS"),Ruler!F$25,IF(AND(All!$V12="P5",All!$AE12="RSS"),Ruler!F$26,IF(AND(All!$V12="P6",All!$AE12="RSS"),Ruler!F$27,IF(AND(All!$V12="P7",All!$AE12="RSS"),Ruler!F$28,IF(AND(All!$V12="P8",All!$AE12="RSS"),Ruler!F$29,IF(AND(All!$V12="P9",All!$AE12="RSS"),Ruler!F$30,0))))))))))))))))))))))))))) -> 4 | BN12: =IF(AND(All!$V12="P1",All!$AE12="RDP"),Ruler!G$6,IF(AND(All!$V12="P2",All!$AE12="RDP"),Ruler!G$7,IF(AND(All!$V12="P3",All!$AE12="RDP"),Ruler!G$8,IF(AND(All!$V12="P4",All!$AE12="RDP"),Ruler!G$9,IF(AND(All!$V12="P5",All!$AE12="RDP"),Ruler!G$10,IF(AND(All!$V12="P6",All!$AE12="RDP"),Ruler!G$11,IF(AND(All!$V12="P7",All!$AE12="RDP"),Ruler!G$12,IF(AND(All!$V12="P8",All!$AE12="RDP"),Ruler!G$13,IF(AND(All!$V12="P9",All!$AE12="RDP"),Ruler!G$14,IF(AND(All!$V12="P1",All!$AE12="RMS"),Ruler!G$6,IF(AND(All!$V12="P2",All!$AE12="RMS"),Ruler!G$15,IF(AND(All!$V12="P3",All!$AE12="RMS"),Ruler!G$16,IF(AND(All!$V12="P4",All!$AE12="RMS"),Ruler!G$17,IF(AND(All!$V12="P5",All!$AE12="RMS"),Ruler!G$18,IF(AND(All!$V12="P6",All!$AE12="RMS"),Ruler!G$19,IF(AND(All!$V12="P7",All!$AE12="RMS"),Ruler!G$20,IF(AND(All!$V12="P8",All!$AE12="RMS"),Ruler!G$21,IF(AND(All!$V12="P9",All!$AE12="RMS"),Ruler!G$22,IF(AND(All!$V12="P1",All!$AE12="RSS"),Ruler!G$6,IF(AND(All!$V12="P2",All!$AE12="RSS"),Ruler!G$23,IF(AND(All!$V12="P3",All!$AE12="RSS"),Ruler!G$24,IF(AND(All!$V12="P4",All!$AE12="RSS"),Ruler!G$25,IF(AND(All!$V12="P5",All!$AE12="RSS"),Ruler!G$26,IF(AND(All!$V12="P6",All!$AE12="RSS"),Ruler!G$27,IF(AND(All!$V12="P7",All!$AE12="RSS"),Ruler!G$28,IF(AND(All!$V12="P8",All!$AE12="RSS"),Ruler!G$29,IF(AND(All!$V12="P9",All!$AE12="RSS"),Ruler!G$30,0))))))))))))))))))))))))))) -> 3 | BO12: =IF(AND(All!$V12="P1",All!$AE12="RDP"),Ruler!H$6,IF(AND(All!$V12="P2",All!$AE12="RDP"),Ruler!H$7,IF(AND(All!$V12="P3",All!$AE12="RDP"),Ruler!H$8,IF(AND(All!$V12="P4",All!$AE12="RDP"),Ruler!H$9,IF(AND(All!$V12="P5",All!$AE12="RDP"),Ruler!H$10,IF(AND(All!$V12="P6",All!$AE12="RDP"),Ruler!H$11,IF(AND(All!$V12="P7",All!$AE12="RDP"),Ruler!H$12,IF(AND(All!$V12="P8",All!$AE12="RDP"),Ruler!H$13,IF(AND(All!$V12="P9",All!$AE12="RDP"),Ruler!H$14,IF(AND(All!$V12="P1",All!$AE12="RMS"),Ruler!H$6,IF(AND(All!$V12="P2",All!$AE12="RMS"),Ruler!H$15,IF(AND(All!$V12="P3",All!$AE12="RMS"),Ruler!H$16,IF(AND(All!$V12="P4",All!$AE12="RMS"),Ruler!H$17,IF(AND(All!$V12="P5",All!$AE12="RMS"),Ruler!H$18,IF(AND(All!$V12="P6",All!$AE12="RMS"),Ruler!H$19,IF(AND(All!$V12="P7",All!$AE12="RMS"),Ruler!H$20,IF(AND(All!$V12="P8",All!$AE12="RMS"),Ruler!H$21,IF(AND(All!$V12="P9",All!$AE12="RMS"),Ruler!H$22,IF(AND(All!$V12="P1",All!$AE12="RSS"),Ruler!H$6,IF(AND(All!$V12="P2",All!$AE12="RSS"),Ruler!H$23,IF(AND(All!$V12="P3",All!$AE12="RSS"),Ruler!H$24,IF(AND(All!$V12="P4",All!$AE12="RSS"),Ruler!H$25,IF(AND(All!$V12="P5",All!$AE12="RSS"),Ruler!H$26,IF(AND(All!$V12="P6",All!$AE12="RSS"),Ruler!H$27,IF(AND(All!$V12="P7",All!$AE12="RSS"),Ruler!H$28,IF(AND(All!$V12="P8",All!$AE12="RSS"),Ruler!H$29,IF(AND(All!$V12="P9",All!$AE12="RSS"),Ruler!H$30,0))))))))))))))))))))))))))) -> 3 | BP12: =IF(AND(All!$V12="P1",All!$AE12="RDP"),Ruler!I$6,IF(AND(All!$V12="P2",All!$AE12="RDP"),Ruler!I$7,IF(AND(All!$V12="P3",All!$AE12="RDP"),Ruler!I$8,IF(AND(All!$V12="P4",All!$AE12="RDP"),Ruler!I$9,IF(AND(All!$V12="P5",All!$AE12="RDP"),Ruler!I$10,IF(AND(All!$V12="P6",All!$AE12="RDP"),Ruler!I$11,IF(AND(All!$V12="P7",All!$AE12="RDP"),Ruler!I$12,IF(AND(All!$V12="P8",All!$AE12="RDP"),Ruler!I$13,IF(AND(All!$V12="P9",All!$AE12="RDP"),Ruler!I$14,IF(AND(All!$V12="P1",All!$AE12="RMS"),Ruler!I$6,IF(AND(All!$V12="P2",All!$AE12="RMS"),Ruler!I$15,IF(AND(All!$V12="P3",All!$AE12="RMS"),Ruler!I$16,IF(AND(All!$V12="P4",All!$AE12="RMS"),Ruler!I$17,IF(AND(All!$V12="P5",All!$AE12="RMS"),Ruler!I$18,IF(AND(All!$V12="P6",All!$AE12="RMS"),Ruler!I$19,IF(AND(All!$V12="P7",All!$AE12="RMS"),Ruler!I$20,IF(AND(All!$V12="P8",All!$AE12="RMS"),Ruler!I$21,IF(AND(All!$V12="P9",All!$AE12="RMS"),Ruler!I$22,IF(AND(All!$V12="P1",All!$AE12="RSS"),Ruler!I$6,IF(AND(All!$V12="P2",All!$AE12="RSS"),Ruler!I$23,IF(AND(All!$V12="P3",All!$AE12="RSS"),Ruler!I$24,IF(AND(All!$V12="P4",All!$AE12="RSS"),Ruler!I$25,IF(AND(All!$V12="P5",All!$AE12="RSS"),Ruler!I$26,IF(AND(All!$V12="P6",All!$AE12="RSS"),Ruler!I$27,IF(AND(All!$V12="P7",All!$AE12="RSS"),Ruler!I$28,IF(AND(All!$V12="P8",All!$AE12="RSS"),Ruler!I$29,IF(AND(All!$V12="P9",All!$AE12="RSS"),Ruler!I$30,0))))))))))))))))))))))))))) -> 3 | BQ12: =IF(AND(All!$V12="P1",All!$AE12="RDP"),Ruler!J$6,IF(AND(All!$V12="P2",All!$AE12="RDP"),Ruler!J$7,IF(AND(All!$V12="P3",All!$AE12="RDP"),Ruler!J$8,IF(AND(All!$V12="P4",All!$AE12="RDP"),Ruler!J$9,IF(AND(All!$V12="P5",All!$AE12="RDP"),Ruler!J$10,IF(AND(All!$V12="P6",All!$AE12="RDP"),Ruler!J$11,IF(AND(All!$V12="P7",All!$AE12="RDP"),Ruler!J$12,IF(AND(All!$V12="P8",All!$AE12="RDP"),Ruler!J$13,IF(AND(All!$V12="P9",All!$AE12="RDP"),Ruler!J$14,IF(AND(All!$V12="P1",All!$AE12="RMS"),Ruler!J$6,IF(AND(All!$V12="P2",All!$AE12="RMS"),Ruler!J$15,IF(AND(All!$V12="P3",All!$AE12="RMS"),Ruler!J$16,IF(AND(All!$V12="P4",All!$AE12="RMS"),Ruler!J$17,IF(AND(All!$V12="P5",All!$AE12="RMS"),Ruler!J$18,IF(AND(All!$V12="P6",All!$AE12="RMS"),Ruler!J$19,IF(AND(All!$V12="P7",All!$AE12="RMS"),Ruler!J$20,IF(AND(All!$V12="P8",All!$AE12="RMS"),Ruler!J$21,IF(AND(All!$V12="P9",All!$AE12="RMS"),Ruler!J$22,IF(AND(All!$V12="P1",All!$AE12="RSS"),Ruler!J$6,IF(AND(All!$V12="P2",All!$AE12="RSS"),Ruler!J$23,IF(AND(All!$V12="P3",All!$AE12="RSS"),Ruler!J$24,IF(AND(All!$V12="P4",All!$AE12="RSS"),Ruler!J$25,IF(AND(All!$V12="P5",All!$AE12="RSS"),Ruler!J$26,IF(AND(All!$V12="P6",All!$AE12="RSS"),Ruler!J$27,IF(AND(All!$V12="P7",All!$AE12="RSS"),Ruler!J$28,IF(AND(All!$V12="P8",All!$AE12="RSS"),Ruler!J$29,IF(AND(All!$V12="P9",All!$AE12="RSS"),Ruler!J$30,0))))))))))))))))))))))))))) -> 5 | BR12: =IF(AND(All!$V12="P1",All!$AE12="RDP"),Ruler!K$6,IF(AND(All!$V12="P2",All!$AE12="RDP"),Ruler!K$7,IF(AND(All!$V12="P3",All!$AE12="RDP"),Ruler!K$8,IF(AND(All!$V12="P4",All!$AE12="RDP"),Ruler!K$9,IF(AND(All!$V12="P5",All!$AE12="RDP"),Ruler!K$10,IF(AND(All!$V12="P6",All!$AE12="RDP"),Ruler!K$11,IF(AND(All!$V12="P7",All!$AE12="RDP"),Ruler!K$12,IF(AND(All!$V12="P8",All!$AE12="RDP"),Ruler!K$13,IF(AND(All!$V12="P9",All!$AE12="RDP"),Ruler!K$14,IF(AND(All!$V12="P1",All!$AE12="RMS"),Ruler!K$6,IF(AND(All!$V12="P2",All!$AE12="RMS"),Ruler!K$15,IF(AND(All!$V12="P3",All!$AE12="RMS"),Ruler!K$16,IF(AND(All!$V12="P4",All!$AE12="RMS"),Ruler!K$17,IF(AND(All!$V12="P5",All!$AE12="RMS"),Ruler!K$18,IF(AND(All!$V12="P6",All!$AE12="RMS"),Ruler!K$19,IF(AND(All!$V12="P7",All!$AE12="RMS"),Ruler!K$20,IF(AND(All!$V12="P8",All!$AE12="RMS"),Ruler!K$21,IF(AND(All!$V12="P9",All!$AE12="RMS"),Ruler!K$22,IF(AND(All!$V12="P1",All!$AE12="RSS"),Ruler!K$6,IF(AND(All!$V12="P2",All!$AE12="RSS"),Ruler!K$23,IF(AND(All!$V12="P3",All!$AE12="RSS"),Ruler!K$24,IF(AND(All!$V12="P4",All!$AE12="RSS"),Ruler!K$25,IF(AND(All!$V12="P5",All!$AE12="RSS"),Ruler!K$26,IF(AND(All!$V12="P6",All!$AE12="RSS"),Ruler!K$27,IF(AND(All!$V12="P7",All!$AE12="RSS"),Ruler!K$28,IF(AND(All!$V12="P8",All!$AE12="RSS"),Ruler!K$29,IF(AND(All!$V12="P9",All!$AE12="RSS"),Ruler!K$30,0))))))))))))))))))))))))))) -> 4 | BS12: =IF(AND(All!$V12="P1",All!$AE12="RDP"),Ruler!L$6,IF(AND(All!$V12="P2",All!$AE12="RDP"),Ruler!L$7,IF(AND(All!$V12="P3",All!$AE12="RDP"),Ruler!L$8,IF(AND(All!$V12="P4",All!$AE12="RDP"),Ruler!L$9,IF(AND(All!$V12="P5",All!$AE12="RDP"),Ruler!L$10,IF(AND(All!$V12="P6",All!$AE12="RDP"),Ruler!L$11,IF(AND(All!$V12="P7",All!$AE12="RDP"),Ruler!L$12,IF(AND(All!$V12="P8",All!$AE12="RDP"),Ruler!L$13,IF(AND(All!$V12="P9",All!$AE12="RDP"),Ruler!L$14,IF(AND(All!$V12="P1",All!$AE12="RMS"),Ruler!L$6,IF(AND(All!$V12="P2",All!$AE12="RMS"),Ruler!L$15,IF(AND(All!$V12="P3",All!$AE12="RMS"),Ruler!L$16,IF(AND(All!$V12="P4",All!$AE12="RMS"),Ruler!L$17,IF(AND(All!$V12="P5",All!$AE12="RMS"),Ruler!L$18,IF(AND(All!$V12="P6",All!$AE12="RMS"),Ruler!L$19,IF(AND(All!$V12="P7",All!$AE12="RMS"),Ruler!L$20,IF(AND(All!$V12="P8",All!$AE12="RMS"),Ruler!L$21,IF(AND(All!$V12="P9",All!$AE12="RMS"),Ruler!L$22,IF(AND(All!$V12="P1",All!$AE12="RSS"),Ruler!L$6,IF(AND(All!$V12="P2",All!$AE12="RSS"),Ruler!L$23,IF(AND(All!$V12="P3",All!$AE12="RSS"),Ruler!L$24,IF(AND(All!$V12="P4",All!$AE12="RSS"),Ruler!L$25,IF(AND(All!$V12="P5",All!$AE12="RSS"),Ruler!L$26,IF(AND(All!$V12="P6",All!$AE12="RSS"),Ruler!L$27,IF(AND(All!$V12="P7",All!$AE12="RSS"),Ruler!L$28,IF(AND(All!$V12="P8",All!$AE12="RSS"),Ruler!L$29,IF(AND(All!$V12="P9",All!$AE12="RSS"),Ruler!L$30,0))))))))))))))))))))))))))) -> 3 | ... CI12: =IF(AND(All!$V12="P1",All!$AE12="RDP"),Ruler!AB$6,IF(AND(All!$V12="P2",All!$AE12="RDP"),Ruler!AB$7,IF(AND(All!$V12="P3",All!$AE12="RDP"),Ruler!AB$8,IF(AND(All!$V12="P4",All!$AE12="RDP"),Ruler!AB$9,IF(AND(All!$V12="P5",All!$AE12="RDP"),Ruler!AB$10,IF(AND(All!$V12="P6",All!$AE12="RDP"),Ruler!AB$11,IF(AND(All!$V12="P7",All!$AE12="RDP"),Ruler!AB$12,IF(AND(All!$V12="P8",All!$AE12="RDP"),Ruler!AB$13,IF(AND(All!$V12="P9",All!$AE12="RDP"),Ruler!AB$14,IF(AND(All!$V12="P1",All!$AE12="RMS"),Ruler!AB$6,IF(AND(All!$V12="P2",All!$AE12="RMS"),Ruler!AB$15,IF(AND(All!$V12="P3",All!$AE12="RMS"),Ruler!AB$16,IF(AND(All!$V12="P4",All!$AE12="RMS"),Ruler!AB$17,IF(AND(All!$V12="P5",All!$AE12="RMS"),Ruler!AB$18,IF(AND(All!$V12="P6",All!$AE12="RMS"),Ruler!AB$19,IF(AND(All!$V12="P7",All!$AE12="RMS"),Ruler!AB$20,IF(AND(All!$V12="P8",All!$AE12="RMS"),Ruler!AB$21,IF(AND(All!$V12="P9",All!$AE12="RMS"),Ruler!AB$22,IF(AND(All!$V12="P1",All!$AE12="RSS"),Ruler!AB$6,IF(AND(All!$V12="P2",All!$AE12="RSS"),Ruler!AB$23,IF(AND(All!$V12="P3",All!$AE12="RSS"),Ruler!AB$24,IF(AND(All!$V12="P4",All!$AE12="RSS"),Ruler!AB$25,IF(AND(All!$V12="P5",All!$AE12="RSS"),Ruler!AB$26,IF(AND(All!$V12="P6",All!$AE12="RSS"),Ruler!AB$27,IF(AND(All!$V12="P7",All!$AE12="RSS"),Ruler!AB$28,IF(AND(All!$V12="P8",All!$AE12="RSS"),Ruler!AB$29,IF(AND(All!$V12="P9",All!$AE12="RSS"),Ruler!AB$30,0))))))))))))))))))))))))))) -> 2 | CJ12: =Table9[[#This Row],[R-B1]]-Table9[[#This Row],[B1]] -> 0 | CK12: =Table9[[#This Row],[R-B2]]-Table9[[#This Row],[B2]] -> 0 | CL12: =Table9[[#This Row],[R-B3]]-Table9[[#This Row],[B3]] -> 0 | CM12: =Table9[[#This Row],[R-B4]]-Table9[[#This Row],[B4]] -> 0 | CN12: =Table9[[#This Row],[R-B5]]-Table9[[#This Row],[B5]] -> 0 | CO12: =Table9[[#This Row],[R-B6]]-Table9[[#This Row],[B6]] -> 1 | CP12: =Table9[[#This Row],[R-B7]]-Table9[[#This Row],[B7]] -> 0 | CQ12: =Table9[[#This Row],[R-B8]]-Table9[[#This Row],[B8]] -> 0 | CR12: =Table9[[#This Row],[R-B9]]-Table9[[#This Row],[B9]] -> 0 | CS12: =Table9[[#This Row],[R-B10]]-Table9[[#This Row],[B10]] -> 0 | CT12: =Table9[[#This Row],[R-B11]]-Table9[[#This Row],[B11]] -> 0 | CU12: =Table9[[#This Row],[R-B12]]-Table9[[#This Row],[B12]] -> 0 | CV12: =Table9[[#This Row],[R-K1]]-Table9[[#This Row],[K1]] -> 0 | CW12: =Table9[[#This Row],[R-K2]]-Table9[[#This Row],[K2]] -> 1 | CX12: =Table9[[#This Row],[R-K3]]-Table9[[#This Row],[K3]] -> 0 | CY12: =Table9[[#This Row],[R-K4]]-Table9[[#This Row],[K4]] -> -1 | CZ12: =Table9[[#This Row],[R-K5]]-Table9[[#This Row],[K5]] -> 0 | DA12: =Table9[[#This Row],[R-P1]]-Table9[[#This Row],[P1]] -> 0 | DB12: =Table9[[#This Row],[R-P2]]-Table9[[#This Row],[P2]] -> 0 | DC12: =Table9[[#This Row],[R-P3]]-Table9[[#This Row],[P3]] -> -1 | DD12: =Table9[[#This Row],[R-P4]]-Table9[[#This Row],[P4]] -> 0 | DE12: =Table9[[#This Row],[R-P5]]-Table9[[#This Row],[P5]] -> 1 | DF12: =Table9[[#This Row],[R-E1]]-Table9[[#This Row],[E1]] -> 0 | DG12: =Table9[[#This Row],[R-E2]]-Table9[[#This Row],[E2]] -> 0 | DH12: =COUNTIF(Table9[[#This Row],[G-B1]:[G-B12]],"<=0")/12*100 -> 91.666667 | DI12: =COUNTIF(Table9[[#This Row],[G-K1]:[G-K5]],"<=0")/5*100 -> 80 | DJ12: =COUNTIF(Table9[[#This Row],[G-P1]:[G-P5]],"<=0")/5*100 -> 80 | DK12: =COUNTIF(Table9[[#This Row],[G-E1]:[G-E2]],"<=0")/2*100 -> 100 | DL12: =IF(AE12="RDP",(COUNTIF(Table9[[#This Row],[G-B3]],"<=0")+COUNTIF(Table9[[#This Row],[G-B4]],"<=0")+COUNTIF(Table9[[#This Row],[G-B7]],"<=0")+COUNTIF(Table9[[#This Row],[G-B11]],"<=0")+COUNTIF(Table9[[#This Row],[G-K2]],"<=0"))/5*100,IF(AE12="RMS",(COUNTIF(Table9[[#This Row],[G-B4]],"<=0")+COUNTIF(Table9[[#This Row],[G-B5]],"<=0")+COUNTIF(Table9[[#This Row],[G-B10]],"<=0")+COUNTIF(Table9[[#This Row],[G-B12]],"<=0")+COUNTIF(Table9[[#This Row],[G-K2]],"<=0"))/5*100,IF(AE12="RSS",(COUNTIF(Table9[[#This Row],[G-B1]],"<=0")+COUNTIF(Table9[[#This Row],[G-B2]],"<=0")+COUNTIF(Table9[[#This Row],[G-B6]],"<=0")+COUNTIF(Table9[[#This Row],[G-B11]],"<=0")+COUNTIF(Table9[[#This Row],[G-B12]],"<=0"))/5*100,0))) -> 80 | DM12: 100 | DN12: 100 | DO12: 100 | DP12: 100 | DQ12: 100 | DR12: 100 | DS12: 80 | DT12: 80 | DU12: 100 | DV12: 100 | DW12: 75 | DX12: 60 | DY12: 60 | DZ12: 100 | EA12: 40 | EB12: Sai | EC12: N/A | ED12: Sharizan
B13: 10 | C13: Yes | D13: 46069 | E13: Ahmad Muzakkir bin Mohamad | F13: 140018 | G13: =($T$1-H13)/365 -> 39.829129 | H13: 31778 | I13: M | J13: Malaysia | K13: Searah | L13: PMA | M13: GPSC | O13: Staff | P13: muzakkir_mohd@petronas.com | Q13: Permanent | R13: N/A | S13: 40544 | T13: =YEARFRAC(S13,$T$1) -> 15.802778 | U13: =Table9[[#This Row],[Years in PET]] -> 15.802778 | V13: P5 | W13: =Table9[[#This Row],[Age]]-($T$1-Table9[[#This Row],[Date of Appointment to Current Grade]])/365 -> 35.772603 | X13: =($T$1-Table9[[#This Row],[Date of Appointment to Current Grade]])/365 -> 4.0565268 | Y13: 44835 | Z13: Searah-PM | AA13: 45717 | AB13: =($T$1-Table9[[#This Row],[Date in Position]])/365 -> 1.6400884 | AC13: Staff | AD13: 44490 | AE13: RDP | AF13: Good | AG13: Joined PCSB in 2011. (11-14) - Pre-Dev, Exp and Data Acq. Dpt. - design DST, data aquisiton plan and some modeling work. (14-16) - Resource Maturation and Asset Acqusition - brown field acquisition (17) - PE Specialized Study group - evaluate some noew technology e.g nano particle, SCAL using large sidewall core, Gas PVT correlation and resource reporting.(17-22) - D28 and Temana FDP with dynamic model, WI and infill scope and project execution (22-25) Promoted as Staff RE for Iraq. Led subsurface team on surveillance and further development utilizing LDM. (25-now ) GPSC TP at region now moved to Searah as Surveillance TP | AH13: ✅ Simulation model including utilizing LDM for production optimisation and recovery improvement ✅ FDP ✅ Asset acquisition | AI13: ✅ Conduct a self‑assessment against the Principal role requirements to identify critical capability gaps. ✅ Identify potential skill gaps that can be addressed through the current job scope and on‑the‑job exposure. ✅ Spearhead GPSC field LDM update and utilization ✅ Intiate small scale AI project | AJ13: • AI • LDM | AK13: • Passion in AI, already proposed some workflow to AI • Utilisation of LDM in reservoir management and optimisation as well as identify opportunity | AL13: TP | AM13: • Raised concern on GPSC young team (lack of experience) | AN13: 3 | AO13: 2 | AP13: 2 | AQ13: 3 | AR13: 3 | AS13: 3 | AT13: 3 | AU13: 2 | AV13: 3 | AW13: 2 | AX13: 3 | AY13: 2 | AZ13: 3 | BA13: 3 | BB13: 2 | BC13: 1 | BD13: 1 | BE13: 2 | BF13: 2 | BG13: 2 | BH13: 1 | BI13: 2 | BJ13: 2 | BK13: 1 | BL13: =IF(AND(All!$V13="P1",All!$AE13="RDP"),Ruler!E$6,IF(AND(All!$V13="P2",All!$AE13="RDP"),Ruler!E$7,IF(AND(All!$V13="P3",All!$AE13="RDP"),Ruler!E$8,IF(AND(All!$V13="P4",All!$AE13="RDP"),Ruler!E$9,IF(AND(All!$V13="P5",All!$AE13="RDP"),Ruler!E$10,IF(AND(All!$V13="P6",All!$AE13="RDP"),Ruler!E$11,IF(AND(All!$V13="P7",All!$AE13="RDP"),Ruler!E$12,IF(AND(All!$V13="P8",All!$AE13="RDP"),Ruler!E$13,IF(AND(All!$V13="P9",All!$AE13="RDP"),Ruler!E$14,IF(AND(All!$V13="P1",All!$AE13="RMS"),Ruler!E$6,IF(AND(All!$V13="P2",All!$AE13="RMS"),Ruler!E$15,IF(AND(All!$V13="P3",All!$AE13="RMS"),Ruler!E$16,IF(AND(All!$V13="P4",All!$AE13="RMS"),Ruler!E$17,IF(AND(All!$V13="P5",All!$AE13="RMS"),Ruler!E$18,IF(AND(All!$V13="P6",All!$AE13="RMS"),Ruler!E$19,IF(AND(All!$V13="P7",All!$AE13="RMS"),Ruler!E$20,IF(AND(All!$V13="P8",All!$AE13="RMS"),Ruler!E$21,IF(AND(All!$V13="P9",All!$AE13="RMS"),Ruler!E$22,IF(AND(All!$V13="P1",All!$AE13="RSS"),Ruler!E$6,IF(AND(All!$V13="P2",All!$AE13="RSS"),Ruler!E$23,IF(AND(All!$V13="P3",All!$AE13="RSS"),Ruler!E$24,IF(AND(All!$V13="P4",All!$AE13="RSS"),Ruler!E$25,IF(AND(All!$V13="P5",All!$AE13="RSS"),Ruler!E$26,IF(AND(All!$V13="P6",All!$AE13="RSS"),Ruler!E$27,IF(AND(All!$V13="P7",All!$AE13="RSS"),Ruler!E$28,IF(AND(All!$V13="P8",All!$AE13="RSS"),Ruler!E$29,IF(AND(All!$V13="P9",All!$AE13="RSS"),Ruler!E$30,0))))))))))))))))))))))))))) -> 3 | BM13: =IF(AND(All!$V13="P1",All!$AE13="RDP"),Ruler!F$6,IF(AND(All!$V13="P2",All!$AE13="RDP"),Ruler!F$7,IF(AND(All!$V13="P3",All!$AE13="RDP"),Ruler!F$8,IF(AND(All!$V13="P4",All!$AE13="RDP"),Ruler!F$9,IF(AND(All!$V13="P5",All!$AE13="RDP"),Ruler!F$10,IF(AND(All!$V13="P6",All!$AE13="RDP"),Ruler!F$11,IF(AND(All!$V13="P7",All!$AE13="RDP"),Ruler!F$12,IF(AND(All!$V13="P8",All!$AE13="RDP"),Ruler!F$13,IF(AND(All!$V13="P9",All!$AE13="RDP"),Ruler!F$14,IF(AND(All!$V13="P1",All!$AE13="RMS"),Ruler!F$6,IF(AND(All!$V13="P2",All!$AE13="RMS"),Ruler!F$15,IF(AND(All!$V13="P3",All!$AE13="RMS"),Ruler!F$16,IF(AND(All!$V13="P4",All!$AE13="RMS"),Ruler!F$17,IF(AND(All!$V13="P5",All!$AE13="RMS"),Ruler!F$18,IF(AND(All!$V13="P6",All!$AE13="RMS"),Ruler!F$19,IF(AND(All!$V13="P7",All!$AE13="RMS"),Ruler!F$20,IF(AND(All!$V13="P8",All!$AE13="RMS"),Ruler!F$21,IF(AND(All!$V13="P9",All!$AE13="RMS"),Ruler!F$22,IF(AND(All!$V13="P1",All!$AE13="RSS"),Ruler!F$6,IF(AND(All!$V13="P2",All!$AE13="RSS"),Ruler!F$23,IF(AND(All!$V13="P3",All!$AE13="RSS"),Ruler!F$24,IF(AND(All!$V13="P4",All!$AE13="RSS"),Ruler!F$25,IF(AND(All!$V13="P5",All!$AE13="RSS"),Ruler!F$26,IF(AND(All!$V13="P6",All!$AE13="RSS"),Ruler!F$27,IF(AND(All!$V13="P7",All!$AE13="RSS"),Ruler!F$28,IF(AND(All!$V13="P8",All!$AE13="RSS"),Ruler!F$29,IF(AND(All!$V13="P9",All!$AE13="RSS"),Ruler!F$30,0))))))))))))))))))))))))))) -> 3 | BN13: =IF(AND(All!$V13="P1",All!$AE13="RDP"),Ruler!G$6,IF(AND(All!$V13="P2",All!$AE13="RDP"),Ruler!G$7,IF(AND(All!$V13="P3",All!$AE13="RDP"),Ruler!G$8,IF(AND(All!$V13="P4",All!$AE13="RDP"),Ruler!G$9,IF(AND(All!$V13="P5",All!$AE13="RDP"),Ruler!G$10,IF(AND(All!$V13="P6",All!$AE13="RDP"),Ruler!G$11,IF(AND(All!$V13="P7",All!$AE13="RDP"),Ruler!G$12,IF(AND(All!$V13="P8",All!$AE13="RDP"),Ruler!G$13,IF(AND(All!$V13="P9",All!$AE13="RDP"),Ruler!G$14,IF(AND(All!$V13="P1",All!$AE13="RMS"),Ruler!G$6,IF(AND(All!$V13="P2",All!$AE13="RMS"),Ruler!G$15,IF(AND(All!$V13="P3",All!$AE13="RMS"),Ruler!G$16,IF(AND(All!$V13="P4",All!$AE13="RMS"),Ruler!G$17,IF(AND(All!$V13="P5",All!$AE13="RMS"),Ruler!G$18,IF(AND(All!$V13="P6",All!$AE13="RMS"),Ruler!G$19,IF(AND(All!$V13="P7",All!$AE13="RMS"),Ruler!G$20,IF(AND(All!$V13="P8",All!$AE13="RMS"),Ruler!G$21,IF(AND(All!$V13="P9",All!$AE13="RMS"),Ruler!G$22,IF(AND(All!$V13="P1",All!$AE13="RSS"),Ruler!G$6,IF(AND(All!$V13="P2",All!$AE13="RSS"),Ruler!G$23,IF(AND(All!$V13="P3",All!$AE13="RSS"),Ruler!G$24,IF(AND(All!$V13="P4",All!$AE13="RSS"),Ruler!G$25,IF(AND(All!$V13="P5",All!$AE13="RSS"),Ruler!G$26,IF(AND(All!$V13="P6",All!$AE13="RSS"),Ruler!G$27,IF(AND(All!$V13="P7",All!$AE13="RSS"),Ruler!G$28,IF(AND(All!$V13="P8",All!$AE13="RSS"),Ruler!G$29,IF(AND(All!$V13="P9",All!$AE13="RSS"),Ruler!G$30,0))))))))))))))))))))))))))) -> 3 | BO13: =IF(AND(All!$V13="P1",All!$AE13="RDP"),Ruler!H$6,IF(AND(All!$V13="P2",All!$AE13="RDP"),Ruler!H$7,IF(AND(All!$V13="P3",All!$AE13="RDP"),Ruler!H$8,IF(AND(All!$V13="P4",All!$AE13="RDP"),Ruler!H$9,IF(AND(All!$V13="P5",All!$AE13="RDP"),Ruler!H$10,IF(AND(All!$V13="P6",All!$AE13="RDP"),Ruler!H$11,IF(AND(All!$V13="P7",All!$AE13="RDP"),Ruler!H$12,IF(AND(All!$V13="P8",All!$AE13="RDP"),Ruler!H$13,IF(AND(All!$V13="P9",All!$AE13="RDP"),Ruler!H$14,IF(AND(All!$V13="P1",All!$AE13="RMS"),Ruler!H$6,IF(AND(All!$V13="P2",All!$AE13="RMS"),Ruler!H$15,IF(AND(All!$V13="P3",All!$AE13="RMS"),Ruler!H$16,IF(AND(All!$V13="P4",All!$AE13="RMS"),Ruler!H$17,IF(AND(All!$V13="P5",All!$AE13="RMS"),Ruler!H$18,IF(AND(All!$V13="P6",All!$AE13="RMS"),Ruler!H$19,IF(AND(All!$V13="P7",All!$AE13="RMS"),Ruler!H$20,IF(AND(All!$V13="P8",All!$AE13="RMS"),Ruler!H$21,IF(AND(All!$V13="P9",All!$AE13="RMS"),Ruler!H$22,IF(AND(All!$V13="P1",All!$AE13="RSS"),Ruler!H$6,IF(AND(All!$V13="P2",All!$AE13="RSS"),Ruler!H$23,IF(AND(All!$V13="P3",All!$AE13="RSS"),Ruler!H$24,IF(AND(All!$V13="P4",All!$AE13="RSS"),Ruler!H$25,IF(AND(All!$V13="P5",All!$AE13="RSS"),Ruler!H$26,IF(AND(All!$V13="P6",All!$AE13="RSS"),Ruler!H$27,IF(AND(All!$V13="P7",All!$AE13="RSS"),Ruler!H$28,IF(AND(All!$V13="P8",All!$AE13="RSS"),Ruler!H$29,IF(AND(All!$V13="P9",All!$AE13="RSS"),Ruler!H$30,0))))))))))))))))))))))))))) -> 3 | BP13: =IF(AND(All!$V13="P1",All!$AE13="RDP"),Ruler!I$6,IF(AND(All!$V13="P2",All!$AE13="RDP"),Ruler!I$7,IF(AND(All!$V13="P3",All!$AE13="RDP"),Ruler!I$8,IF(AND(All!$V13="P4",All!$AE13="RDP"),Ruler!I$9,IF(AND(All!$V13="P5",All!$AE13="RDP"),Ruler!I$10,IF(AND(All!$V13="P6",All!$AE13="RDP"),Ruler!I$11,IF(AND(All!$V13="P7",All!$AE13="RDP"),Ruler!I$12,IF(AND(All!$V13="P8",All!$AE13="RDP"),Ruler!I$13,IF(AND(All!$V13="P9",All!$AE13="RDP"),Ruler!I$14,IF(AND(All!$V13="P1",All!$AE13="RMS"),Ruler!I$6,IF(AND(All!$V13="P2",All!$AE13="RMS"),Ruler!I$15,IF(AND(All!$V13="P3",All!$AE13="RMS"),Ruler!I$16,IF(AND(All!$V13="P4",All!$AE13="RMS"),Ruler!I$17,IF(AND(All!$V13="P5",All!$AE13="RMS"),Ruler!I$18,IF(AND(All!$V13="P6",All!$AE13="RMS"),Ruler!I$19,IF(AND(All!$V13="P7",All!$AE13="RMS"),Ruler!I$20,IF(AND(All!$V13="P8",All!$AE13="RMS"),Ruler!I$21,IF(AND(All!$V13="P9",All!$AE13="RMS"),Ruler!I$22,IF(AND(All!$V13="P1",All!$AE13="RSS"),Ruler!I$6,IF(AND(All!$V13="P2",All!$AE13="RSS"),Ruler!I$23,IF(AND(All!$V13="P3",All!$AE13="RSS"),Ruler!I$24,IF(AND(All!$V13="P4",All!$AE13="RSS"),Ruler!I$25,IF(AND(All!$V13="P5",All!$AE13="RSS"),Ruler!I$26,IF(AND(All!$V13="P6",All!$AE13="RSS"),Ruler!I$27,IF(AND(All!$V13="P7",All!$AE13="RSS"),Ruler!I$28,IF(AND(All!$V13="P8",All!$AE13="RSS"),Ruler!I$29,IF(AND(All!$V13="P9",All!$AE13="RSS"),Ruler!I$30,0))))))))))))))))))))))))))) -> 3 | BQ13: =IF(AND(All!$V13="P1",All!$AE13="RDP"),Ruler!J$6,IF(AND(All!$V13="P2",All!$AE13="RDP"),Ruler!J$7,IF(AND(All!$V13="P3",All!$AE13="RDP"),Ruler!J$8,IF(AND(All!$V13="P4",All!$AE13="RDP"),Ruler!J$9,IF(AND(All!$V13="P5",All!$AE13="RDP"),Ruler!J$10,IF(AND(All!$V13="P6",All!$AE13="RDP"),Ruler!J$11,IF(AND(All!$V13="P7",All!$AE13="RDP"),Ruler!J$12,IF(AND(All!$V13="P8",All!$AE13="RDP"),Ruler!J$13,IF(AND(All!$V13="P9",All!$AE13="RDP"),Ruler!J$14,IF(AND(All!$V13="P1",All!$AE13="RMS"),Ruler!J$6,IF(AND(All!$V13="P2",All!$AE13="RMS"),Ruler!J$15,IF(AND(All!$V13="P3",All!$AE13="RMS"),Ruler!J$16,IF(AND(All!$V13="P4",All!$AE13="RMS"),Ruler!J$17,IF(AND(All!$V13="P5",All!$AE13="RMS"),Ruler!J$18,IF(AND(All!$V13="P6",All!$AE13="RMS"),Ruler!J$19,IF(AND(All!$V13="P7",All!$AE13="RMS"),Ruler!J$20,IF(AND(All!$V13="P8",All!$AE13="RMS"),Ruler!J$21,IF(AND(All!$V13="P9",All!$AE13="RMS"),Ruler!J$22,IF(AND(All!$V13="P1",All!$AE13="RSS"),Ruler!J$6,IF(AND(All!$V13="P2",All!$AE13="RSS"),Ruler!J$23,IF(AND(All!$V13="P3",All!$AE13="RSS"),Ruler!J$24,IF(AND(All!$V13="P4",All!$AE13="RSS"),Ruler!J$25,IF(AND(All!$V13="P5",All!$AE13="RSS"),Ruler!J$26,IF(AND(All!$V13="P6",All!$AE13="RSS"),Ruler!J$27,IF(AND(All!$V13="P7",All!$AE13="RSS"),Ruler!J$28,IF(AND(All!$V13="P8",All!$AE13="RSS"),Ruler!J$29,IF(AND(All!$V13="P9",All!$AE13="RSS"),Ruler!J$30,0))))))))))))))))))))))))))) -> 2 | BR13: =IF(AND(All!$V13="P1",All!$AE13="RDP"),Ruler!K$6,IF(AND(All!$V13="P2",All!$AE13="RDP"),Ruler!K$7,IF(AND(All!$V13="P3",All!$AE13="RDP"),Ruler!K$8,IF(AND(All!$V13="P4",All!$AE13="RDP"),Ruler!K$9,IF(AND(All!$V13="P5",All!$AE13="RDP"),Ruler!K$10,IF(AND(All!$V13="P6",All!$AE13="RDP"),Ruler!K$11,IF(AND(All!$V13="P7",All!$AE13="RDP"),Ruler!K$12,IF(AND(All!$V13="P8",All!$AE13="RDP"),Ruler!K$13,IF(AND(All!$V13="P9",All!$AE13="RDP"),Ruler!K$14,IF(AND(All!$V13="P1",All!$AE13="RMS"),Ruler!K$6,IF(AND(All!$V13="P2",All!$AE13="RMS"),Ruler!K$15,IF(AND(All!$V13="P3",All!$AE13="RMS"),Ruler!K$16,IF(AND(All!$V13="P4",All!$AE13="RMS"),Ruler!K$17,IF(AND(All!$V13="P5",All!$AE13="RMS"),Ruler!K$18,IF(AND(All!$V13="P6",All!$AE13="RMS"),Ruler!K$19,IF(AND(All!$V13="P7",All!$AE13="RMS"),Ruler!K$20,IF(AND(All!$V13="P8",All!$AE13="RMS"),Ruler!K$21,IF(AND(All!$V13="P9",All!$AE13="RMS"),Ruler!K$22,IF(AND(All!$V13="P1",All!$AE13="RSS"),Ruler!K$6,IF(AND(All!$V13="P2",All!$AE13="RSS"),Ruler!K$23,IF(AND(All!$V13="P3",All!$AE13="RSS"),Ruler!K$24,IF(AND(All!$V13="P4",All!$AE13="RSS"),Ruler!K$25,IF(AND(All!$V13="P5",All!$AE13="RSS"),Ruler!K$26,IF(AND(All!$V13="P6",All!$AE13="RSS"),Ruler!K$27,IF(AND(All!$V13="P7",All!$AE13="RSS"),Ruler!K$28,IF(AND(All!$V13="P8",All!$AE13="RSS"),Ruler!K$29,IF(AND(All!$V13="P9",All!$AE13="RSS"),Ruler!K$30,0))))))))))))))))))))))))))) -> 3 | BS13: =IF(AND(All!$V13="P1",All!$AE13="RDP"),Ruler!L$6,IF(AND(All!$V13="P2",All!$AE13="RDP"),Ruler!L$7,IF(AND(All!$V13="P3",All!$AE13="RDP"),Ruler!L$8,IF(AND(All!$V13="P4",All!$AE13="RDP"),Ruler!L$9,IF(AND(All!$V13="P5",All!$AE13="RDP"),Ruler!L$10,IF(AND(All!$V13="P6",All!$AE13="RDP"),Ruler!L$11,IF(AND(All!$V13="P7",All!$AE13="RDP"),Ruler!L$12,IF(AND(All!$V13="P8",All!$AE13="RDP"),Ruler!L$13,IF(AND(All!$V13="P9",All!$AE13="RDP"),Ruler!L$14,IF(AND(All!$V13="P1",All!$AE13="RMS"),Ruler!L$6,IF(AND(All!$V13="P2",All!$AE13="RMS"),Ruler!L$15,IF(AND(All!$V13="P3",All!$AE13="RMS"),Ruler!L$16,IF(AND(All!$V13="P4",All!$AE13="RMS"),Ruler!L$17,IF(AND(All!$V13="P5",All!$AE13="RMS"),Ruler!L$18,IF(AND(All!$V13="P6",All!$AE13="RMS"),Ruler!L$19,IF(AND(All!$V13="P7",All!$AE13="RMS"),Ruler!L$20,IF(AND(All!$V13="P8",All!$AE13="RMS"),Ruler!L$21,IF(AND(All!$V13="P9",All!$AE13="RMS"),Ruler!L$22,IF(AND(All!$V13="P1",All!$AE13="RSS"),Ruler!L$6,IF(AND(All!$V13="P2",All!$AE13="RSS"),Ruler!L$23,IF(AND(All!$V13="P3",All!$AE13="RSS"),Ruler!L$24,IF(AND(All!$V13="P4",All!$AE13="RSS"),Ruler!L$25,IF(AND(All!$V13="P5",All!$AE13="RSS"),Ruler!L$26,IF(AND(All!$V13="P6",All!$AE13="RSS"),Ruler!L$27,IF(AND(All!$V13="P7",All!$AE13="RSS"),Ruler!L$28,IF(AND(All!$V13="P8",All!$AE13="RSS"),Ruler!L$29,IF(AND(All!$V13="P9",All!$AE13="RSS"),Ruler!L$30,0))))))))))))))))))))))))))) -> 3 | ... CI13: =IF(AND(All!$V13="P1",All!$AE13="RDP"),Ruler!AB$6,IF(AND(All!$V13="P2",All!$AE13="RDP"),Ruler!AB$7,IF(AND(All!$V13="P3",All!$AE13="RDP"),Ruler!AB$8,IF(AND(All!$V13="P4",All!$AE13="RDP"),Ruler!AB$9,IF(AND(All!$V13="P5",All!$AE13="RDP"),Ruler!AB$10,IF(AND(All!$V13="P6",All!$AE13="RDP"),Ruler!AB$11,IF(AND(All!$V13="P7",All!$AE13="RDP"),Ruler!AB$12,IF(AND(All!$V13="P8",All!$AE13="RDP"),Ruler!AB$13,IF(AND(All!$V13="P9",All!$AE13="RDP"),Ruler!AB$14,IF(AND(All!$V13="P1",All!$AE13="RMS"),Ruler!AB$6,IF(AND(All!$V13="P2",All!$AE13="RMS"),Ruler!AB$15,IF(AND(All!$V13="P3",All!$AE13="RMS"),Ruler!AB$16,IF(AND(All!$V13="P4",All!$AE13="RMS"),Ruler!AB$17,IF(AND(All!$V13="P5",All!$AE13="RMS"),Ruler!AB$18,IF(AND(All!$V13="P6",All!$AE13="RMS"),Ruler!AB$19,IF(AND(All!$V13="P7",All!$AE13="RMS"),Ruler!AB$20,IF(AND(All!$V13="P8",All!$AE13="RMS"),Ruler!AB$21,IF(AND(All!$V13="P9",All!$AE13="RMS"),Ruler!AB$22,IF(AND(All!$V13="P1",All!$AE13="RSS"),Ruler!AB$6,IF(AND(All!$V13="P2",All!$AE13="RSS"),Ruler!AB$23,IF(AND(All!$V13="P3",All!$AE13="RSS"),Ruler!AB$24,IF(AND(All!$V13="P4",All!$AE13="RSS"),Ruler!AB$25,IF(AND(All!$V13="P5",All!$AE13="RSS"),Ruler!AB$26,IF(AND(All!$V13="P6",All!$AE13="RSS"),Ruler!AB$27,IF(AND(All!$V13="P7",All!$AE13="RSS"),Ruler!AB$28,IF(AND(All!$V13="P8",All!$AE13="RSS"),Ruler!AB$29,IF(AND(All!$V13="P9",All!$AE13="RSS"),Ruler!AB$30,0))))))))))))))))))))))))))) -> 1 | CJ13: =Table9[[#This Row],[R-B1]]-Table9[[#This Row],[B1]] -> 0 | CK13: =Table9[[#This Row],[R-B2]]-Table9[[#This Row],[B2]] -> 1 | CL13: =Table9[[#This Row],[R-B3]]-Table9[[#This Row],[B3]] -> 1 | CM13: =Table9[[#This Row],[R-B4]]-Table9[[#This Row],[B4]] -> 0 | CN13: =Table9[[#This Row],[R-B5]]-Table9[[#This Row],[B5]] -> 0 | CO13: =Table9[[#This Row],[R-B6]]-Table9[[#This Row],[B6]] -> -1 | CP13: =Table9[[#This Row],[R-B7]]-Table9[[#This Row],[B7]] -> 0 | CQ13: =Table9[[#This Row],[R-B8]]-Table9[[#This Row],[B8]] -> 1 | CR13: =Table9[[#This Row],[R-B9]]-Table9[[#This Row],[B9]] -> 0 | CS13: =Table9[[#This Row],[R-B10]]-Table9[[#This Row],[B10]] -> 0 | CT13: =Table9[[#This Row],[R-B11]]-Table9[[#This Row],[B11]] -> 0 | CU13: =Table9[[#This Row],[R-B12]]-Table9[[#This Row],[B12]] -> 1 | CV13: =Table9[[#This Row],[R-K1]]-Table9[[#This Row],[K1]] -> 0 | CW13: =Table9[[#This Row],[R-K2]]-Table9[[#This Row],[K2]] -> 0 | CX13: =Table9[[#This Row],[R-K3]]-Table9[[#This Row],[K3]] -> 0 | CY13: =Table9[[#This Row],[R-K4]]-Table9[[#This Row],[K4]] -> 1 | CZ13: =Table9[[#This Row],[R-K5]]-Table9[[#This Row],[K5]] -> 1 | DA13: =Table9[[#This Row],[R-P1]]-Table9[[#This Row],[P1]] -> 0 | DB13: =Table9[[#This Row],[R-P2]]-Table9[[#This Row],[P2]] -> 0 | DC13: =Table9[[#This Row],[R-P3]]-Table9[[#This Row],[P3]] -> 0 | DD13: =Table9[[#This Row],[R-P4]]-Table9[[#This Row],[P4]] -> 0 | DE13: =Table9[[#This Row],[R-P5]]-Table9[[#This Row],[P5]] -> 0 | DF13: =Table9[[#This Row],[R-E1]]-Table9[[#This Row],[E1]] -> -1 | DG13: =Table9[[#This Row],[R-E2]]-Table9[[#This Row],[E2]] -> 0 | DH13: =COUNTIF(Table9[[#This Row],[G-B1]:[G-B12]],"<=0")/12*100 -> 66.666667 | DI13: =COUNTIF(Table9[[#This Row],[G-K1]:[G-K5]],"<=0")/5*100 -> 60 | DJ13: =COUNTIF(Table9[[#This Row],[G-P1]:[G-P5]],"<=0")/5*100 -> 100 | DK13: =COUNTIF(Table9[[#This Row],[G-E1]:[G-E2]],"<=0")/2*100 -> 100 | DL13: =IF(AE13="RDP",(COUNTIF(Table9[[#This Row],[G-B3]],"<=0")+COUNTIF(Table9[[#This Row],[G-B4]],"<=0")+COUNTIF(Table9[[#This Row],[G-B7]],"<=0")+COUNTIF(Table9[[#This Row],[G-B11]],"<=0")+COUNTIF(Table9[[#This Row],[G-K2]],"<=0"))/5*100,IF(AE13="RMS",(COUNTIF(Table9[[#This Row],[G-B4]],"<=0")+COUNTIF(Table9[[#This Row],[G-B5]],"<=0")+COUNTIF(Table9[[#This Row],[G-B10]],"<=0")+COUNTIF(Table9[[#This Row],[G-B12]],"<=0")+COUNTIF(Table9[[#This Row],[G-K2]],"<=0"))/5*100,IF(AE13="RSS",(COUNTIF(Table9[[#This Row],[G-B1]],"<=0")+COUNTIF(Table9[[#This Row],[G-B2]],"<=0")+COUNTIF(Table9[[#This Row],[G-B6]],"<=0")+COUNTIF(Table9[[#This Row],[G-B11]],"<=0")+COUNTIF(Table9[[#This Row],[G-B12]],"<=0"))/5*100,0))) -> 80 | DM13: 91 | DN13: 83 | DO13: 100 | DP13: 100 | DQ13: 100 | DR13: 27 | DS13: 20 | DT13: 60 | DU13: 0 | DV13: 0 | DW13: 27 | DX13: 20 | DY13: 20 | DZ13: 0 | EA13: 0 | EB13: Chander Shekhar | EC13: Rakesh Ranjan | ED13: Nurlizawati Latif | EE13: Score based on remapping
B14: 11 | C14: Yes | D14: 46216 | E14: Ahmad Nabil Bin Ahmad Subandi | F14: 1125489 | G14: =($T$1-H14)/365 -> 28.146938 | H14: 36042 | I14: M | J14: Malaysia | K14: Searah | L14: PMA | M14: GPSC | N14: Guntong | O14: Executive | P14: ahmadnabil.ahmadsub@petronas.com.my | Q14: Permanent | R14: N/A | S14: 45717 | T14: =YEARFRAC(S14,$T$1) -> 1.6361111 | V14: P2 | X14: =($T$1-Table9[[#This Row],[Date of Appointment to Current Grade]])/365 -> 0.30584183 | Y14: 46204 | Z14: Searah-PM | AA14: 45717 | AB14: =($T$1-Table9[[#This Row],[Date in Position]])/365 -> 1.6400884 | AC14: Ongoing | AF14: Good | AG14: UTM graduate. Internship/joined with MiS Energy PE, acidization., sand mgt. ESP design subsurface support. Data analyst/phyton. Exxon (2023-25) - RE - prod. Engineer for Palas, RE for Guntong. PCSB/Searah (25-now). | AH14: ✅ Scripting ✅ Analytical/Classical RE ✅ SE | AI14: Get familir with PCSB TI&R. Self assessment to gauge | AK14: Scripting/phyton. To be become Relaible end-to-end RE. Opportuity to be part of study/FDP team. | AL14: TP | AM14: How to access to other field experience. Approach to improve skill and competencies. | BL14: =IF(AND(All!$V14="P1",All!$AE14="RDP"),Ruler!E$6,IF(AND(All!$V14="P2",All!$AE14="RDP"),Ruler!E$7,IF(AND(All!$V14="P3",All!$AE14="RDP"),Ruler!E$8,IF(AND(All!$V14="P4",All!$AE14="RDP"),Ruler!E$9,IF(AND(All!$V14="P5",All!$AE14="RDP"),Ruler!E$10,IF(AND(All!$V14="P6",All!$AE14="RDP"),Ruler!E$11,IF(AND(All!$V14="P7",All!$AE14="RDP"),Ruler!E$12,IF(AND(All!$V14="P8",All!$AE14="RDP"),Ruler!E$13,IF(AND(All!$V14="P9",All!$AE14="RDP"),Ruler!E$14,IF(AND(All!$V14="P1",All!$AE14="RMS"),Ruler!E$6,IF(AND(All!$V14="P2",All!$AE14="RMS"),Ruler!E$15,IF(AND(All!$V14="P3",All!$AE14="RMS"),Ruler!E$16,IF(AND(All!$V14="P4",All!$AE14="RMS"),Ruler!E$17,IF(AND(All!$V14="P5",All!$AE14="RMS"),Ruler!E$18,IF(AND(All!$V14="P6",All!$AE14="RMS"),Ruler!E$19,IF(AND(All!$V14="P7",All!$AE14="RMS"),Ruler!E$20,IF(AND(All!$V14="P8",All!$AE14="RMS"),Ruler!E$21,IF(AND(All!$V14="P9",All!$AE14="RMS"),Ruler!E$22,IF(AND(All!$V14="P1",All!$AE14="RSS"),Ruler!E$6,IF(AND(All!$V14="P2",All!$AE14="RSS"),Ruler!E$23,IF(AND(All!$V14="P3",All!$AE14="RSS"),Ruler!E$24,IF(AND(All!$V14="P4",All!$AE14="RSS"),Ruler!E$25,IF(AND(All!$V14="P5",All!$AE14="RSS"),Ruler!E$26,IF(AND(All!$V14="P6",All!$AE14="RSS"),Ruler!E$27,IF(AND(All!$V14="P7",All!$AE14="RSS"),Ruler!E$28,IF(AND(All!$V14="P8",All!$AE14="RSS"),Ruler!E$29,IF(AND(All!$V14="P9",All!$AE14="RSS"),Ruler!E$30,0))))))))))))))))))))))))))) -> 0 | BM14: =IF(AND(All!$V14="P1",All!$AE14="RDP"),Ruler!F$6,IF(AND(All!$V14="P2",All!$AE14="RDP"),Ruler!F$7,IF(AND(All!$V14="P3",All!$AE14="RDP"),Ruler!F$8,IF(AND(All!$V14="P4",All!$AE14="RDP"),Ruler!F$9,IF(AND(All!$V14="P5",All!$AE14="RDP"),Ruler!F$10,IF(AND(All!$V14="P6",All!$AE14="RDP"),Ruler!F$11,IF(AND(All!$V14="P7",All!$AE14="RDP"),Ruler!F$12,IF(AND(All!$V14="P8",All!$AE14="RDP"),Ruler!F$13,IF(AND(All!$V14="P9",All!$AE14="RDP"),Ruler!F$14,IF(AND(All!$V14="P1",All!$AE14="RMS"),Ruler!F$6,IF(AND(All!$V14="P2",All!$AE14="RMS"),Ruler!F$15,IF(AND(All!$V14="P3",All!$AE14="RMS"),Ruler!F$16,IF(AND(All!$V14="P4",All!$AE14="RMS"),Ruler!F$17,IF(AND(All!$V14="P5",All!$AE14="RMS"),Ruler!F$18,IF(AND(All!$V14="P6",All!$AE14="RMS"),Ruler!F$19,IF(AND(All!$V14="P7",All!$AE14="RMS"),Ruler!F$20,IF(AND(All!$V14="P8",All!$AE14="RMS"),Ruler!F$21,IF(AND(All!$V14="P9",All!$AE14="RMS"),Ruler!F$22,IF(AND(All!$V14="P1",All!$AE14="RSS"),Ruler!F$6,IF(AND(All!$V14="P2",All!$AE14="RSS"),Ruler!F$23,IF(AND(All!$V14="P3",All!$AE14="RSS"),Ruler!F$24,IF(AND(All!$V14="P4",All!$AE14="RSS"),Ruler!F$25,IF(AND(All!$V14="P5",All!$AE14="RSS"),Ruler!F$26,IF(AND(All!$V14="P6",All!$AE14="RSS"),Ruler!F$27,IF(AND(All!$V14="P7",All!$AE14="RSS"),Ruler!F$28,IF(AND(All!$V14="P8",All!$AE14="RSS"),Ruler!F$29,IF(AND(All!$V14="P9",All!$AE14="RSS"),Ruler!F$30,0))))))))))))))))))))))))))) -> 0 | BN14: =IF(AND(All!$V14="P1",All!$AE14="RDP"),Ruler!G$6,IF(AND(All!$V14="P2",All!$AE14="RDP"),Ruler!G$7,IF(AND(All!$V14="P3",All!$AE14="RDP"),Ruler!G$8,IF(AND(All!$V14="P4",All!$AE14="RDP"),Ruler!G$9,IF(AND(All!$V14="P5",All!$AE14="RDP"),Ruler!G$10,IF(AND(All!$V14="P6",All!$AE14="RDP"),Ruler!G$11,IF(AND(All!$V14="P7",All!$AE14="RDP"),Ruler!G$12,IF(AND(All!$V14="P8",All!$AE14="RDP"),Ruler!G$13,IF(AND(All!$V14="P9",All!$AE14="RDP"),Ruler!G$14,IF(AND(All!$V14="P1",All!$AE14="RMS"),Ruler!G$6,IF(AND(All!$V14="P2",All!$AE14="RMS"),Ruler!G$15,IF(AND(All!$V14="P3",All!$AE14="RMS"),Ruler!G$16,IF(AND(All!$V14="P4",All!$AE14="RMS"),Ruler!G$17,IF(AND(All!$V14="P5",All!$AE14="RMS"),Ruler!G$18,IF(AND(All!$V14="P6",All!$AE14="RMS"),Ruler!G$19,IF(AND(All!$V14="P7",All!$AE14="RMS"),Ruler!G$20,IF(AND(All!$V14="P8",All!$AE14="RMS"),Ruler!G$21,IF(AND(All!$V14="P9",All!$AE14="RMS"),Ruler!G$22,IF(AND(All!$V14="P1",All!$AE14="RSS"),Ruler!G$6,IF(AND(All!$V14="P2",All!$AE14="RSS"),Ruler!G$23,IF(AND(All!$V14="P3",All!$AE14="RSS"),Ruler!G$24,IF(AND(All!$V14="P4",All!$AE14="RSS"),Ruler!G$25,IF(AND(All!$V14="P5",All!$AE14="RSS"),Ruler!G$26,IF(AND(All!$V14="P6",All!$AE14="RSS"),Ruler!G$27,IF(AND(All!$V14="P7",All!$AE14="RSS"),Ruler!G$28,IF(AND(All!$V14="P8",All!$AE14="RSS"),Ruler!G$29,IF(AND(All!$V14="P9",All!$AE14="RSS"),Ruler!G$30,0))))))))))))))))))))))))))) -> 0 | BO14: =IF(AND(All!$V14="P1",All!$AE14="RDP"),Ruler!H$6,IF(AND(All!$V14="P2",All!$AE14="RDP"),Ruler!H$7,IF(AND(All!$V14="P3",All!$AE14="RDP"),Ruler!H$8,IF(AND(All!$V14="P4",All!$AE14="RDP"),Ruler!H$9,IF(AND(All!$V14="P5",All!$AE14="RDP"),Ruler!H$10,IF(AND(All!$V14="P6",All!$AE14="RDP"),Ruler!H$11,IF(AND(All!$V14="P7",All!$AE14="RDP"),Ruler!H$12,IF(AND(All!$V14="P8",All!$AE14="RDP"),Ruler!H$13,IF(AND(All!$V14="P9",All!$AE14="RDP"),Ruler!H$14,IF(AND(All!$V14="P1",All!$AE14="RMS"),Ruler!H$6,IF(AND(All!$V14="P2",All!$AE14="RMS"),Ruler!H$15,IF(AND(All!$V14="P3",All!$AE14="RMS"),Ruler!H$16,IF(AND(All!$V14="P4",All!$AE14="RMS"),Ruler!H$17,IF(AND(All!$V14="P5",All!$AE14="RMS"),Ruler!H$18,IF(AND(All!$V14="P6",All!$AE14="RMS"),Ruler!H$19,IF(AND(All!$V14="P7",All!$AE14="RMS"),Ruler!H$20,IF(AND(All!$V14="P8",All!$AE14="RMS"),Ruler!H$21,IF(AND(All!$V14="P9",All!$AE14="RMS"),Ruler!H$22,IF(AND(All!$V14="P1",All!$AE14="RSS"),Ruler!H$6,IF(AND(All!$V14="P2",All!$AE14="RSS"),Ruler!H$23,IF(AND(All!$V14="P3",All!$AE14="RSS"),Ruler!H$24,IF(AND(All!$V14="P4",All!$AE14="RSS"),Ruler!H$25,IF(AND(All!$V14="P5",All!$AE14="RSS"),Ruler!H$26,IF(AND(All!$V14="P6",All!$AE14="RSS"),Ruler!H$27,IF(AND(All!$V14="P7",All!$AE14="RSS"),Ruler!H$28,IF(AND(All!$V14="P8",All!$AE14="RSS"),Ruler!H$29,IF(AND(All!$V14="P9",All!$AE14="RSS"),Ruler!H$30,0))))))))))))))))))))))))))) -> 0 | BP14: =IF(AND(All!$V14="P1",All!$AE14="RDP"),Ruler!I$6,IF(AND(All!$V14="P2",All!$AE14="RDP"),Ruler!I$7,IF(AND(All!$V14="P3",All!$AE14="RDP"),Ruler!I$8,IF(AND(All!$V14="P4",All!$AE14="RDP"),Ruler!I$9,IF(AND(All!$V14="P5",All!$AE14="RDP"),Ruler!I$10,IF(AND(All!$V14="P6",All!$AE14="RDP"),Ruler!I$11,IF(AND(All!$V14="P7",All!$AE14="RDP"),Ruler!I$12,IF(AND(All!$V14="P8",All!$AE14="RDP"),Ruler!I$13,IF(AND(All!$V14="P9",All!$AE14="RDP"),Ruler!I$14,IF(AND(All!$V14="P1",All!$AE14="RMS"),Ruler!I$6,IF(AND(All!$V14="P2",All!$AE14="RMS"),Ruler!I$15,IF(AND(All!$V14="P3",All!$AE14="RMS"),Ruler!I$16,IF(AND(All!$V14="P4",All!$AE14="RMS"),Ruler!I$17,IF(AND(All!$V14="P5",All!$AE14="RMS"),Ruler!I$18,IF(AND(All!$V14="P6",All!$AE14="RMS"),Ruler!I$19,IF(AND(All!$V14="P7",All!$AE14="RMS"),Ruler!I$20,IF(AND(All!$V14="P8",All!$AE14="RMS"),Ruler!I$21,IF(AND(All!$V14="P9",All!$AE14="RMS"),Ruler!I$22,IF(AND(All!$V14="P1",All!$AE14="RSS"),Ruler!I$6,IF(AND(All!$V14="P2",All!$AE14="RSS"),Ruler!I$23,IF(AND(All!$V14="P3",All!$AE14="RSS"),Ruler!I$24,IF(AND(All!$V14="P4",All!$AE14="RSS"),Ruler!I$25,IF(AND(All!$V14="P5",All!$AE14="RSS"),Ruler!I$26,IF(AND(All!$V14="P6",All!$AE14="RSS"),Ruler!I$27,IF(AND(All!$V14="P7",All!$AE14="RSS"),Ruler!I$28,IF(AND(All!$V14="P8",All!$AE14="RSS"),Ruler!I$29,IF(AND(All!$V14="P9",All!$AE14="RSS"),Ruler!I$30,0))))))))))))))))))))))))))) -> 0 | BQ14: =IF(AND(All!$V14="P1",All!$AE14="RDP"),Ruler!J$6,IF(AND(All!$V14="P2",All!$AE14="RDP"),Ruler!J$7,IF(AND(All!$V14="P3",All!$AE14="RDP"),Ruler!J$8,IF(AND(All!$V14="P4",All!$AE14="RDP"),Ruler!J$9,IF(AND(All!$V14="P5",All!$AE14="RDP"),Ruler!J$10,IF(AND(All!$V14="P6",All!$AE14="RDP"),Ruler!J$11,IF(AND(All!$V14="P7",All!$AE14="RDP"),Ruler!J$12,IF(AND(All!$V14="P8",All!$AE14="RDP"),Ruler!J$13,IF(AND(All!$V14="P9",All!$AE14="RDP"),Ruler!J$14,IF(AND(All!$V14="P1",All!$AE14="RMS"),Ruler!J$6,IF(AND(All!$V14="P2",All!$AE14="RMS"),Ruler!J$15,IF(AND(All!$V14="P3",All!$AE14="RMS"),Ruler!J$16,IF(AND(All!$V14="P4",All!$AE14="RMS"),Ruler!J$17,IF(AND(All!$V14="P5",All!$AE14="RMS"),Ruler!J$18,IF(AND(All!$V14="P6",All!$AE14="RMS"),Ruler!J$19,IF(AND(All!$V14="P7",All!$AE14="RMS"),Ruler!J$20,IF(AND(All!$V14="P8",All!$AE14="RMS"),Ruler!J$21,IF(AND(All!$V14="P9",All!$AE14="RMS"),Ruler!J$22,IF(AND(All!$V14="P1",All!$AE14="RSS"),Ruler!J$6,IF(AND(All!$V14="P2",All!$AE14="RSS"),Ruler!J$23,IF(AND(All!$V14="P3",All!$AE14="RSS"),Ruler!J$24,IF(AND(All!$V14="P4",All!$AE14="RSS"),Ruler!J$25,IF(AND(All!$V14="P5",All!$AE14="RSS"),Ruler!J$26,IF(AND(All!$V14="P6",All!$AE14="RSS"),Ruler!J$27,IF(AND(All!$V14="P7",All!$AE14="RSS"),Ruler!J$28,IF(AND(All!$V14="P8",All!$AE14="RSS"),Ruler!J$29,IF(AND(All!$V14="P9",All!$AE14="RSS"),Ruler!J$30,0))))))))))))))))))))))))))) -> 0 | BR14: =IF(AND(All!$V14="P1",All!$AE14="RDP"),Ruler!K$6,IF(AND(All!$V14="P2",All!$AE14="RDP"),Ruler!K$7,IF(AND(All!$V14="P3",All!$AE14="RDP"),Ruler!K$8,IF(AND(All!$V14="P4",All!$AE14="RDP"),Ruler!K$9,IF(AND(All!$V14="P5",All!$AE14="RDP"),Ruler!K$10,IF(AND(All!$V14="P6",All!$AE14="RDP"),Ruler!K$11,IF(AND(All!$V14="P7",All!$AE14="RDP"),Ruler!K$12,IF(AND(All!$V14="P8",All!$AE14="RDP"),Ruler!K$13,IF(AND(All!$V14="P9",All!$AE14="RDP"),Ruler!K$14,IF(AND(All!$V14="P1",All!$AE14="RMS"),Ruler!K$6,IF(AND(All!$V14="P2",All!$AE14="RMS"),Ruler!K$15,IF(AND(All!$V14="P3",All!$AE14="RMS"),Ruler!K$16,IF(AND(All!$V14="P4",All!$AE14="RMS"),Ruler!K$17,IF(AND(All!$V14="P5",All!$AE14="RMS"),Ruler!K$18,IF(AND(All!$V14="P6",All!$AE14="RMS"),Ruler!K$19,IF(AND(All!$V14="P7",All!$AE14="RMS"),Ruler!K$20,IF(AND(All!$V14="P8",All!$AE14="RMS"),Ruler!K$21,IF(AND(All!$V14="P9",All!$AE14="RMS"),Ruler!K$22,IF(AND(All!$V14="P1",All!$AE14="RSS"),Ruler!K$6,IF(AND(All!$V14="P2",All!$AE14="RSS"),Ruler!K$23,IF(AND(All!$V14="P3",All!$AE14="RSS"),Ruler!K$24,IF(AND(All!$V14="P4",All!$AE14="RSS"),Ruler!K$25,IF(AND(All!$V14="P5",All!$AE14="RSS"),Ruler!K$26,IF(AND(All!$V14="P6",All!$AE14="RSS"),Ruler!K$27,IF(AND(All!$V14="P7",All!$AE14="RSS"),Ruler!K$28,IF(AND(All!$V14="P8",All!$AE14="RSS"),Ruler!K$29,IF(AND(All!$V14="P9",All!$AE14="RSS"),Ruler!K$30,0))))))))))))))))))))))))))) -> 0 | BS14: =IF(AND(All!$V14="P1",All!$AE14="RDP"),Ruler!L$6,IF(AND(All!$V14="P2",All!$AE14="RDP"),Ruler!L$7,IF(AND(All!$V14="P3",All!$AE14="RDP"),Ruler!L$8,IF(AND(All!$V14="P4",All!$AE14="RDP"),Ruler!L$9,IF(AND(All!$V14="P5",All!$AE14="RDP"),Ruler!L$10,IF(AND(All!$V14="P6",All!$AE14="RDP"),Ruler!L$11,IF(AND(All!$V14="P7",All!$AE14="RDP"),Ruler!L$12,IF(AND(All!$V14="P8",All!$AE14="RDP"),Ruler!L$13,IF(AND(All!$V14="P9",All!$AE14="RDP"),Ruler!L$14,IF(AND(All!$V14="P1",All!$AE14="RMS"),Ruler!L$6,IF(AND(All!$V14="P2",All!$AE14="RMS"),Ruler!L$15,IF(AND(All!$V14="P3",All!$AE14="RMS"),Ruler!L$16,IF(AND(All!$V14="P4",All!$AE14="RMS"),Ruler!L$17,IF(AND(All!$V14="P5",All!$AE14="RMS"),Ruler!L$18,IF(AND(All!$V14="P6",All!$AE14="RMS"),Ruler!L$19,IF(AND(All!$V14="P7",All!$AE14="RMS"),Ruler!L$20,IF(AND(All!$V14="P8",All!$AE14="RMS"),Ruler!L$21,IF(AND(All!$V14="P9",All!$AE14="RMS"),Ruler!L$22,IF(AND(All!$V14="P1",All!$AE14="RSS"),Ruler!L$6,IF(AND(All!$V14="P2",All!$AE14="RSS"),Ruler!L$23,IF(AND(All!$V14="P3",All!$AE14="RSS"),Ruler!L$24,IF(AND(All!$V14="P4",All!$AE14="RSS"),Ruler!L$25,IF(AND(All!$V14="P5",All!$AE14="RSS"),Ruler!L$26,IF(AND(All!$V14="P6",All!$AE14="RSS"),Ruler!L$27,IF(AND(All!$V14="P7",All!$AE14="RSS"),Ruler!L$28,IF(AND(All!$V14="P8",All!$AE14="RSS"),Ruler!L$29,IF(AND(All!$V14="P9",All!$AE14="RSS"),Ruler!L$30,0))))))))))))))))))))))))))) -> 0 | ... CI14: =IF(AND(All!$V14="P1",All!$AE14="RDP"),Ruler!AB$6,IF(AND(All!$V14="P2",All!$AE14="RDP"),Ruler!AB$7,IF(AND(All!$V14="P3",All!$AE14="RDP"),Ruler!AB$8,IF(AND(All!$V14="P4",All!$AE14="RDP"),Ruler!AB$9,IF(AND(All!$V14="P5",All!$AE14="RDP"),Ruler!AB$10,IF(AND(All!$V14="P6",All!$AE14="RDP"),Ruler!AB$11,IF(AND(All!$V14="P7",All!$AE14="RDP"),Ruler!AB$12,IF(AND(All!$V14="P8",All!$AE14="RDP"),Ruler!AB$13,IF(AND(All!$V14="P9",All!$AE14="RDP"),Ruler!AB$14,IF(AND(All!$V14="P1",All!$AE14="RMS"),Ruler!AB$6,IF(AND(All!$V14="P2",All!$AE14="RMS"),Ruler!AB$15,IF(AND(All!$V14="P3",All!$AE14="RMS"),Ruler!AB$16,IF(AND(All!$V14="P4",All!$AE14="RMS"),Ruler!AB$17,IF(AND(All!$V14="P5",All!$AE14="RMS"),Ruler!AB$18,IF(AND(All!$V14="P6",All!$AE14="RMS"),Ruler!AB$19,IF(AND(All!$V14="P7",All!$AE14="RMS"),Ruler!AB$20,IF(AND(All!$V14="P8",All!$AE14="RMS"),Ruler!AB$21,IF(AND(All!$V14="P9",All!$AE14="RMS"),Ruler!AB$22,IF(AND(All!$V14="P1",All!$AE14="RSS"),Ruler!AB$6,IF(AND(All!$V14="P2",All!$AE14="RSS"),Ruler!AB$23,IF(AND(All!$V14="P3",All!$AE14="RSS"),Ruler!AB$24,IF(AND(All!$V14="P4",All!$AE14="RSS"),Ruler!AB$25,IF(AND(All!$V14="P5",All!$AE14="RSS"),Ruler!AB$26,IF(AND(All!$V14="P6",All!$AE14="RSS"),Ruler!AB$27,IF(AND(All!$V14="P7",All!$AE14="RSS"),Ruler!AB$28,IF(AND(All!$V14="P8",All!$AE14="RSS"),Ruler!AB$29,IF(AND(All!$V14="P9",All!$AE14="RSS"),Ruler!AB$30,0))))))))))))))))))))))))))) -> 0 | CJ14: =Table9[[#This Row],[R-B1]]-Table9[[#This Row],[B1]] -> 0 | CK14: =Table9[[#This Row],[R-B2]]-Table9[[#This Row],[B2]] -> 0 | CL14: =Table9[[#This Row],[R-B3]]-Table9[[#This Row],[B3]] -> 0 | CM14: =Table9[[#This Row],[R-B4]]-Table9[[#This Row],[B4]] -> 0 | CN14: =Table9[[#This Row],[R-B5]]-Table9[[#This Row],[B5]] -> 0 | CO14: =Table9[[#This Row],[R-B6]]-Table9[[#This Row],[B6]] -> 0 | CP14: =Table9[[#This Row],[R-B7]]-Table9[[#This Row],[B7]] -> 0 | CQ14: =Table9[[#This Row],[R-B8]]-Table9[[#This Row],[B8]] -> 0 | CR14: =Table9[[#This Row],[R-B9]]-Table9[[#This Row],[B9]] -> 0 | CS14: =Table9[[#This Row],[R-B10]]-Table9[[#This Row],[B10]] -> 0 | CT14: =Table9[[#This Row],[R-B11]]-Table9[[#This Row],[B11]] -> 0 | CU14: =Table9[[#This Row],[R-B12]]-Table9[[#This Row],[B12]] -> 0 | CV14: =Table9[[#This Row],[R-K1]]-Table9[[#This Row],[K1]] -> 0 | CW14: =Table9[[#This Row],[R-K2]]-Table9[[#This Row],[K2]] -> 0 | CX14: =Table9[[#This Row],[R-K3]]-Table9[[#This Row],[K3]] -> 0 | CY14: =Table9[[#This Row],[R-K4]]-Table9[[#This Row],[K4]] -> 0 | CZ14: =Table9[[#This Row],[R-K5]]-Table9[[#This Row],[K5]] -> 0 | DA14: =Table9[[#This Row],[R-P1]]-Table9[[#This Row],[P1]] -> 0 | DB14: =Table9[[#This Row],[R-P2]]-Table9[[#This Row],[P2]] -> 0 | DC14: =Table9[[#This Row],[R-P3]]-Table9[[#This Row],[P3]] -> 0 | DD14: =Table9[[#This Row],[R-P4]]-Table9[[#This Row],[P4]] -> 0 | DE14: =Table9[[#This Row],[R-P5]]-Table9[[#This Row],[P5]] -> 0 | DF14: =Table9[[#This Row],[R-E1]]-Table9[[#This Row],[E1]] -> 0 | DG14: =Table9[[#This Row],[R-E2]]-Table9[[#This Row],[E2]] -> 0 | DH14: =COUNTIF(Table9[[#This Row],[G-B1]:[G-B12]],"<=0")/12*100 -> 100 | DI14: =COUNTIF(Table9[[#This Row],[G-K1]:[G-K5]],"<=0")/5*100 -> 100 | DJ14: =COUNTIF(Table9[[#This Row],[G-P1]:[G-P5]],"<=0")/5*100 -> 100 | DK14: =COUNTIF(Table9[[#This Row],[G-E1]:[G-E2]],"<=0")/2*100 -> 100 | DL14: =IF(AE14="RDP",(COUNTIF(Table9[[#This Row],[G-B3]],"<=0")+COUNTIF(Table9[[#This Row],[G-B4]],"<=0")+COUNTIF(Table9[[#This Row],[G-B7]],"<=0")+COUNTIF(Table9[[#This Row],[G-B11]],"<=0")+COUNTIF(Table9[[#This Row],[G-K2]],"<=0"))/5*100,IF(AE14="RMS",(COUNTIF(Table9[[#This Row],[G-B4]],"<=0")+COUNTIF(Table9[[#This Row],[G-B5]],"<=0")+COUNTIF(Table9[[#This Row],[G-B10]],"<=0")+COUNTIF(Table9[[#This Row],[G-B12]],"<=0")+COUNTIF(Table9[[#This Row],[G-K2]],"<=0"))/5*100,IF(AE14="RSS",(COUNTIF(Table9[[#This Row],[G-B1]],"<=0")+COUNTIF(Table9[[#This Row],[G-B2]],"<=0")+COUNTIF(Table9[[#This Row],[G-B6]],"<=0")+COUNTIF(Table9[[#This Row],[G-B11]],"<=0")+COUNTIF(Table9[[#This Row],[G-B12]],"<=0"))/5*100,0))) -> 0
B15: 12 | C15: Yes | D15: 46091 | E15: Ahmad Zikri bin Nor Azlan | F15: 125545 | G15: =($T$1-H15)/365 -> 38.829129 | H15: 32143 | I15: M | J15: Malaysia | K15: DPE | L15: RMS | M15: SKA | O15: Snr RE | P15: ahmadzikri.norazlan@petronas.com.my | Q15: Permanent | R15: N/A | S15: 41396 | T15: =YEARFRAC(S15,$T$1) -> 13.466667 | U15: =Table9[[#This Row],[Years in PET]] -> 13.466667 | V15: P4 | X15: =($T$1-Table9[[#This Row],[Date of Appointment to Current Grade]])/365 -> 3.0565268 | Y15: 45200 | Z15: SKA | AA15: 45383 | AB15: =($T$1-Table9[[#This Row],[Date in Position]])/365 -> 2.5551569 | AC15: UPE | AE15: RDP | AF15: Average | AH15: ✅ Gas FDP ✅ PTA/RTA | AI15: • Conduct self assessment and identify critical skill and map out plan to close gap | AJ15: PTA/RTA | AK15: PTA/RTA | AL15: TP | AM15: • Next FDP to learn more on modeling | AN15: 2 | AO15: 1 | AP15: 2 | AQ15: 2 | AR15: 2 | AS15: 2 | AT15: 2 | AU15: 2 | AV15: 2 | AW15: 2 | AX15: 2 | AY15: 2 | AZ15: 2 | BA15: 2 | BB15: 1 | BC15: 1 | BD15: 0 | BE15: 1 | BF15: 1 | BG15: 0 | BH15: 1 | BI15: 0 | BJ15: 0 | BK15: 0 | BL15: =IF(AND(All!$V15="P1",All!$AE15="RDP"),Ruler!E$6,IF(AND(All!$V15="P2",All!$AE15="RDP"),Ruler!E$7,IF(AND(All!$V15="P3",All!$AE15="RDP"),Ruler!E$8,IF(AND(All!$V15="P4",All!$AE15="RDP"),Ruler!E$9,IF(AND(All!$V15="P5",All!$AE15="RDP"),Ruler!E$10,IF(AND(All!$V15="P6",All!$AE15="RDP"),Ruler!E$11,IF(AND(All!$V15="P7",All!$AE15="RDP"),Ruler!E$12,IF(AND(All!$V15="P8",All!$AE15="RDP"),Ruler!E$13,IF(AND(All!$V15="P9",All!$AE15="RDP"),Ruler!E$14,IF(AND(All!$V15="P1",All!$AE15="RMS"),Ruler!E$6,IF(AND(All!$V15="P2",All!$AE15="RMS"),Ruler!E$15,IF(AND(All!$V15="P3",All!$AE15="RMS"),Ruler!E$16,IF(AND(All!$V15="P4",All!$AE15="RMS"),Ruler!E$17,IF(AND(All!$V15="P5",All!$AE15="RMS"),Ruler!E$18,IF(AND(All!$V15="P6",All!$AE15="RMS"),Ruler!E$19,IF(AND(All!$V15="P7",All!$AE15="RMS"),Ruler!E$20,IF(AND(All!$V15="P8",All!$AE15="RMS"),Ruler!E$21,IF(AND(All!$V15="P9",All!$AE15="RMS"),Ruler!E$22,IF(AND(All!$V15="P1",All!$AE15="RSS"),Ruler!E$6,IF(AND(All!$V15="P2",All!$AE15="RSS"),Ruler!E$23,IF(AND(All!$V15="P3",All!$AE15="RSS"),Ruler!E$24,IF(AND(All!$V15="P4",All!$AE15="RSS"),Ruler!E$25,IF(AND(All!$V15="P5",All!$AE15="RSS"),Ruler!E$26,IF(AND(All!$V15="P6",All!$AE15="RSS"),Ruler!E$27,IF(AND(All!$V15="P7",All!$AE15="RSS"),Ruler!E$28,IF(AND(All!$V15="P8",All!$AE15="RSS"),Ruler!E$29,IF(AND(All!$V15="P9",All!$AE15="RSS"),Ruler!E$30,0))))))))))))))))))))))))))) -> 3 | BM15: =IF(AND(All!$V15="P1",All!$AE15="RDP"),Ruler!F$6,IF(AND(All!$V15="P2",All!$AE15="RDP"),Ruler!F$7,IF(AND(All!$V15="P3",All!$AE15="RDP"),Ruler!F$8,IF(AND(All!$V15="P4",All!$AE15="RDP"),Ruler!F$9,IF(AND(All!$V15="P5",All!$AE15="RDP"),Ruler!F$10,IF(AND(All!$V15="P6",All!$AE15="RDP"),Ruler!F$11,IF(AND(All!$V15="P7",All!$AE15="RDP"),Ruler!F$12,IF(AND(All!$V15="P8",All!$AE15="RDP"),Ruler!F$13,IF(AND(All!$V15="P9",All!$AE15="RDP"),Ruler!F$14,IF(AND(All!$V15="P1",All!$AE15="RMS"),Ruler!F$6,IF(AND(All!$V15="P2",All!$AE15="RMS"),Ruler!F$15,IF(AND(All!$V15="P3",All!$AE15="RMS"),Ruler!F$16,IF(AND(All!$V15="P4",All!$AE15="RMS"),Ruler!F$17,IF(AND(All!$V15="P5",All!$AE15="RMS"),Ruler!F$18,IF(AND(All!$V15="P6",All!$AE15="RMS"),Ruler!F$19,IF(AND(All!$V15="P7",All!$AE15="RMS"),Ruler!F$20,IF(AND(All!$V15="P8",All!$AE15="RMS"),Ruler!F$21,IF(AND(All!$V15="P9",All!$AE15="RMS"),Ruler!F$22,IF(AND(All!$V15="P1",All!$AE15="RSS"),Ruler!F$6,IF(AND(All!$V15="P2",All!$AE15="RSS"),Ruler!F$23,IF(AND(All!$V15="P3",All!$AE15="RSS"),Ruler!F$24,IF(AND(All!$V15="P4",All!$AE15="RSS"),Ruler!F$25,IF(AND(All!$V15="P5",All!$AE15="RSS"),Ruler!F$26,IF(AND(All!$V15="P6",All!$AE15="RSS"),Ruler!F$27,IF(AND(All!$V15="P7",All!$AE15="RSS"),Ruler!F$28,IF(AND(All!$V15="P8",All!$AE15="RSS"),Ruler!F$29,IF(AND(All!$V15="P9",All!$AE15="RSS"),Ruler!F$30,0))))))))))))))))))))))))))) -> 3 | BN15: =IF(AND(All!$V15="P1",All!$AE15="RDP"),Ruler!G$6,IF(AND(All!$V15="P2",All!$AE15="RDP"),Ruler!G$7,IF(AND(All!$V15="P3",All!$AE15="RDP"),Ruler!G$8,IF(AND(All!$V15="P4",All!$AE15="RDP"),Ruler!G$9,IF(AND(All!$V15="P5",All!$AE15="RDP"),Ruler!G$10,IF(AND(All!$V15="P6",All!$AE15="RDP"),Ruler!G$11,IF(AND(All!$V15="P7",All!$AE15="RDP"),Ruler!G$12,IF(AND(All!$V15="P8",All!$AE15="RDP"),Ruler!G$13,IF(AND(All!$V15="P9",All!$AE15="RDP"),Ruler!G$14,IF(AND(All!$V15="P1",All!$AE15="RMS"),Ruler!G$6,IF(AND(All!$V15="P2",All!$AE15="RMS"),Ruler!G$15,IF(AND(All!$V15="P3",All!$AE15="RMS"),Ruler!G$16,IF(AND(All!$V15="P4",All!$AE15="RMS"),Ruler!G$17,IF(AND(All!$V15="P5",All!$AE15="RMS"),Ruler!G$18,IF(AND(All!$V15="P6",All!$AE15="RMS"),Ruler!G$19,IF(AND(All!$V15="P7",All!$AE15="RMS"),Ruler!G$20,IF(AND(All!$V15="P8",All!$AE15="RMS"),Ruler!G$21,IF(AND(All!$V15="P9",All!$AE15="RMS"),Ruler!G$22,IF(AND(All!$V15="P1",All!$AE15="RSS"),Ruler!G$6,IF(AND(All!$V15="P2",All!$AE15="RSS"),Ruler!G$23,IF(AND(All!$V15="P3",All!$AE15="RSS"),Ruler!G$24,IF(AND(All!$V15="P4",All!$AE15="RSS"),Ruler!G$25,IF(AND(All!$V15="P5",All!$AE15="RSS"),Ruler!G$26,IF(AND(All!$V15="P6",All!$AE15="RSS"),Ruler!G$27,IF(AND(All!$V15="P7",All!$AE15="RSS"),Ruler!G$28,IF(AND(All!$V15="P8",All!$AE15="RSS"),Ruler!G$29,IF(AND(All!$V15="P9",All!$AE15="RSS"),Ruler!G$30,0))))))))))))))))))))))))))) -> 2 | BO15: =IF(AND(All!$V15="P1",All!$AE15="RDP"),Ruler!H$6,IF(AND(All!$V15="P2",All!$AE15="RDP"),Ruler!H$7,IF(AND(All!$V15="P3",All!$AE15="RDP"),Ruler!H$8,IF(AND(All!$V15="P4",All!$AE15="RDP"),Ruler!H$9,IF(AND(All!$V15="P5",All!$AE15="RDP"),Ruler!H$10,IF(AND(All!$V15="P6",All!$AE15="RDP"),Ruler!H$11,IF(AND(All!$V15="P7",All!$AE15="RDP"),Ruler!H$12,IF(AND(All!$V15="P8",All!$AE15="RDP"),Ruler!H$13,IF(AND(All!$V15="P9",All!$AE15="RDP"),Ruler!H$14,IF(AND(All!$V15="P1",All!$AE15="RMS"),Ruler!H$6,IF(AND(All!$V15="P2",All!$AE15="RMS"),Ruler!H$15,IF(AND(All!$V15="P3",All!$AE15="RMS"),Ruler!H$16,IF(AND(All!$V15="P4",All!$AE15="RMS"),Ruler!H$17,IF(AND(All!$V15="P5",All!$AE15="RMS"),Ruler!H$18,IF(AND(All!$V15="P6",All!$AE15="RMS"),Ruler!H$19,IF(AND(All!$V15="P7",All!$AE15="RMS"),Ruler!H$20,IF(AND(All!$V15="P8",All!$AE15="RMS"),Ruler!H$21,IF(AND(All!$V15="P9",All!$AE15="RMS"),Ruler!H$22,IF(AND(All!$V15="P1",All!$AE15="RSS"),Ruler!H$6,IF(AND(All!$V15="P2",All!$AE15="RSS"),Ruler!H$23,IF(AND(All!$V15="P3",All!$AE15="RSS"),Ruler!H$24,IF(AND(All!$V15="P4",All!$AE15="RSS"),Ruler!H$25,IF(AND(All!$V15="P5",All!$AE15="RSS"),Ruler!H$26,IF(AND(All!$V15="P6",All!$AE15="RSS"),Ruler!H$27,IF(AND(All!$V15="P7",All!$AE15="RSS"),Ruler!H$28,IF(AND(All!$V15="P8",All!$AE15="RSS"),Ruler!H$29,IF(AND(All!$V15="P9",All!$AE15="RSS"),Ruler!H$30,0))))))))))))))))))))))))))) -> 3 | BP15: =IF(AND(All!$V15="P1",All!$AE15="RDP"),Ruler!I$6,IF(AND(All!$V15="P2",All!$AE15="RDP"),Ruler!I$7,IF(AND(All!$V15="P3",All!$AE15="RDP"),Ruler!I$8,IF(AND(All!$V15="P4",All!$AE15="RDP"),Ruler!I$9,IF(AND(All!$V15="P5",All!$AE15="RDP"),Ruler!I$10,IF(AND(All!$V15="P6",All!$AE15="RDP"),Ruler!I$11,IF(AND(All!$V15="P7",All!$AE15="RDP"),Ruler!I$12,IF(AND(All!$V15="P8",All!$AE15="RDP"),Ruler!I$13,IF(AND(All!$V15="P9",All!$AE15="RDP"),Ruler!I$14,IF(AND(All!$V15="P1",All!$AE15="RMS"),Ruler!I$6,IF(AND(All!$V15="P2",All!$AE15="RMS"),Ruler!I$15,IF(AND(All!$V15="P3",All!$AE15="RMS"),Ruler!I$16,IF(AND(All!$V15="P4",All!$AE15="RMS"),Ruler!I$17,IF(AND(All!$V15="P5",All!$AE15="RMS"),Ruler!I$18,IF(AND(All!$V15="P6",All!$AE15="RMS"),Ruler!I$19,IF(AND(All!$V15="P7",All!$AE15="RMS"),Ruler!I$20,IF(AND(All!$V15="P8",All!$AE15="RMS"),Ruler!I$21,IF(AND(All!$V15="P9",All!$AE15="RMS"),Ruler!I$22,IF(AND(All!$V15="P1",All!$AE15="RSS"),Ruler!I$6,IF(AND(All!$V15="P2",All!$AE15="RSS"),Ruler!I$23,IF(AND(All!$V15="P3",All!$AE15="RSS"),Ruler!I$24,IF(AND(All!$V15="P4",All!$AE15="RSS"),Ruler!I$25,IF(AND(All!$V15="P5",All!$AE15="RSS"),Ruler!I$26,IF(AND(All!$V15="P6",All!$AE15="RSS"),Ruler!I$27,IF(AND(All!$V15="P7",All!$AE15="RSS"),Ruler!I$28,IF(AND(All!$V15="P8",All!$AE15="RSS"),Ruler!I$29,IF(AND(All!$V15="P9",All!$AE15="RSS"),Ruler!I$30,0))))))))))))))))))))))))))) -> 3 | BQ15: =IF(AND(All!$V15="P1",All!$AE15="RDP"),Ruler!J$6,IF(AND(All!$V15="P2",All!$AE15="RDP"),Ruler!J$7,IF(AND(All!$V15="P3",All!$AE15="RDP"),Ruler!J$8,IF(AND(All!$V15="P4",All!$AE15="RDP"),Ruler!J$9,IF(AND(All!$V15="P5",All!$AE15="RDP"),Ruler!J$10,IF(AND(All!$V15="P6",All!$AE15="RDP"),Ruler!J$11,IF(AND(All!$V15="P7",All!$AE15="RDP"),Ruler!J$12,IF(AND(All!$V15="P8",All!$AE15="RDP"),Ruler!J$13,IF(AND(All!$V15="P9",All!$AE15="RDP"),Ruler!J$14,IF(AND(All!$V15="P1",All!$AE15="RMS"),Ruler!J$6,IF(AND(All!$V15="P2",All!$AE15="RMS"),Ruler!J$15,IF(AND(All!$V15="P3",All!$AE15="RMS"),Ruler!J$16,IF(AND(All!$V15="P4",All!$AE15="RMS"),Ruler!J$17,IF(AND(All!$V15="P5",All!$AE15="RMS"),Ruler!J$18,IF(AND(All!$V15="P6",All!$AE15="RMS"),Ruler!J$19,IF(AND(All!$V15="P7",All!$AE15="RMS"),Ruler!J$20,IF(AND(All!$V15="P8",All!$AE15="RMS"),Ruler!J$21,IF(AND(All!$V15="P9",All!$AE15="RMS"),Ruler!J$22,IF(AND(All!$V15="P1",All!$AE15="RSS"),Ruler!J$6,IF(AND(All!$V15="P2",All!$AE15="RSS"),Ruler!J$23,IF(AND(All!$V15="P3",All!$AE15="RSS"),Ruler!J$24,IF(AND(All!$V15="P4",All!$AE15="RSS"),Ruler!J$25,IF(AND(All!$V15="P5",All!$AE15="RSS"),Ruler!J$26,IF(AND(All!$V15="P6",All!$AE15="RSS"),Ruler!J$27,IF(AND(All!$V15="P7",All!$AE15="RSS"),Ruler!J$28,IF(AND(All!$V15="P8",All!$AE15="RSS"),Ruler!J$29,IF(AND(All!$V15="P9",All!$AE15="RSS"),Ruler!J$30,0))))))))))))))))))))))))))) -> 2 | BR15: =IF(AND(All!$V15="P1",All!$AE15="RDP"),Ruler!K$6,IF(AND(All!$V15="P2",All!$AE15="RDP"),Ruler!K$7,IF(AND(All!$V15="P3",All!$AE15="RDP"),Ruler!K$8,IF(AND(All!$V15="P4",All!$AE15="RDP"),Ruler!K$9,IF(AND(All!$V15="P5",All!$AE15="RDP"),Ruler!K$10,IF(AND(All!$V15="P6",All!$AE15="RDP"),Ruler!K$11,IF(AND(All!$V15="P7",All!$AE15="RDP"),Ruler!K$12,IF(AND(All!$V15="P8",All!$AE15="RDP"),Ruler!K$13,IF(AND(All!$V15="P9",All!$AE15="RDP"),Ruler!K$14,IF(AND(All!$V15="P1",All!$AE15="RMS"),Ruler!K$6,IF(AND(All!$V15="P2",All!$AE15="RMS"),Ruler!K$15,IF(AND(All!$V15="P3",All!$AE15="RMS"),Ruler!K$16,IF(AND(All!$V15="P4",All!$AE15="RMS"),Ruler!K$17,IF(AND(All!$V15="P5",All!$AE15="RMS"),Ruler!K$18,IF(AND(All!$V15="P6",All!$AE15="RMS"),Ruler!K$19,IF(AND(All!$V15="P7",All!$AE15="RMS"),Ruler!K$20,IF(AND(All!$V15="P8",All!$AE15="RMS"),Ruler!K$21,IF(AND(All!$V15="P9",All!$AE15="RMS"),Ruler!K$22,IF(AND(All!$V15="P1",All!$AE15="RSS"),Ruler!K$6,IF(AND(All!$V15="P2",All!$AE15="RSS"),Ruler!K$23,IF(AND(All!$V15="P3",All!$AE15="RSS"),Ruler!K$24,IF(AND(All!$V15="P4",All!$AE15="RSS"),Ruler!K$25,IF(AND(All!$V15="P5",All!$AE15="RSS"),Ruler!K$26,IF(AND(All!$V15="P6",All!$AE15="RSS"),Ruler!K$27,IF(AND(All!$V15="P7",All!$AE15="RSS"),Ruler!K$28,IF(AND(All!$V15="P8",All!$AE15="RSS"),Ruler!K$29,IF(AND(All!$V15="P9",All!$AE15="RSS"),Ruler!K$30,0))))))))))))))))))))))))))) -> 3 | BS15: =IF(AND(All!$V15="P1",All!$AE15="RDP"),Ruler!L$6,IF(AND(All!$V15="P2",All!$AE15="RDP"),Ruler!L$7,IF(AND(All!$V15="P3",All!$AE15="RDP"),Ruler!L$8,IF(AND(All!$V15="P4",All!$AE15="RDP"),Ruler!L$9,IF(AND(All!$V15="P5",All!$AE15="RDP"),Ruler!L$10,IF(AND(All!$V15="P6",All!$AE15="RDP"),Ruler!L$11,IF(AND(All!$V15="P7",All!$AE15="RDP"),Ruler!L$12,IF(AND(All!$V15="P8",All!$AE15="RDP"),Ruler!L$13,IF(AND(All!$V15="P9",All!$AE15="RDP"),Ruler!L$14,IF(AND(All!$V15="P1",All!$AE15="RMS"),Ruler!L$6,IF(AND(All!$V15="P2",All!$AE15="RMS"),Ruler!L$15,IF(AND(All!$V15="P3",All!$AE15="RMS"),Ruler!L$16,IF(AND(All!$V15="P4",All!$AE15="RMS"),Ruler!L$17,IF(AND(All!$V15="P5",All!$AE15="RMS"),Ruler!L$18,IF(AND(All!$V15="P6",All!$AE15="RMS"),Ruler!L$19,IF(AND(All!$V15="P7",All!$AE15="RMS"),Ruler!L$20,IF(AND(All!$V15="P8",All!$AE15="RMS"),Ruler!L$21,IF(AND(All!$V15="P9",All!$AE15="RMS"),Ruler!L$22,IF(AND(All!$V15="P1",All!$AE15="RSS"),Ruler!L$6,IF(AND(All!$V15="P2",All!$AE15="RSS"),Ruler!L$23,IF(AND(All!$V15="P3",All!$AE15="RSS"),Ruler!L$24,IF(AND(All!$V15="P4",All!$AE15="RSS"),Ruler!L$25,IF(AND(All!$V15="P5",All!$AE15="RSS"),Ruler!L$26,IF(AND(All!$V15="P6",All!$AE15="RSS"),Ruler!L$27,IF(AND(All!$V15="P7",All!$AE15="RSS"),Ruler!L$28,IF(AND(All!$V15="P8",All!$AE15="RSS"),Ruler!L$29,IF(AND(All!$V15="P9",All!$AE15="RSS"),Ruler!L$30,0))))))))))))))))))))))))))) -> 3 | ... CI15: =IF(AND(All!$V15="P1",All!$AE15="RDP"),Ruler!AB$6,IF(AND(All!$V15="P2",All!$AE15="RDP"),Ruler!AB$7,IF(AND(All!$V15="P3",All!$AE15="RDP"),Ruler!AB$8,IF(AND(All!$V15="P4",All!$AE15="RDP"),Ruler!AB$9,IF(AND(All!$V15="P5",All!$AE15="RDP"),Ruler!AB$10,IF(AND(All!$V15="P6",All!$AE15="RDP"),Ruler!AB$11,IF(AND(All!$V15="P7",All!$AE15="RDP"),Ruler!AB$12,IF(AND(All!$V15="P8",All!$AE15="RDP"),Ruler!AB$13,IF(AND(All!$V15="P9",All!$AE15="RDP"),Ruler!AB$14,IF(AND(All!$V15="P1",All!$AE15="RMS"),Ruler!AB$6,IF(AND(All!$V15="P2",All!$AE15="RMS"),Ruler!AB$15,IF(AND(All!$V15="P3",All!$AE15="RMS"),Ruler!AB$16,IF(AND(All!$V15="P4",All!$AE15="RMS"),Ruler!AB$17,IF(AND(All!$V15="P5",All!$AE15="RMS"),Ruler!AB$18,IF(AND(All!$V15="P6",All!$AE15="RMS"),Ruler!AB$19,IF(AND(All!$V15="P7",All!$AE15="RMS"),Ruler!AB$20,IF(AND(All!$V15="P8",All!$AE15="RMS"),Ruler!AB$21,IF(AND(All!$V15="P9",All!$AE15="RMS"),Ruler!AB$22,IF(AND(All!$V15="P1",All!$AE15="RSS"),Ruler!AB$6,IF(AND(All!$V15="P2",All!$AE15="RSS"),Ruler!AB$23,IF(AND(All!$V15="P3",All!$AE15="RSS"),Ruler!AB$24,IF(AND(All!$V15="P4",All!$AE15="RSS"),Ruler!AB$25,IF(AND(All!$V15="P5",All!$AE15="RSS"),Ruler!AB$26,IF(AND(All!$V15="P6",All!$AE15="RSS"),Ruler!AB$27,IF(AND(All!$V15="P7",All!$AE15="RSS"),Ruler!AB$28,IF(AND(All!$V15="P8",All!$AE15="RSS"),Ruler!AB$29,IF(AND(All!$V15="P9",All!$AE15="RSS"),Ruler!AB$30,0))))))))))))))))))))))))))) -> 1 | CJ15: =Table9[[#This Row],[R-B1]]-Table9[[#This Row],[B1]] -> 1 | CK15: =Table9[[#This Row],[R-B2]]-Table9[[#This Row],[B2]] -> 2 | CL15: =Table9[[#This Row],[R-B3]]-Table9[[#This Row],[B3]] -> 0 | CM15: =Table9[[#This Row],[R-B4]]-Table9[[#This Row],[B4]] -> 1 | CN15: =Table9[[#This Row],[R-B5]]-Table9[[#This Row],[B5]] -> 1 | CO15: =Table9[[#This Row],[R-B6]]-Table9[[#This Row],[B6]] -> 0 | CP15: =Table9[[#This Row],[R-B7]]-Table9[[#This Row],[B7]] -> 1 | CQ15: =Table9[[#This Row],[R-B8]]-Table9[[#This Row],[B8]] -> 1 | CR15: =Table9[[#This Row],[R-B9]]-Table9[[#This Row],[B9]] -> 1 | CS15: =Table9[[#This Row],[R-B10]]-Table9[[#This Row],[B10]] -> 0 | CT15: =Table9[[#This Row],[R-B11]]-Table9[[#This Row],[B11]] -> 1 | CU15: =Table9[[#This Row],[R-B12]]-Table9[[#This Row],[B12]] -> 0 | CV15: =Table9[[#This Row],[R-K1]]-Table9[[#This Row],[K1]] -> 1 | CW15: =Table9[[#This Row],[R-K2]]-Table9[[#This Row],[K2]] -> 1 | CX15: =Table9[[#This Row],[R-K3]]-Table9[[#This Row],[K3]] -> 1 | CY15: =Table9[[#This Row],[R-K4]]-Table9[[#This Row],[K4]] -> 1 | CZ15: =Table9[[#This Row],[R-K5]]-Table9[[#This Row],[K5]] -> 2 | DA15: =Table9[[#This Row],[R-P1]]-Table9[[#This Row],[P1]] -> 1 | DB15: =Table9[[#This Row],[R-P2]]-Table9[[#This Row],[P2]] -> 1 | DC15: =Table9[[#This Row],[R-P3]]-Table9[[#This Row],[P3]] -> 2 | DD15: =Table9[[#This Row],[R-P4]]-Table9[[#This Row],[P4]] -> 0 | DE15: =Table9[[#This Row],[R-P5]]-Table9[[#This Row],[P5]] -> 2 | DF15: =Table9[[#This Row],[R-E1]]-Table9[[#This Row],[E1]] -> 1 | DG15: =Table9[[#This Row],[R-E2]]-Table9[[#This Row],[E2]] -> 1 | DH15: =COUNTIF(Table9[[#This Row],[G-B1]:[G-B12]],"<=0")/12*100 -> 33.333333 | DI15: =COUNTIF(Table9[[#This Row],[G-K1]:[G-K5]],"<=0")/5*100 -> 0 | DJ15: =COUNTIF(Table9[[#This Row],[G-P1]:[G-P5]],"<=0")/5*100 -> 20 | DK15: =COUNTIF(Table9[[#This Row],[G-E1]:[G-E2]],"<=0")/2*100 -> 0 | DL15: =IF(AE15="RDP",(COUNTIF(Table9[[#This Row],[G-B3]],"<=0")+COUNTIF(Table9[[#This Row],[G-B4]],"<=0")+COUNTIF(Table9[[#This Row],[G-B7]],"<=0")+COUNTIF(Table9[[#This Row],[G-B11]],"<=0")+COUNTIF(Table9[[#This Row],[G-K2]],"<=0"))/5*100,IF(AE15="RMS",(COUNTIF(Table9[[#This Row],[G-B4]],"<=0")+COUNTIF(Table9[[#This Row],[G-B5]],"<=0")+COUNTIF(Table9[[#This Row],[G-B10]],"<=0")+COUNTIF(Table9[[#This Row],[G-B12]],"<=0")+COUNTIF(Table9[[#This Row],[G-K2]],"<=0"))/5*100,IF(AE15="RSS",(COUNTIF(Table9[[#This Row],[G-B1]],"<=0")+COUNTIF(Table9[[#This Row],[G-B2]],"<=0")+COUNTIF(Table9[[#This Row],[G-B6]],"<=0")+COUNTIF(Table9[[#This Row],[G-B11]],"<=0")+COUNTIF(Table9[[#This Row],[G-B12]],"<=0"))/5*100,0))) -> 20 | DM15: 33 | DN15: 0 | DO15: 20 | DP15: 0 | DQ15: 20 | DR15: 0 | DS15: 0 | DT15: 0 | DU15: 0 | DV15: 0 | DW15: 0 | DX15: 0 | DY15: 0 | DZ15: 0 | EA15: 0 | EE15: UPE map to RDP ruler
